Workbook

Sheet Outputs
B1: знак | C1: Контрольные показатели | D1: Тип показателя | E1: Наименование | F1: Источник/ Формула для расчета | G1: Ед. измерения | H1: 2018 | I1: 2019 | J1: 2020 | K1: 2021 | L1: 2022 | M1: 2023 | N1: 2024 | O1: 2025 | P1: 2026 | Q1: 2027 | R1: 2028 | S1: 2029 | T1: 2030 | U1: 2031 | V1: 2032 | W1: 2033 | X1: 2034 | Y1: 2035 | Z1: 2036 | AA1: 2037 | AB1: 2038 | AC1: 2039 | AD1: 2040
B2: + | C2: Финансовый показатель | D2: Общий (обязательный) | E2: Выручка | F2: Отчет о финансовых результатах | G2: USD млн | H2: ='P&L'!L8 -> 3931.847 | I2: ='P&L'!M8 -> 3283.514 | J2: ='P&L'!N8 -> 2649.963 | K2: ='P&L'!O8 -> 4414.559 | L2: ='P&L'!P8 -> 4311.188 | M2: ='P&L'!Q8 -> 3168.5897 | N2: ='P&L'!R8 -> 4407.8544 | O2: ='P&L'!S8 -> 4887.5047 | ... V2: ='P&L'!Z8 -> 4808.972
B3: + | C3: Расчетный показатель | D3: Общий (обязательный) | E3: Операционные расходы (без амортизации) | F3: Предзаполненная формула | G3: =$G$2 -> USD млн | H3: =H2-H6 -> 2784.9191 | I3: =I2-I6 -> 2747.7192 | J3: =J2-J6 -> 2325.5461 | K3: =K2-K6 -> 3241.7675 | L3: =L2-L6 -> 3369.1625 | M3: =M2-M6 -> 2568.8677 | N3: =N2-N6 -> 3458.3718 | O3: =O2-O6 -> 3803.5377 | ... AD3: =AD2-AD6 -> 0
C4: Расчетный показатель | D4: Общий (обязательный) | E4: Коммерческие и управленческие расходы | F4: Отчет о финансовых результатах | G4: =$G$2 -> USD млн
B5: + | C5: Финансовый показатель | D5: Общий (обязательный) | E5: Прибыль от реализации | F5: Отчет о финансовых результатах | G5: =$G$2 -> USD млн
C6: Расчетный показатель | D6: Общий (обязательный) | E6: EBITDA | F6: см. лист формулы | G6: =$G$2 -> USD млн | H6: ='P&L'!L17 -> 1146.9279 | I6: ='P&L'!M17 -> 535.79477 | J6: ='P&L'!N17 -> 324.41686 | K6: ='P&L'!O17 -> 1172.7915 | L6: ='P&L'!P17 -> 942.02546 | M6: ='P&L'!Q17 -> 599.72192 | N6: ='P&L'!R17 -> 949.48262 | O6: ='P&L'!S17 -> 1083.967 | ... V6: ='P&L'!Z17 -> 1007.8291
C7: Расчетный показатель | D7: Общий (обязательный) | E7: Рентабельность EBITDA | F7: Предзаполненная формула | G7: % | H7: =IFERROR(H6/H2,"") -> 0.29170206 | I7: =IFERROR(I6/I2,"") -> 0.16317725 | J7: =IFERROR(J6/J2,"") -> 0.12242317 | K7: =IFERROR(K6/K2,"") -> 0.26566448 | L7: =IFERROR(L6/L2,"") -> 0.21850716 | M7: =IFERROR(M6/M2,"") -> 0.18927093 | N7: =IFERROR(N6/N2,"") -> 0.21540698 | O7: =IFERROR(O6/O2,"") -> 0.22178332 | ... AD7: =IFERROR(AD6/AD2,"")
B8: + | C8: Финансовый показатель | D8: Общий (обязательный) | E8: Амортизация | F8: Приложение к Бухгалтерскому балансу; информация от клиента (заполняется абсолютное значение со знаком +) | G8: =$G$2 -> USD млн | H8: ='P&L'!L20 -> 245.303 | I8: ='P&L'!M20 -> 344.127 | J8: ='P&L'!N20 -> 357.129 | K8: ='P&L'!O20 -> 363.084 | L8: ='P&L'!P20 -> 372.42 | M8: ='P&L'!Q20 -> 358.28537 | N8: ='P&L'!R20 -> 378.29411 | O8: ='P&L'!S20 -> 361.26797 | ... V8: ='P&L'!Z20 -> 284.61719
C9: Финансовый показатель | D9: Общий (обязательный) | E9: Прочие доходы и расходы после EBIT (включая налог на прибыль) | F9: Предзаполненная формула | G9: =$G$2 -> USD млн | H9: =H6-H10-H8 -> 243.641 | I9: =I6-I10-I8 -> 75.302 | J9: =J6-J10-J8 -> 92.615 | K9: =K6-K10-K8 -> 253.797 | L9: =L6-L10-L8 -> 107.317 | M9: =M6-M10-M8 -> 174.70265 | N9: =N6-N10-N8 -> 230.8744 | O9: =O6-O10-O8 -> 245.29011 | ... AD9: =AD6-AD10-AD8 -> 0
C10: Финансовый показатель | D10: Общий (обязательный) | E10: Чистая прибыль | F10: Отчет о финансовых результатах | G10: =$G$2 -> USD млн | H10: ='P&L'!L39 -> 657.98389 | I10: ='P&L'!M39 -> 116.36577 | J10: ='P&L'!N39 -> -125.32714 | K10: ='P&L'!O39 -> 555.91053 | L10: ='P&L'!P39 -> 462.28846 | M10: ='P&L'!Q39 -> 66.733909 | N10: ='P&L'!R39 -> 340.31411 | O10: ='P&L'!S39 -> 477.40894 | ... V10: ='P&L'!Z39 -> 547.37267
C11: Расчетный показатель | D11: Общий (обязательный) | E11: Рентабельность чистой прибыли | F11: Предзаполненная формула | G11: % | H11: =IFERROR(H10/H2,"") -> 0.16734728 | I11: =IFERROR(I10/I2,"") -> 0.035439402 | J11: =IFERROR(J10/J2,"") -> -0.04729392 | K11: =IFERROR(K10/K2,"") -> 0.12592663 | L11: =IFERROR(L10/L2,"") -> 0.10722995 | M11: =IFERROR(M10/M2,"") -> 0.021061076 | N11: =IFERROR(N10/N2,"") -> 0.077206296 | O11: =IFERROR(O10/O2,"") -> 0.097679486 | ... AD11: =IFERROR(AD10/AD2,"")
B13: + | C13: Финансовый показатель | D13: Общий (обязательный) | E13: Остаток денежных средств на конец периода | G13: =$G$2 -> USD млн | H13: =CFS!L32 -> 256.077 | I13: =CFS!M32 -> 416.763 | J13: =CFS!N32 -> 833.841 | K13: =CFS!O32 -> 932.069 | L13: =CFS!P32 -> 857.747 | M13: =CFS!Q32 -> 589.22299 | N13: =CFS!R32 -> 552.97392 | O13: =CFS!S32 -> 966.62759 | ... V13: =CFS!Z32 -> 2472.0674
C14: Финансовый показатель | D14: Общий (обязательный) | E14: Чистый денежный поток за период (NCF) | F14: Предзаполненная формула | G14: =$G$2 -> USD млн | H14: =H15+H16+H17 -> 264.549 | I14: =I15+I16+I17 -> -60.232 | J14: =J15+J16+J17 -> -125.269 | K14: =K15+K16+K17 -> 388.193 | L14: =L15+L16+L17 -> 113.427 | M14: =M15+M16+M17 -> -268.52401 | N14: =N15+N16+N17 -> -36.249069 | O14: =O15+O16+O17 -> 413.65367 | ... AD14: =AD15+AD16+AD17 -> 0
C15: Финансовый показатель | D15: Общий (обязательный) | E15: Денежные потоки от текущих операций (CFO) | F15: Отчет о движении денежных средств | G15: =$G$2 -> USD млн | H15: =CFS!L12 -> 980.206 | I15: =CFS!M12 -> 515.431 | J15: =CFS!N12 -> 461.082 | K15: =CFS!O12 -> 994.369 | L15: =CFS!P12 -> 987.349 | M15: =CFS!Q12 -> 605.80242 | N15: =CFS!R12 -> 778.40913 | O15: =CFS!S12 -> 939.82855 | ... V15: =CFS!Z12 -> 883.18181
C16: Финансовый показатель | D16: Общий (обязательный) | E16: Денежные потоки от инвестиционных операций (CFI) | F16: Отчет о движении денежных средств | G16: =$G$2 -> USD млн | H16: =CFS!L18 -> -306.351 | I16: =CFS!M18 -> -250.692 | J16: =CFS!N18 -> -278.063 | K16: =CFS!O18 -> -253.048 | L16: =CFS!P18 -> -553.137 | M16: =CFS!Q18 -> -590.34062 | N16: =CFS!R18 -> -180.83022 | O16: =CFS!S18 -> -184.55384 | ... V16: =CFS!Z18 -> -212.11736
C17: Финансовый показатель | D17: Общий (обязательный) | E17: Денежные потоки от финансовых операций (CFF) | F17: Отчет о движении денежных средств | G17: =$G$2 -> USD млн | H17: =CFS!L21+CFS!L22+CFS!L23 -> -409.306 | I17: =CFS!M21+CFS!M22+CFS!M23 -> -324.971 | J17: =CFS!N21+CFS!N22+CFS!N23 -> -308.288 | K17: =CFS!O21+CFS!O22+CFS!O23 -> -353.128 | L17: =CFS!P21+CFS!P22+CFS!P23 -> -320.785 | M17: =CFS!Q21+CFS!Q22+CFS!Q23 -> -283.98581 | N17: =CFS!R21+CFS!R22+CFS!R23 -> -633.82798 | O17: =CFS!S21+CFS!S22+CFS!S23 -> -341.62104 | ... V17: =CFS!Z21+CFS!Z22+CFS!Z23 -> -257.25073
C18: Расчетный показатель | D18: Общий (обязательный) | E18: Свободный денежный поток (FCFF) | F18: Предзаполненная формула (см. лист формулы) | G18: =$G$2 -> USD млн | H18: =H15-H21+H35*(1-INDIRECT("Inputs!AA34")) -> 807.7364 | I18: =I15-I21+I35*(1-INDIRECT("Inputs!AA34")) -> 399.1904 | J18: =J15-J21+J35*(1-INDIRECT("Inputs!AA34")) -> 464.656 | K18: =K15-K21+K35*(1-INDIRECT("Inputs!AA34")) -> 1022.9312 | L18: =L15-L21+L35*(1-INDIRECT("Inputs!AA34")) -> 971.1008 | M18: =M15-M21+M35*(1-INDIRECT("Inputs!AA34")) -> 583.04046 | N18: =N15-N21+N35*(1-INDIRECT("Inputs!AA34")) -> 720.14807 | O18: =O15-O21+O35*(1-INDIRECT("Inputs!AA34")) -> 864.34735 | ... V18: =V15-V21+V35*(1-INDIRECT("Inputs!AA34")) -> 711.8033 | W18: =W15-W21+W35*(1-INDIRECT("Inputs!AT34")) -> 0 | X18: =X15-X21+X35*(1-INDIRECT("Inputs!AT34")) -> 0 | Y18: =Y15-Y21+Y35*(1-INDIRECT("Inputs!AT34")) -> 0 | Z18: =Z15-Z21+Z35*(1-INDIRECT("Inputs!AT34")) -> 0 | AA18: =AA15-AA21+AA35*(1-INDIRECT("Inputs!AT34")) -> 0 | AB18: =AB15-AB21+AB35*(1-INDIRECT("Inputs!AT34")) -> 0 | AC18: =AC15-AC21+AC35*(1-INDIRECT("Inputs!AT34")) -> 0 | AD18: =AD15-AD21+AD35*(1-INDIRECT("Inputs!AT34")) -> 0
C19: Расчетный показатель | D19: Общий (обязательный) | E19: Денежные средства, доступные для обслуживания долга (CFADS) | F19: Предзаполненная формула | G19: =$G$2 -> USD млн | H19: =H15+H35-H23 -> 825.738 | I19: =I15+I35-I23 -> 422.247 | J19: =J15+J35-J23 -> 497.746 | K19: =K15+K35-K23 -> 1055.943 | L19: =L15+L35-L23 -> 1003.464 | M19: =M15+M35-M23 -> 614.93513 | N19: =N15+N35-N23 -> 750.79036 | O19: =O15+O35-O23 -> 891.61551 | ... AD19: =AD15+AD35-AD23 -> 0
B21: + | C21: Финансовый показатель | D21: Общий (обязательный) | E21: Сумма капитальных затрат (CAPEX) | F21: Отчет о движении денежных средств; информация от клиента | G21: =$G$2 -> USD млн | H21: =H22+H23 -> 244.476 | I21: =I22+I23 -> 208.467 | J21: =J22+J23 -> 128.786 | K21: =K22+K23 -> 103.485 | L21: =L22+L23 -> 145.701 | M21: =M22+M23 -> 150.34062 | N21: =N22+N23 -> 180.83022 | O21: =O22+O23 -> 184.55384 | ... AD21: =AD22+AD23 -> 0
B22: + | C22: Финансовый показатель | D22: Общий (заполняется при наличии информации) | E22: Капитальные затраты на развитие (Development CAPEX) | F22: Информация от клиента | G22: =$G$2 -> USD млн
B23: + | C23: Финансовый показатель | D23: Общий (обязательный) | E23: Капитальные затраты на поддержание (Maintenance CAPEX) | F23: Информация от клиента; экспертнообоснованный КП уровень, согласованный с АР | G23: =$G$2 -> USD млн | H23: =-CFS!L15 -> 244.476 | I23: =-CFS!M15 -> 208.467 | J23: =-CFS!N15 -> 128.786 | K23: =-CFS!O15 -> 103.485 | L23: =-CFS!P15 -> 145.701 | M23: =-CFS!Q15 -> 150.34062 | N23: =-CFS!R15 -> 180.83022 | O23: =-CFS!S15 -> 184.55384 | ... V23: =-CFS!Z15 -> 212.11736
B25: + | C25: Финансовый показатель | D25: Общий (обязательный) | E25: Долг (Debt) | F25: см. лист формулы | G25: =$G$2 -> USD млн | H25: =PRINT!L25 -> 1458.286 | I25: =PRINT!M25 -> 2487.358 | J25: =PRINT!N25 -> 3085.606 | K25: =PRINT!O25 -> 2875.293 | L25: =PRINT!P25 -> 3021.676 | M25: =PRINT!Q25 -> 2913.847 | N25: =PRINT!R25 -> 2518.309 | O25: =PRINT!S25 -> 2432.381 | ... V25: =PRINT!Z25 -> 489.579
B26: + | C26: Финансовый показатель | D26: Общий (обязательный) | E26: Долг без учета задолженности по лизингу | F26: Информация по клиенту | G26: =$G$2 -> USD млн
B27: + | C27: Финансовый показатель | D27: Общий (обязательный) | E27: Долг с учетом забалансовых обязательств | F27: см. лист формулы | G27: =$G$2 -> USD млн
C28: Расчетный показатель | D28: Общий (обязательный) | E28: Чистый долг (Net Debt) | F28: см. лист формулы | G28: =$G$2 -> USD млн | H28: =PRINT!L28 -> 1202.209 | I28: =PRINT!M28 -> 2070.595 | J28: =PRINT!N28 -> 2251.765 | K28: =PRINT!O28 -> 1943.224 | L28: =PRINT!P28 -> 2163.929 | M28: =PRINT!Q28 -> 2324.624 | N28: =PRINT!R28 -> 1965.3351 | O28: =PRINT!S28 -> 1465.7534 | ... V28: =PRINT!Z28 -> -1982.4884
C29: Расчетный показатель | D29: Общий (обязательный) | E29: Долгосрочные кредиты и займы | F29: Бухгалтерский баланс | G29: =$G$2 -> USD млн
C30: Расчетный показатель | D30: Общий (обязательный) | E30: Краткосрочные кредиты и займы | F30: Бухгалтерский баланс | G30: =$G$2 -> USD млн
C31: Расчетный показатель | D31: Общий (обязательный) | E31: Обязательства по финансовому лизингу | F31: см. лист формулы | G31: =$G$2 -> USD млн
B32: + | C32: Финансовый показатель | D32: Общий (обязательный) | E32: Балансирующий долг | F32: Информация по клиенту | G32: =$G$2 -> USD млн
B33: + | C33: Расчетный показатель | D33: Общий (обязательный) | E33: Обслуживание долга (Debt Service) | F33: Предзаполненная формула | G33: =$G$2 -> USD млн | H33: =H34+H35+H38 -> 90.008 | I33: =I34+I35+I38 -> 115.283 | J33: =J34+J35+J38 -> 165.45 | K33: =K34+K35+K38 -> 165.059 | L33: =L34+L35+L38 -> 161.816 | M33: =M34+M35+M38 -> 159.47333 | N33: =N34+N35+N38 -> 153.21145 | O33: =O34+O35+O38 -> 136.3408 | ... AD33: =AD34+AD35+AD38 -> 0
B34: + | C34: Расчетный показатель | D34: Общий (обязательный) | E34: Погашение основного долга | F34: Отчет о движении денежных средств; информация, полученная от клиента | G34: =$G$2 -> USD млн
B35: + | C35: Финансовый показатель | D35: Общий (обязательный) | E35: Платежи процентов по долговым обязательствам | F35: Отчет о движении денежных средств; информация, полученная от клиента | G35: =$G$2 -> USD млн | H35: =-CFS!L22 -> 90.008 | I35: =-CFS!M22 -> 115.283 | J35: =-CFS!N22 -> 165.45 | K35: =-CFS!O22 -> 165.059 | L35: =-CFS!P22 -> 161.816 | M35: =-CFS!Q22 -> 159.47333 | N35: =-CFS!R22 -> 153.21145 | O35: =-CFS!S22 -> 136.3408 | ... V35: =-CFS!Z22 -> 50.92356
B36: + | C36: Финансовый показатель | D36: Общий (обязательный) | E36: Начисленные проценты по долговым обязательствам | F36: Информация по клиенту | G36: =$G$2 -> USD млн
B37: + | C37: Финансовый показатель | D37: Общий (обязательный) | E37: Капитализированные проценты | F37: Информация по клиенту | G37: =$G$2 -> USD млн
B38: + | C38: Финансовый показатель | D38: Общий (обязательный) | E38: Лизинговые платежи (вкл. основной долг в их составе) | F38: Предзаполненная формула | G38: =$G$2 -> USD млн | H38: =H39+H40 -> 0 | I38: =I39+I40 -> 0 | J38: =J39+J40 -> 0 | K38: =K39+K40 -> 0 | L38: =L39+L40 -> 0 | M38: =M39+M40 -> 0 | N38: =N39+N40 -> 0 | O38: =O39+O40 -> 0 | ... AD38: =AD39+AD40 -> 0
B39: + | C39: Финансовый показатель | D39: Общий (обязательный) | E39: Лизинговые платежи | F39: Отчет о финансовых результатах; информация, полученная от клиента | G39: =$G$2 -> USD млн
B40: + | C40: Финансовый показатель | D40: Общий (обязательный) | E40: Платежи процентов по лизингу | F40: Отчет о финансовых результатах; информация, полученная от клиента | G40: =$G$2 -> USD млн
C41: Финансовый показатель | D41: Общий (обязательный) | E41: Эффект от переоценки валютного долга | F41: Информация по клиенту | G41: =$G$2 -> USD млн
B42: + | C42: Финансовый показатель | D42: Общий (обязательный) | E42: Привлечение денежных средств (итого) | F42: = Кредиты без подтверждения финансирования + кредиты с подтверждением финансирования + прочие привлечения Отчет о движении денежных средств, информация, полученная от клиента | G42: =$G$2 -> USD млн
C43: Финансовый показатель | D43: Общий (обязательный) | E43: Оборотный капитал на конец периода | F43: = Оборотные (текущие) активы (код 1600) – Оборотные (текущие) пассивы (код 1700), Бухгалтерский баланс | G43: =$G$2 -> USD млн
B44: + | C44: Финансовый показатель | D44: Общий (обязательный) | E44: Остаточная стоимость ОС на конец периода | F44: Бухгалтерский баланс | G44: =$G$2 -> USD млн
B45: + | C45: Финансовый показатель | D45: Общий (обязательный) | E45: Финансовые вложения | F45: Бухгалтерский баланс | G45: =$G$2 -> USD млн
B46: + | C46: Финансовый показатель | D46: Общий (обязательный) | E46: Нематериальные активы | F46: Бухгалтерский баланс | G46: =$G$2 -> USD млн
B47: + | C47: Финансовый показатель | D47: Общий (обязательный) | E47: Сумма Актива бухгалтерского баланса | F47: Бухгалтерский баланс | G47: =$G$2 -> USD млн
B48: + | C48: Финансовый показатель | D48: Общий (обязательный) | E48: Итого долгосрочные обязательства | F48: Бухгалтерский баланс | G48: =$G$2 -> USD млн
B49: + | C49: Финансовый показатель | D49: Общий (обязательный) | E49: Итого краткосрочные обязательства | F49: Бухгалтерский баланс | G49: =$G$2 -> USD млн
B50: + | C50: Финансовый показатель | D50: Общий (обязательный) | E50: Капитал и резервы | F50: Бухгалтерский баланс | G50: =$G$2 -> USD млн
B51: + | C51: Финансовый показатель | D51: Общий (обязательный) | E51: Оборотные активы | F51: Бухгалтерский баланс | G51: =$G$2 -> USD млн
B52: + | C52: Финансовый показатель | D52: Общий (обязательный) | E52: Прочие операционные доходы и расходы | F52: Отчет о финансовых результатах | G52: =$G$2 -> USD млн
B53: + | C53: Финансовый показатель | D53: Общий (обязательный) | E53: Прочие неоперационные доходы и расходы | F53: Отчет о финансовых результатах | G53: =$G$2 -> USD млн
B56: + | C56: Финансовый показатель | D56: Общий (обязательный) | E56: Долг перед Сбербанком на конец (Sberbank Debt) | F56: Информация по клиенту | G56: =$G$2 -> USD млн
B57: + | C57: Финансовый показатель | D57: Общий (обязательный) | E57: Долг перед Сбербанком без учета задолженности по лизингу | F57: Информация по клиенту | G57: =$G$2 -> USD млн
B58: + | C58: Финансовый показатель | D58: Общий (обязательный) | E58: Обслуживание обязательств перед Сбербанком (Sberbank Debt Service) | F58: Предзаполненная формула | G58: =$G$2 -> USD млн | H58: =H59+H60+H63 -> 0 | I58: =I59+I60+I63 -> 0 | J58: =J59+J60+J63 -> 0 | K58: =K59+K60+K63 -> 0 | L58: =L59+L60+L63 -> 0 | M58: =M59+M60+M63 -> 0 | N58: =N59+N60+N63 -> 0 | O58: =O59+O60+O63 -> 0 | ... AD58: =AD59+AD60+AD63 -> 0
B59: + | C59: Финансовый показатель | D59: Общий (обязательный) | E59: Погашение кредитов в Сбербанке за период (Sberbank debt repayment) | F59: Информация по клиенту | G59: =$G$2 -> USD млн
B60: + | C60: Финансовый показатель | D60: Общий (обязательный) | E60: Процентные и прочие платежи (Sberbank interest/other payments) | F60: Информация по клиенту | G60: =$G$2 -> USD млн
B61: + | C61: Финансовый показатель | D61: Общий (обязательный) | E61: Начисленные проценты по долговым обязательствам перед Сбербанком | F61: Информация по клиенту | G61: =$G$2 -> USD млн
B62: + | C62: Финансовый показатель | D62: Общий (обязательный) | E62: Капитализированные проценты по кредитам Сбербанка | F62: Информация по клиенту | G62: =$G$2 -> USD млн
B63: + | C63: Финансовый показатель | D63: Общий (обязательный) | E63: Лизинговые платежи Сбербанку (Sberbank leasing payments) | F63: Информация по клиенту | G63: =$G$2 -> USD млн | H63: =H64+H65 -> 0 | I63: =I64+I65 -> 0 | J63: =J64+J65 -> 0 | K63: =K64+K65 -> 0 | L63: =L64+L65 -> 0 | M63: =M64+M65 -> 0 | N63: =N64+N65 -> 0 | O63: =O64+O65 -> 0 | ... AD63: =AD64+AD65 -> 0
B64: + | C64: Финансовый показатель | D64: Общий (обязательный) | E64: Лизинговые платежи Сбербанку | F64: Информация по клиенту | G64: =$G$2 -> USD млн
B65: + | C65: Финансовый показатель | D65: Общий (обязательный) | E65: Платежи процентов по лизингу Сбербанку | F65: Информация по клиенту | G65: =$G$2 -> USD млн
C66: Финансовый показатель | D66: Общий (обязательный) | E66: Эффект от переоценки валютного долга перед Сбербанком | F66: Информация по клиенту | G66: =$G$2 -> USD млн
B67: + | C67: Финансовый показатель | D67: Общий (обязательный) | E67: Привлечение в Сбербанке за период (Sberbank debt attraction) | F67: Информация по клиенту | G67: =$G$2 -> USD млн
C69: Коэффициент | D69: Общий (обязательный) | E69: Debt/EBITDA | F69: Предзаполненная формула | G69: количество раз, с округлением до 100-х | H69: =IFERROR(H25/H6,"") -> 1.2714714 | I69: =IFERROR(I25/I6,"") -> 4.6423708 | J69: =IFERROR(J25/J6,"") -> 9.511238 | K69: =IFERROR(K25/K6,"") -> 2.4516659 | L69: =IFERROR(L25/L6,"") -> 3.2076373 | M69: =IFERROR(M25/M6,"") -> 4.8586635 | N69: =IFERROR(N25/N6,"") -> 2.652296 | O69: =IFERROR(O25/O6,"") -> 2.2439622 | ... AD69: =IFERROR(AD25/AD6,"")
C70: Коэффициент | D70: Общий (обязательный) | E70: Net Debt/EBITDA | F70: Предзаполненная формула | G70: количество раз, с округлением до 100-х | H70: =IFERROR(H28/H6,"") -> 1.0481993 | I70: =IFERROR(I28/I6,"") -> 3.86453 | J70: =IFERROR(J28/J6,"") -> 6.9409616 | K70: =IFERROR(K28/K6,"") -> 1.6569219 | L70: =IFERROR(L28/L6,"") -> 2.2971025 | M70: =IFERROR(M28/M6,"") -> 3.8761698 | N70: =IFERROR(N28/N6,"") -> 2.069901 | O70: =IFERROR(O28/O6,"") -> 1.3522122 | ... AD70: =IFERROR(AD28/AD6,"")
C71: Расчетный показатель | D71: Общий (обязательный) | E71: Долг с учетом забалансовых обязательств/EBITDA | F71: Предзаполненная формула | G71: количество раз, с округлением до 100-х | H71: =IFERROR(H27/H6,"") -> 0 | I71: =IFERROR(I27/I6,"") -> 0 | J71: =IFERROR(J27/J6,"") -> 0 | K71: =IFERROR(K27/K6,"") -> 0 | L71: =IFERROR(L27/L6,"") -> 0 | M71: =IFERROR(M27/M6,"") -> 0 | N71: =IFERROR(N27/N6,"") -> 0 | O71: =IFERROR(O27/O6,"") -> 0 | ... AD71: =IFERROR(AD27/AD6,"")
C72: Расчетный показатель | D72: Общий (обязательный) | E72: Коэффициент покрытия процентов в i-ом периоде (ICR) | F72: Предзаполненная формула | G72: количество раз, с округлением до 100-х | H72: =IFERROR(H6/H73,"") -> 12.742511 | I72: =IFERROR(I6/I73,"") -> 4.6476477 | J72: =IFERROR(J6/J73,"") -> 1.9608151 | K72: =IFERROR(K6/K73,"") -> 7.1052868 | L72: =IFERROR(L6/L73,"") -> 5.8215842 | M72: =IFERROR(M6/M73,"") -> 3.7606408 | N72: =IFERROR(N6/N73,"") -> 6.197204 | O72: =IFERROR(O6/O73,"") -> 7.9504229 | ... AD72: =IFERROR(AD6/AD73,"")
B73: + | C73: Финансовый показатель | D73: Общий (обязательный) | E73: Проценты к уплате | F73: Отчет о финансовых результатах; информация, полученная от клиента | G73: =$G$2 -> USD млн | H73: =H35 -> 90.008 | I73: =I35 -> 115.283 | J73: =J35 -> 165.45 | K73: =K35 -> 165.059 | L73: =L35 -> 161.816 | M73: =M35 -> 159.47333 | N73: =N35 -> 153.21145 | O73: =O35 -> 136.3408 | ... V73: =V35 -> 50.92356
C74: Расчетный показатель | D74: Общий (обязательный) | E74: Коэффициент покрытия процентов в i-ом периоде (ISCR) | F74: Предзаполненная формула | G74: количество раз, с округлением до 100-х | H74: =IFERROR((H15+H35-H23)/H35,"") -> 9.1740512 | I74: =IFERROR((I15+I35-I23)/I35,"") -> 3.6626996 | J74: =IFERROR((J15+J35-J23)/J35,"") -> 3.0084376 | K74: =IFERROR((K15+K35-K23)/K35,"") -> 6.397367 | L74: =IFERROR((L15+L35-L23)/L35,"") -> 6.2012656 | M74: =IFERROR((M15+M35-M23)/M35,"") -> 3.8560374 | N74: =IFERROR((N15+N35-N23)/N35,"") -> 4.9003541 | O74: =IFERROR((O15+O35-O23)/O35,"") -> 6.5396088 | ... AD74: =IFERROR((AD15+AD35-AD23)/AD35,"")
C75: Расчетный показатель | D75: Общий (обязательный) | E75: Коэффициент покрытия долга в i-ом периоде (DSCR) | F75: Предзаполненная формула (см. лист формулы) | G75: количество раз, с округлением до 100-х | H75: =IFERROR((H15+H35-H21)/H33,"") -> 9.1740512 | I75: =IFERROR((I15+I35-I21)/I33,"") -> 3.6626996 | J75: =IFERROR((J15+J35-J21)/J33,"") -> 3.0084376 | K75: =IFERROR((K15+K35-K21)/K33,"") -> 6.397367 | L75: =IFERROR((L15+L35-L21)/L33,"") -> 6.2012656 | M75: =IFERROR((M15+M35-M21)/M33,"") -> 3.8560374 | N75: =IFERROR((N15+N35-N21)/N33,"") -> 4.9003541 | O75: =IFERROR((O15+O35-O21)/O33,"") -> 6.5396088 | ... AD75: =IFERROR((AD15+AD35-AD21)/AD33,"")
C76: Расчетный показатель | D76: Общий (обязательный) | E76: Коэффициент покрытия долга с учетом привлечения долга в i-ом периоде (DSCR с долгом) | F76: Предзаполненная формула (см. лист формулы) | G76: количество раз, с округлением до 100-х | H76: =IFERROR((H15+H35-H21+H42)/H33,"") -> 9.1740512 | I76: =IFERROR((I15+I35-I21+I42)/I33,"") -> 3.6626996 | J76: =IFERROR((J15+J35-J21+J42)/J33,"") -> 3.0084376 | K76: =IFERROR((K15+K35-K21+K42)/K33,"") -> 6.397367 | L76: =IFERROR((L15+L35-L21+L42)/L33,"") -> 6.2012656 | M76: =IFERROR((M15+M35-M21+M42)/M33,"") -> 3.8560374 | N76: =IFERROR((N15+N35-N21+N42)/N33,"") -> 4.9003541 | O76: =IFERROR((O15+O35-O21+O42)/O33,"") -> 6.5396088 | ... AD76: =IFERROR((AD15+AD35-AD21+AD42)/AD33,"")
C77: Расчетный показатель | D77: Общий (обязательный) | E77: Свободный денежный поток за вычетом финансовых расходов на погашение и обслуживание долга | F77: Предзаполненная формула | G77: =$G$2 -> USD млн | H77: =H18-H33 -> 717.7284 | I77: =I18-I33 -> 283.9074 | J77: =J18-J33 -> 299.206 | K77: =K18-K33 -> 857.8722 | L77: =L18-L33 -> 809.2848 | M77: =M18-M33 -> 423.56713 | N77: =N18-N33 -> 566.93662 | O77: =O18-O33 -> 728.00655 | ... AD77: =AD18-AD33 -> 0
C78: Расчетный показатель | D78: Общий (обязательный) | E78: Срок до полного погашения | F78: Предзаполненная формула | G78: количество периодов, с округлением до 10-х | H78: =IFERROR(H28/(H15-H23),"") -> 1.6340356 | I78: =IFERROR(I28/(I15-I23),"") -> 6.7454001 | J78: =IFERROR(J28/(J15-J23),"") -> 6.7763831 | K78: =IFERROR(K28/(K15-K23),"") -> 2.1812312 | L78: =IFERROR(L28/(L15-L23),"") -> 2.5710618 | M78: =IFERROR(M28/(M15-M23),"") -> 5.1038836 | N78: =IFERROR(N28/(N15-N23),"") -> 3.2888294 | O78: =IFERROR(O28/(O15-O23),"") -> 1.9406891 | ... AD78: =IFERROR(AD28/(AD15-AD23),"")
C80: Расчетный показатель | D80: Общий (обязательный) | E80: Выручка (LTM) | F80: Предзаполненная формула | G80: =$G$2 -> USD млн | H80: =H2 -> 3931.847 | I80: =I2 -> 3283.514 | J80: =J2 -> 2649.963 | K80: =K2 -> 4414.559 | L80: =L2 -> 4311.188 | M80: =M2 -> 3168.5897 | N80: =N2 -> 4407.8544 | O80: =O2 -> 4887.5047 | ... AD80: =AD2 -> 0
C81: Расчетный показатель | D81: Общий (обязательный) | E81: EBITDA (LTM) | F81: Предзаполненная формула | G81: =$G$2 -> USD млн | H81: =H6 -> 1146.9279 | I81: =I6 -> 535.79477 | J81: =J6 -> 324.41686 | K81: =K6 -> 1172.7915 | L81: =L6 -> 942.02546 | M81: =M6 -> 599.72192 | N81: =N6 -> 949.48262 | O81: =O6 -> 1083.967 | ... AD81: =AD6 -> 0
C82: Расчетный показатель | D82: Общий (обязательный) | E82: Рентабельность EBITDA (LTM) | F82: Предзаполненная формула | G82: % | H82: =H7 -> 0.29170206 | I82: =I7 -> 0.16317725 | J82: =J7 -> 0.12242317 | K82: =K7 -> 0.26566448 | L82: =L7 -> 0.21850716 | M82: =M7 -> 0.18927093 | N82: =N7 -> 0.21540698 | O82: =O7 -> 0.22178332 | ... AD82: =AD7
C83: Расчетный показатель | D83: Общий (обязательный) | E83: Debt/EBITDA (LTM) | F83: Предзаполненная формула | G83: количество раз, с округлением до 100-х | H83: =IFERROR(ROUND(H25,0)/ROUND(H81,0),"") -> 1.2711421 | I83: =IFERROR(ROUND(I25,0)/ROUND(I81,0),"") -> 4.6399254 | J83: =IFERROR(ROUND(J25,0)/ROUND(J81,0),"") -> 9.5246914 | K83: =IFERROR(ROUND(K25,0)/ROUND(K81,0),"") -> 2.4509804 | L83: =IFERROR(ROUND(L25,0)/ROUND(L81,0),"") -> 3.2080679 | M83: =IFERROR(ROUND(M25,0)/ROUND(M81,0),"") -> 4.8566667 | N83: =IFERROR(ROUND(N25,0)/ROUND(N81,0),"") -> 2.6533193 | O83: =IFERROR(ROUND(O25,0)/ROUND(O81,0),"") -> 2.2435424 | ... AD83: =IFERROR(ROUND(AD25,0)/ROUND(AD81,0),"")
C84: Расчетный показатель | D84: Общий (обязательный) | E84: Долг/Выручка (LTM) | F84: Предзаполненная формула | G84: количество раз, с округлением до 100-х | H84: =IFERROR(ROUND(H25,0)/ROUND(H80,0),"") -> 0.37080366 | I84: =IFERROR(ROUND(I25,0)/ROUND(I80,0),"") -> 0.75730816 | J84: =IFERROR(ROUND(J25,0)/ROUND(J80,0),"") -> 1.1645283 | K84: =IFERROR(ROUND(K25,0)/ROUND(K80,0),"") -> 0.65118913 | L84: =IFERROR(ROUND(L25,0)/ROUND(L80,0),"") -> 0.70099745 | M84: =IFERROR(ROUND(M25,0)/ROUND(M80,0),"") -> 0.91953298 | N84: =IFERROR(ROUND(N25,0)/ROUND(N80,0),"") -> 0.57123412 | O84: =IFERROR(ROUND(O25,0)/ROUND(O80,0),"") -> 0.49754501 | ... AD84: =IFERROR(ROUND(AD25,0)/ROUND(AD80,0),"")
C85: Расчетный показатель | D85: Общий (обязательный) | E85: Net Debt/EBITDA (LTM) | F85: Предзаполненная формула | G85: количество раз, с округлением до 100-х | H85: =IFERROR(ROUND(H28,0)/ROUND(H81,0),"") -> 1.0479512 | I85: =IFERROR(ROUND(I28,0)/ROUND(I81,0),"") -> 3.863806 | J85: =IFERROR(ROUND(J28,0)/ROUND(J81,0),"") -> 6.9506173 | K85: =IFERROR(ROUND(K28,0)/ROUND(K81,0),"") -> 1.6564365 | L85: =IFERROR(ROUND(L28,0)/ROUND(L81,0),"") -> 2.2972399 | M85: =IFERROR(ROUND(M28,0)/ROUND(M81,0),"") -> 3.875 | N85: =IFERROR(ROUND(N28,0)/ROUND(N81,0),"") -> 2.0706006 | O85: =IFERROR(ROUND(O28,0)/ROUND(O81,0),"") -> 1.3523985 | ... AD85: =IFERROR(ROUND(AD28,0)/ROUND(AD81,0),"")
C86: Расчетный показатель | D86: Общий (обязательный) | E86: Долг с учетом забалансовых обязательств/Выручка (LTM) | F86: Предзаполненная формула | G86: количество раз, с округлением до 100-х | H86: =IFERROR(H27/H80,"") -> 0 | I86: =IFERROR(I27/I80,"") -> 0 | J86: =IFERROR(J27/J80,"") -> 0 | K86: =IFERROR(K27/K80,"") -> 0 | L86: =IFERROR(L27/L80,"") -> 0 | M86: =IFERROR(M27/M80,"") -> 0 | N86: =IFERROR(N27/N80,"") -> 0 | O86: =IFERROR(O27/O80,"") -> 0 | ... AD86: =IFERROR(AD27/AD80,"")
C87: Расчетный показатель | D87: Общий (обязательный) | E87: Долг с учетом забалансовых обязательств/EBITDA (LTM) | F87: Предзаполненная формула | G87: количество раз, с округлением до 100-х | H87: =IFERROR(H27/H81,"") -> 0 | I87: =IFERROR(I27/I81,"") -> 0 | J87: =IFERROR(J27/J81,"") -> 0 | K87: =IFERROR(K27/K81,"") -> 0 | L87: =IFERROR(L27/L81,"") -> 0 | M87: =IFERROR(M27/M81,"") -> 0 | N87: =IFERROR(N27/N81,"") -> 0 | O87: =IFERROR(O27/O81,"") -> 0 | ... AD87: =IFERROR(AD27/AD81,"")
C88: Расчетный показатель | D88: Общий (обязательный) | E88: ICR (LTM) | F88: Предзаполненная формула | G88: количество раз, с округлением до 100-х | H88: =H72 -> 12.742511 | I88: =I72 -> 4.6476477 | J88: =J72 -> 1.9608151 | K88: =K72 -> 7.1052868 | L88: =L72 -> 5.8215842 | M88: =M72 -> 3.7606408 | N88: =N72 -> 6.197204 | O88: =O72 -> 7.9504229 | ... AD88: =AD72
C89: Расчетный показатель | D89: Общий (обязательный) | E89: ISCR (LTM) | F89: Предзаполненная формула | G89: количество раз, с округлением до 100-х | H89: =H74 -> 9.1740512 | I89: =I74 -> 3.6626996 | J89: =J74 -> 3.0084376 | K89: =K74 -> 6.397367 | L89: =L74 -> 6.2012656 | M89: =M74 -> 3.8560374 | N89: =N74 -> 4.9003541 | O89: =O74 -> 6.5396088 | ... AD89: =AD74
C90: Расчетный показатель | D90: Общий (обязательный) | E90: DSCR (LTM) | F90: Предзаполненная формула | G90: количество раз, с округлением до 100-х | H90: =H75 -> 9.1740512 | I90: =I75 -> 3.6626996 | J90: =J75 -> 3.0084376 | K90: =K75 -> 6.397367 | L90: =L75 -> 6.2012656 | M90: =M75 -> 3.8560374 | N90: =N75 -> 4.9003541 | O90: =O75 -> 6.5396088 | ... AD90: =AD75
C91: Расчетный показатель | D91: Общий (обязательный) | E91: DSCR с долгом (LTM) | F91: Предзаполненная формула | G91: количество раз, с округлением до 100-х
C92: Расчетный показатель | D92: Общий (обязательный) | E92: Денежные потоки от текущих операций (CFO) (LTM) | F92: Предзаполненная формула | G92: количество раз, с округлением до 100-х | H92: =H15 -> 980.206 | I92: =I15 -> 515.431 | J92: =J15 -> 461.082 | K92: =K15 -> 994.369 | L92: =L15 -> 987.349 | M92: =M15 -> 605.80242 | N92: =N15 -> 778.40913 | O92: =O15 -> 939.82855 | ... AD92: =AD15 -> 0
C93: Расчетный показатель | D93: Общий (обязательный) | E93: Платежи процентов по долговым обязательствам (LTM) | F93: Предзаполненная формула | G93: количество раз, с округлением до 100-х | H93: =H35 -> 90.008 | I93: =I35 -> 115.283 | J93: =J35 -> 165.45 | K93: =K35 -> 165.059 | L93: =L35 -> 161.816 | M93: =M35 -> 159.47333 | N93: =N35 -> 153.21145 | O93: =O35 -> 136.3408 | ... AD93: =AD35 -> 0
C94: Расчетный показатель | D94: Общий (обязательный) | E94: Обслуживание долга (Debt Service) (LTM) | F94: Предзаполненная формула | G94: количество раз, с округлением до 100-х | H94: =H33 -> 90.008 | I94: =I33 -> 115.283 | J94: =J33 -> 165.45 | K94: =K33 -> 165.059 | L94: =L33 -> 161.816 | M94: =M33 -> 159.47333 | N94: =N33 -> 153.21145 | O94: =O33 -> 136.3408 | ... AD94: =AD33 -> 0
C95: Расчетный показатель | D95: Общий (обязательный) | E95: Привлечение денежных средств (LTM) | F95: Предзаполненная формула | G95: количество раз, с округлением до 100-х | H95: =H32 -> 0 | I95: =I32 -> 0 | J95: =J32 -> 0 | K95: =K32 -> 0 | L95: =L32 -> 0 | M95: =M32 -> 0 | N95: =N32 -> 0 | O95: =O32 -> 0 | ... AD95: =AD32 -> 0
C96: Расчетный показатель | D96: Общий (обязательный) | E96: Сумма капитальных затрат (CAPEX) (LTM) | F96: Предзаполненная формула | G96: количество раз, с округлением до 100-х | H96: =IFERROR(H97+H98,"") -> 244.476 | I96: =IFERROR(I97+I98,"") -> 208.467 | J96: =IFERROR(J97+J98,"") -> 128.786 | K96: =IFERROR(K97+K98,"") -> 103.485 | L96: =IFERROR(L97+L98,"") -> 145.701 | M96: =IFERROR(M97+M98,"") -> 150.34062 | N96: =IFERROR(N97+N98,"") -> 180.83022 | O96: =IFERROR(O97+O98,"") -> 184.55384 | ... AD96: =IFERROR(AD97+AD98,"") -> 0
C97: Расчетный показатель | D97: Общий (обязательный) | E97: Капитальные затраты на поддержание (Maintenance CAPEX) (LTM) | F97: Предзаполненная формула | G97: количество раз, с округлением до 100-х | H97: =H23 -> 244.476 | I97: =I23 -> 208.467 | J97: =J23 -> 128.786 | K97: =K23 -> 103.485 | L97: =L23 -> 145.701 | M97: =M23 -> 150.34062 | N97: =N23 -> 180.83022 | O97: =O23 -> 184.55384 | ... AD97: =AD23 -> 0
C98: Расчетный показатель | D98: Общий (обязательный) | E98: Капитальные затраты на развитие (Development CAPEX) (LTM) | F98: Предзаполненная формула | G98: количество раз, с округлением до 100-х | H98: =H22 -> 0 | I98: =I22 -> 0 | J98: =J22 -> 0 | K98: =K22 -> 0 | L98: =L22 -> 0 | M98: =M22 -> 0 | N98: =N22 -> 0 | O98: =O22 -> 0 | ... AD98: =AD22 -> 0
C100: Расчетный показатель | D100: Общий (заполняется при необходимости) | E100: Коэффициент обсуживания процентных платежей в i-ом периоде - скорректированный (ISCR корр.) | F100: Корректировки на дополнительные притоки / оттоки, отражающие постоянные во времени операции, характерные для деятельности контрагента | G100: количество раз, с округлением до 100-х
C101: Расчетный показатель | D101: Общий (заполняется при необходимости) | E101: Коэффициент покрытия долга в i-ом периоде - скорректированный (DSCR корр.) | F101: см. лист формулы | G101: количество раз, с округлением до 100-х
C102: Расчетный показатель | D102: Общий (заполняется при необходимости) | E102: Денежные средства, доступные для обслуживания долга - скорректированный (CFADS корр.) | F102: Корректировки на дополнительные притоки / оттоки, отражающие постоянные во времени операции, характерные для деятельности контрагента | G102: =$G$2 -> USD млн
C104: Расчетный показатель | D104: Общий (заполняется при необходимости) | E104: EBITDA корр. | F104: Корректировки на дополнительные притоки / оттоки, отражающие постоянные во времени операции, характерные для деятельности контрагента | G104: =$G$2 -> USD млн
C105: Расчетный показатель | D105: Общий (заполняется при необходимости) | E105: Рентабельность EBITDA корр. | F105: Предзаполненная формула | G105: % | H105: =IFERROR(H104/H2,"") -> 0 | I105: =IFERROR(I104/I2,"") -> 0 | J105: =IFERROR(J104/J2,"") -> 0 | K105: =IFERROR(K104/K2,"") -> 0 | L105: =IFERROR(L104/L2,"") -> 0 | M105: =IFERROR(M104/M2,"") -> 0 | N105: =IFERROR(N104/N2,"") -> 0 | O105: =IFERROR(O104/O2,"") -> 0 | ... AD105: =IFERROR(AD104/AD2,"")
C106: Коэффициент | D106: Общий (заполняется при необходимости) | E106: Debt/EBITDA корр. | F106: Предзаполненная формула | G106: количество раз, с округлением до 100-х | H106: =IFERROR(H25/H104,"") | I106: =IFERROR(I25/I104,"") | J106: =IFERROR(J25/J104,"") | K106: =IFERROR(K25/K104,"") | L106: =IFERROR(L25/L104,"") | M106: =IFERROR(M25/M104,"") | N106: =IFERROR(N25/N104,"") | O106: =IFERROR(O25/O104,"") | ... AD106: =IFERROR(AD25/AD104,"")
C107: Коэффициент | D107: Общий (заполняется при необходимости) | E107: Net Debt/EBITDA корр. | F107: Предзаполненная формула | G107: количество раз, с округлением до 100-х | H107: =IFERROR(H28/H104,"") | I107: =IFERROR(I28/I104,"") | J107: =IFERROR(J28/J104,"") | K107: =IFERROR(K28/K104,"") | L107: =IFERROR(L28/L104,"") | M107: =IFERROR(M28/M104,"") | N107: =IFERROR(N28/N104,"") | O107: =IFERROR(O28/O104,"") | ... AD107: =IFERROR(AD28/AD104,"")
C108: Расчетный показатель | D108: Общий (заполняется при необходимости) | E108: Долг с учетом забалансовых обязательств/EBITDA корр. | F108: Предзаполненная формула | G108: количество раз, с округлением до 100-х | H108: =IFERROR(H27/H104,"") | I108: =IFERROR(I27/I104,"") | J108: =IFERROR(J27/J104,"") | K108: =IFERROR(K27/K104,"") | L108: =IFERROR(L27/L104,"") | M108: =IFERROR(M27/M104,"") | N108: =IFERROR(N27/N104,"") | O108: =IFERROR(O27/O104,"") | ... AD108: =IFERROR(AD27/AD104,"")
C109: Расчетный показатель | D109: Общий (заполняется при необходимости) | E109: ICR corr | F109: Предзаполненная формула | G109: количество раз, с округлением до 100-х | H109: =IFERROR((H6-H23)/H73,"") -> 10.026352 | I109: =IFERROR((I6-I23)/I73,"") -> 2.8393412 | J109: =IFERROR((J6-J23)/J73,"") -> 1.1824168 | K109: =IFERROR((K6-K23)/K73,"") -> 6.4783291 | L109: =IFERROR((L6-L23)/L73,"") -> 4.9211726 | M109: =IFERROR((M6-M23)/M73,"") -> 2.8179088 | N109: =IFERROR((N6-N23)/N73,"") -> 5.0169383 | O109: =IFERROR((O6-O23)/O73,"") -> 6.5968013 | ... AD109: =IFERROR((AD6-AD23)/AD73,"")
...

Sheet PRINT
E2: Scenario | F2: 1 | G2: =G13/G7 -> 85.230989 | H2: =H13/H7 -> 94.862472 | I2: =I13/I7 -> 49.527249 | J2: =J13/J7 -> 25.73639 | K2: =K13/K7 -> 73.548422 | L2: =L13/L7 -> 102.33118 | M2: =M13/M7 -> 48.122398 | N2: =N13/N7 -> 30.206412 | ... Z2: =Z13/Z7 -> 86.984989
E4: Показатель | F4: Ед.изм. | G4: =Calc!G2 -> 2013 | H4: =Calc!H2 -> 2014 | I4: =Calc!I2 -> 2015 | J4: =Calc!J2 -> 2016 | K4: =Calc!K2 -> 2017 | L4: =Calc!L2 -> 2018 | M4: =Calc!M2 -> 2019 | N4: =Calc!N2 -> 2020 | ... Z4: =Calc!Z2 -> 2032
E5: Операционные показатели
E6: Объем производства метанола | F6: млн т | G6: =Calc!G42/1000 -> 4.344 | H6: =Calc!H42/1000 -> 4.853 | I6: =Calc!I42/1000 -> 5.193 | J6: =Calc!J42/1000 -> 7.017 | K6: =Calc!K42/1000 -> 7.187 | L6: =Calc!L42/1000 -> 7.211 | M6: =Calc!M42/1000 -> 7.589 | N6: =Calc!N42/1000 -> 6.614 | ... Z6: =Calc!Z42/1000 -> 7.738
E7: Объем продажи метанола | F7: млн т | G7: =Calc!G63/1000 -> 7.991 | H7: =Calc!H63/1000 -> 8.504 | I7: =Calc!I63/1000 -> 8.471 | J7: =Calc!J63/1000 -> 9.478 | K7: =Calc!K63/1000 -> 10.669 | L7: =Calc!L63/1000 -> 11.208 | M7: =Calc!M63/1000 -> 11.134 | N7: =Calc!N63/1000 -> 10.74 | ... Z7: =Calc!Z63/1000 -> 11.586242
E8: Цена реализации метанола | F8: $/т | G8: =Calc!G68 -> 378.43161 | H8: =Calc!H68 -> 379.04504 | I8: =Calc!I68 -> 262.73191 | J8: =Calc!J68 -> 210.84923 | K8: =Calc!K68 -> 286.87243 | L8: =Calc!L68 -> 350.80719 | M8: =Calc!M68 -> 294.90875 | N8: =Calc!N68 -> 246.73771 | ... Z8: =Calc!Z68 -> 415.05883
E9: Изменение | F9: % | G9: =IFERROR(G8/F8-1,"-") -> - | H9: =IFERROR(H8/G8-1,"-") -> 0.0016209721 | I9: =IFERROR(I8/H8-1,"-") -> -0.30685833 | J9: =IFERROR(J8/I8-1,"-") -> -0.19747384 | K9: =IFERROR(K8/J8-1,"-") -> 0.36055718 | L9: =IFERROR(L8/K8-1,"-") -> 0.22286825 | M9: =IFERROR(M8/L8-1,"-") -> -0.15934235 | N9: =IFERROR(N8/M8-1,"-") -> -0.16334218 | ... Z9: =IFERROR(Z8/Y8-1,"-") -> 0.004
E10: Финансовые показатели
E11: Выручка | F11: млн $ | G11: ='P&L'!G8 -> 3024.047 | H11: ='P&L'!H8 -> 3223.399 | I11: ='P&L'!I8 -> 2225.602 | J11: ='P&L'!J8 -> 1998.429 | K11: ='P&L'!K8 -> 3060.642 | L11: ='P&L'!L8 -> 3931.847 | M11: ='P&L'!M8 -> 3283.514 | N11: ='P&L'!N8 -> 2649.963 | ... Z11: ='P&L'!Z8 -> 4808.972
E12: Темп прироста выручки | F12: % | G12: =IFERROR(G11/F11-1,"-") -> - | H12: =IFERROR(H11/G11-1,"-") -> 0.065922256 | I12: =IFERROR(I11/H11-1,"-") -> -0.30954809 | J12: =IFERROR(J11/I11-1,"-") -> -0.10207261 | K12: =IFERROR(K11/J11-1,"-") -> 0.53152401 | L12: =IFERROR(L11/K11-1,"-") -> 0.2846478 | M12: =IFERROR(M11/L11-1,"-") -> -0.16489273 | N12: =IFERROR(N11/M11-1,"-") -> -0.19294908 | ... Z12: =IFERROR(Z11/Y11-1,"-") -> 0.004
E13: EBITDA | F13: млн $ | G13: ='P&L'!G17 -> 681.08083 | H13: ='P&L'!H17 -> 806.71046 | I13: ='P&L'!I17 -> 419.54533 | J13: ='P&L'!J17 -> 243.9295 | K13: ='P&L'!K17 -> 784.68812 | L13: ='P&L'!L17 -> 1146.9279 | M13: ='P&L'!M17 -> 535.79477 | N13: ='P&L'!N17 -> 324.41686 | ... Z13: ='P&L'!Z17 -> 1007.8291
E14: EBITDA margin, % | F14: % | G14: =IFERROR(G13/G11,"-") -> 0.22522164 | H14: =IFERROR(H13/H11,"-") -> 0.25026702 | I14: =IFERROR(I13/I11,"-") -> 0.1885087 | J14: =IFERROR(J13/J11,"-") -> 0.12206063 | K14: =IFERROR(K13/K11,"-") -> 0.25638024 | L14: =IFERROR(L13/L11,"-") -> 0.29170206 | M14: =IFERROR(M13/M11,"-") -> 0.16317725 | N14: =IFERROR(N13/N11,"-") -> 0.12242317 | ... Z14: =IFERROR(Z13/Z11,"-") -> 0.20957267
E15: Операционный денежный поток | F15: млн $ | G15: =CFS!G12 -> 585.797 | H15: =CFS!H12 -> 801.017 | I15: =CFS!I12 -> 296.951 | J15: =CFS!J12 -> 249.93 | K15: =CFS!K12 -> 780.22 | L15: =CFS!L12 -> 980.206 | M15: =CFS!M12 -> 515.431 | N15: =CFS!N12 -> 461.082 | ... Z15: =CFS!Z12 -> 883.18181
E16: CapEx на поддержание | F16: млн $ | G16: =CFS!G15 -> -269.367 | H16: =CFS!H15 -> -84.168 | I16: =CFS!I15 -> -96.909 | J16: =CFS!J15 -> -99.881 | K16: =CFS!K15 -> -103.17 | L16: =CFS!L15 -> -244.476 | M16: =CFS!M15 -> -208.467 | N16: =CFS!N15 -> -128.786 | ... Z16: =CFS!Z15 -> -212.11736
E17: CapEx на расширение | F17: млн $ | G17: =CFS!G16 -> -309.469 | H17: =CFS!H16 -> -573.844 | I17: =CFS!I16 -> -328.112 | J17: =CFS!J16 -> 0 | K17: =CFS!K16 -> 0 | L17: =CFS!L16 -> 0 | M17: =CFS!M16 -> -115.393 | N17: =CFS!N16 -> -213.03 | ... Z17: =CFS!Z16 -> 0
E18: Инвестиционный денежный поток | F18: млн $ | G18: =CFS!G18 -> -526.429 | H18: =CFS!H18 -> -681.022 | I18: =CFS!I18 -> -426.255 | J18: =CFS!J18 -> -88.209 | K18: =CFS!K18 -> -105.517 | L18: =CFS!L18 -> -306.351 | M18: =CFS!M18 -> -250.692 | N18: =CFS!N18 -> -278.063 | ... Z18: =CFS!Z18 -> -212.11736
E19: Погашение долга | F19: млн $ | G19: =CFS!G21 -> -39.491 | H19: =CFS!H21 -> -41.504 | I19: =CFS!I21 -> -193.996 | J19: =CFS!J21 -> -48.417 | K19: =CFS!K21 -> -56.997 | L19: =CFS!L21 -> -213.622 | M19: =CFS!M21 -> -101.812 | N19: =CFS!N21 -> -106.834 | ... Z19: =CFS!Z21 -> -69.484
E20: PRES | F20: млн $ | G20: =CFS!G22 -> -55.446 | H20: =CFS!H22 -> -52.995 | I20: =CFS!I22 -> -82.275 | J20: =CFS!J22 -> -82.965 | K20: =CFS!K22 -> -86.041 | L20: =CFS!L22 -> -90.008 | M20: =CFS!M22 -> -115.283 | N20: =CFS!N22 -> -165.45 | ... Z20: =CFS!Z22 -> -50.92356
E21: Дивиденды | F21: млн $ | G21: =CFS!G23 -> -74.937 | H21: =CFS!H23 -> -89.913 | I21: =CFS!I23 -> -97.221 | J21: =CFS!J23 -> -98.797 | K21: =CFS!K23 -> -101.497 | L21: =CFS!L23 -> -105.676 | M21: =CFS!M23 -> -107.876 | N21: =CFS!N23 -> -36.004 | ... Z21: =CFS!Z23 -> -136.84317
E22: Финансовый денежный поток | F22: млн $ | G22: =CFS!G28 -> -54.017 | H22: =CFS!H28 -> 98.869 | I22: =CFS!I28 -> -567.362 | J22: =CFS!J28 -> -192.765 | K22: =CFS!K28 -> -523.114 | L22: =CFS!L28 -> -793.257 | M22: =CFS!M28 -> -104.053 | N22: =CFS!N28 -> 234.059 | ... Z22: =CFS!Z28 -> -257.25073
E23: Денежные средства на конец | F23: млн $ | G23: =CFS!G32 -> 732.736 | H23: =CFS!H32 -> 951.6 | I23: =CFS!I32 -> 254.934 | J23: =CFS!J32 -> 223.89 | K23: =CFS!K32 -> 375.479 | L23: =CFS!L32 -> 256.077 | M23: =CFS!M32 -> 416.763 | N23: =CFS!N32 -> 833.841 | ... Z23: =CFS!Z32 -> 2472.0674
E24: Долговые метрики
E25: Долг | F25: млн $ | G25: =SUM(G26:G27) -> 1168.306 | H25: =SUM(H26:H27) -> 1722.038 | I25: =SUM(I26:I27) -> 1535.89 | J25: =SUM(J26:J27) -> 1556.206 | K25: =SUM(K26:K27) -> 1502.271 | L25: =SUM(L26:L27) -> 1458.286 | M25: =SUM(M26:M27) -> 2487.358 | N25: =SUM(N26:N27) -> 3085.606 | ... Z25: =SUM(Z26:Z27) -> 489.579
E26: Долг | F26: млн $ | G26: =BS!G28+BS!G33 -> 1168.306 | H26: =BS!H28+BS!H33 -> 1722.038 | I26: =BS!I28+BS!I33 -> 1535.89 | J26: =BS!J28+BS!J33 -> 1556.206 | K26: =BS!K28+BS!K33 -> 1502.271 | L26: =BS!L28+BS!L33 -> 1458.286 | M26: =BS!M28+BS!M33 -> 1768.853 | N26: =BS!N28+BS!N33 -> 2363.372 | ... Z26: =BS!Z28+BS!Z33 -> 401.767
E27: Лизинг | F27: млн $ | G27: =BS!G29+BS!G34 -> 0 | H27: =BS!H29+BS!H34 -> 0 | I27: =BS!I29+BS!I34 -> 0 | J27: =BS!J29+BS!J34 -> 0 | K27: =BS!K29+BS!K34 -> 0 | L27: =BS!L29+BS!L34 -> 0 | M27: =BS!M29+BS!M34 -> 718.505 | N27: =BS!N29+BS!N34 -> 722.234 | ... Z27: =BS!Z29+BS!Z34 -> 87.812
E28: Чистый долг | F28: млн $ | G28: =G25-G23 -> 435.57 | H28: =H25-H23 -> 770.438 | I28: =I25-I23 -> 1280.956 | J28: =J25-J23 -> 1332.316 | K28: =K25-K23 -> 1126.792 | L28: =L25-L23 -> 1202.209 | M28: =M25-M23 -> 2070.595 | N28: =N25-N23 -> 2251.765 | ... Z28: =Z25-Z23 -> -1982.4884
E29: Долг/EBITDA | F29: x | G29: =IFERROR(G25/G13,"-") -> 1.7153705 | H29: =IFERROR(H25/H13,"-") -> 2.134642 | I29: =IFERROR(I25/I13,"-") -> 3.660844 | J29: =IFERROR(J25/J13,"-") -> 6.3797367 | K29: =IFERROR(K25/K13,"-") -> 1.9144817 | L29: =IFERROR(L25/L13,"-") -> 1.2714714 | M29: =IFERROR(M25/M13,"-") -> 4.6423708 | N29: =IFERROR(N25/N13,"-") -> 9.511238 | ... Z29: =IFERROR(Z25/Z13,"-") -> 0.48577581
E30: Чистый долг/EBITDA | F30: x | G30: =IFERROR(G28/G13,"-") -> 0.63952761 | H30: =IFERROR(H28/H13,"-") -> 0.95503658 | I30: =IFERROR(I28/I13,"-") -> 3.0532005 | J30: =IFERROR(J28/J13,"-") -> 5.4618895 | K30: =IFERROR(K28/K13,"-") -> 1.4359743 | L30: =IFERROR(L28/L13,"-") -> 1.0481993 | M30: =IFERROR(M28/M13,"-") -> 3.86453 | N30: =IFERROR(N28/N13,"-") -> 6.9409616 | ... Z30: =IFERROR(Z28/Z13,"-") -> -1.9670878
E31: ISCR | F31: x | G31: =IFERROR((G15+G16)/-G20,"-") -> 5.7069942 | H31: =IFERROR((H15+H16)/-H20,"-") -> 13.526729 | I31: =IFERROR((I15+I16)/-I20,"-") -> 2.4313826 | J31: =IFERROR((J15+J16)/-J20,"-") -> 1.8085819 | K31: =IFERROR((K15+K16)/-K20,"-") -> 7.868923 | L31: =IFERROR((L15+L16)/-L20,"-") -> 8.1740512 | M31: =IFERROR((M15+M16)/-M20,"-") -> 2.6626996 | N31: =IFERROR((N15+N16)/-N20,"-") -> 2.0084376 | ... Z31: =IFERROR((Z15+Z16)/-Z20,"-") -> 13.177878
E32: DSCR | F32: x | G32: =IFERROR((G15+G16)/-(G19+G20),"-") -> 3.3330524 | H32: =IFERROR((H15+H16)/-(H19+H20),"-") -> 7.585784 | I32: =IFERROR((I15+I16)/-(I19+I20),"-") -> 0.72407889 | J32: =IFERROR((J15+J16)/-(J19+J20),"-") -> 1.1420819 | K32: =IFERROR((K15+K16)/-(K19+K20),"-") -> 4.7333576 | L32: =IFERROR((L15+L16)/-(L19+L20),"-") -> 2.4231137 | M32: =IFERROR((M15+M16)/-(M19+M20),"-") -> 1.4139616 | N32: =IFERROR((N15+N16)/-(N19+N20),"-") -> 1.2204022 | ... Z32: =IFERROR((Z15+Z16)/-(Z19+Z20),"-") -> 5.573275
E33: Оценка бизнеса
E34: WACC | F34: % | G34: =DCF!$F$19 -> 0.11375701
E35: TGR | F35: % | G35: =DCF!$F$24 -> 0.02
E36: ΣDFCFF | F36: млн $ | G36: =SUM(DCF!R22:AA22) -> 3646.6789
E37: TV | F37: млн $ | G37: =DCF!AA25 -> 2729.4774
E38: EV | F38: млн $ | G38: =G36+G37 -> 6376.1563
E39: EV / EBITDA 2022 | F39: x | G39: =G38/P13 -> 6.7685605
E40: Equity | F40: млн $ | G40: =DCF!R31 -> 4161.2883
E41: Стоимость акции | F41: $ | G41: =DCF!R34 -> 58.055725
E42: Недооценка (переоценка) | F42: % | G42: =G41/41.66-1 -> 0.39356037
Q47: 1978
Q48: 369
Q49: =Q48/Q47 -> 0.18655207

Sheet Scenario
B2: Index | E2: Measure | F2: Base | G2: =Calc!G2 -> 2013 | H2: =Calc!H2 -> 2014 | I2: =Calc!I2 -> 2015 | J2: =Calc!J2 -> 2016 | K2: =Calc!K2 -> 2017 | L2: =Calc!L2 -> 2018 | M2: =Calc!M2 -> 2019 | N2: =Calc!N2 -> 2020 | ... Z2: =Calc!Z2 -> 2032
F3: =PRINT!F2 -> 1 | G3: =Calc!G3 -> fact | H3: =Calc!H3 -> fact | I3: =Calc!I3 -> fact | J3: =Calc!J3 -> fact | K3: =Calc!K3 -> fact | L3: =Calc!L3 -> fact | M3: =Calc!M3 -> fact | N3: =Calc!N3 -> fact | ... Z3: =Calc!Z3 -> forecast
B5: Панель управления | F5: =DCF!R34 -> 58.055725 | J5: 1 | K5: =J5+1 -> 2 | L5: =K5+1 -> 3 | M5: =L5+1 -> 4 | N5: =M5+1 -> 5 | O5: =N5+1 -> 6 | P5: =O5+1 -> 7
J7: Sber | K7: Sber | L7: Sber | M7: Sber | N7: Sber | O7: Sber | P7: Sber
J8: Base (Price) | K8: Base (NG) | L8: Negative | M8: Optimistic | N8: Base (w/o G-3) | O8: Negative (w/o G-3) | P8: Optimistic (w/o G-3)
D9: Macro
D10: CPI US | E10: x | F10: =CHOOSE($F$3,J10,K10,L10,M10,N10,O10,P10,Q10,R10) -> 1 | G10: 1-Base, 2-Negative, 3-Optimistic | J10: 1 | K10: 1 | L10: 1 | M10: 1 | N10: 1 | O10: 1 | P10: 1
D11: Natural gas price Henry Hub | E11: x | F11: =CHOOSE($F$3,J11,K11,L11,M11,N11,O11,P11,Q11,R11) -> 1 | G11: 1-Base, 2-Negative, 3-Optimistic | J11: 1 | K11: 1 | L11: 1 | M11: 1 | N11: 1 | O11: 1 | P11: 1
D13: Revenue
D14: Production | E14: x | F14: =CHOOSE($F$3,J14,K14,L14,M14,N14,O14,P14,Q14,R14) -> 1 | G14: 1-2022, 2-Average, 3-Hard number | J14: 1 | K14: 1 | L14: 1 | M14: 1 | N14: 1 | O14: 1 | P14: 1
D15: Coeff. (if production - 3) | E15: % | F15: =CHOOSE($F$3,J15,K15,L15,M15,N15,O15,P15,Q15,R15) -> 0
D16: Methanex-produced methanol | E16: x | F16: =CHOOSE($F$3,J16,K16,L16,M16,N16,O16,P16,Q16,R16) -> 3 | G16: 1-2022, 2-Average, 3-Hard number | J16: 3 | K16: 3 | L16: 3 | M16: 3 | N16: 3 | O16: 3 | P16: 3
D17: Coeff. (if Methanex-produced methanol - 3) | E17: % | F17: =CHOOSE($F$3,J17,K17,L17,M17,N17,O17,P17,Q17,R17) -> 1 | J17: 1 | K17: 1 | L17: 1 | M17: 1 | N17: 1 | O17: 1 | P17: 1
D18: Purchased methanol | E18: x | F18: =CHOOSE($F$3,J18,K18,L18,M18,N18,O18,P18,Q18,R18) -> 2 | G18: 1-2022, 2-Average, 3-Hard number | J18: 2 | K18: 2 | L18: 2 | M18: 2 | N18: 2 | O18: 2 | P18: 2
D19: Coeff. (if purchased methanol - 3) | E19: % | F19: =CHOOSE($F$3,J19,K19,L19,M19,N19,O19,P19,Q19,R19) -> 0
D20: Commission sales | E20: x | F20: =CHOOSE($F$3,J20,K20,L20,M20,N20,O20,P20,Q20,R20) -> 2 | G20: 1-2022, 2-Average, 3-Hard number | J20: 2 | K20: 2 | L20: 2 | M20: 2 | N20: 2 | O20: 2 | P20: 2
D21: Coeff. (if commission sales - 3) | E21: % | F21: =CHOOSE($F$3,J21,K21,L21,M21,N21,O21,P21,Q21,R21) -> 0
D22: Price | E22: x | F22: =CHOOSE($F$3,J22,K22,L22,M22,N22,O22,P22,Q22,R22) -> 1 | G22: 1-Base, 2-Negative, 3-Optimistic | J22: 1 | K22: 1 | L22: 2 | M22: 3 | N22: 1 | O22: 2 | P22: 3
D24: OpEx
D25: Cost of raw materials | E25: x | F25: =CHOOSE($F$3,J25,K25,L25,M25,N25,O25,P25,Q25,R25) -> 1 | G25: 1-Price, 2-CPI, 3-Natural gas price Henry Hub | J25: 1 | K25: 3 | L25: 1 | M25: 1 | N25: 1 | O25: 1 | P25: 1
D26: Cost of purchased methanol | E26: x | F26: =CHOOSE($F$3,J26,K26,L26,M26,N26,O26,P26,Q26,R26) -> 1 | G26: 1-Price, 2-CPI | J26: 1 | K26: 1 | L26: 1 | M26: 1 | N26: 1 | O26: 1 | P26: 1
D27: Ocean freight and other logistics | E27: x | F27: =CHOOSE($F$3,J27,K27,L27,M27,N27,O27,P27,Q27,R27) -> 1 | G27: 1-Price, 2-CPI | J27: 1 | K27: 1 | L27: 1 | M27: 1 | N27: 1 | O27: 1 | P27: 1
D28: Employee expenses, including share-based compensation | E28: x | F28: =CHOOSE($F$3,J28,K28,L28,M28,N28,O28,P28,Q28,R28) -> 2 | G28: 1-Price, 2-CPI | J28: 2 | K28: 2 | L28: 2 | M28: 2 | N28: 2 | O28: 2 | P28: 2
D29: Other expenses | E29: x | F29: =CHOOSE($F$3,J29,K29,L29,M29,N29,O29,P29,Q29,R29) -> 2 | G29: 1-Price, 2-CPI | J29: 2 | K29: 2 | L29: 2 | M29: 2 | N29: 2 | O29: 2 | P29: 2
D31: CapEx
D32: Property, plant and equipment | E32: x | F32: =CHOOSE($F$3,J32,K32,L32,M32,N32,O32,P32,Q32,R32) -> 1 | G32: 1-CPI, 2-as % of Revenue | J32: 1 | K32: 1 | L32: 1 | M32: 1 | N32: 1 | O32: 1 | P32: 1
D33: USA (Geismar 3) | E33: x | F33: =CHOOSE($F$3,J33,K33,L33,M33,N33,O33,P33,Q33,R33) -> 1 | G33: 0-no, 1-yes | J33: 1 | K33: 1 | L33: 1 | M33: 1 | N33: 0 | O33: 0 | P33: 0
D34: Operation phase | E34: year | F34: =CHOOSE($F$3,J34,K34,L34,M34,N34,O34,P34,Q34,R34) -> 2024 | J34: 2024 | K34: 2024 | L34: 2024 | M34: 2024 | N34: 2024 | O34: 2024 | P34: 2024
D35: Production | E35: x | F35: =CHOOSE($F$3,J35,K35,L35,M35,N35,O35,P35,Q35,R35) -> 1800 | J35: 1800 | K35: 1800 | L35: 1800 | M35: 1800 | N35: 1800 | O35: 1800 | P35: 1800
D36: Coeff. | E36: % | F36: =CHOOSE($F$3,J36,K36,L36,M36,N36,O36,P36,Q36,R36) -> 0.9 | J36: 0.9 | K36: 0.9 | L36: 0.9 | M36: 0.9 | N36: 0.9 | O36: 0.9 | P36: 0.9
D37: CapEx remaining | E37: mn $ | F37: =CHOOSE($F$3,J37,K37,L37,M37,N37,O37,P37,Q37,R37) -> 440 | J37: =(415+465)/2 -> 440 | K37: =(415+465)/2 -> 440 | L37: =(415+465)/2 -> 440 | M37: =(415+465)/2 -> 440 | N37: =(415+465)/2 -> 440 | O37: =(415+465)/2 -> 440 | P37: =(415+465)/2 -> 440
D39: Valuation
D40: WACC | E40: % | F40: =CHOOSE($F$3,J40,K40,L40,M40,N40,O40,P40,Q40,R40) -> 0.11375701 | J40: 0.11375701 | K40: 0.11375701 | L40: 0.11375701 | M40: 0.11375701 | N40: 0.11375701 | O40: 0.11375701 | P40: 0.11375701
D41: TGR | E41: % | F41: =CHOOSE($F$3,J41,K41,L41,M41,N41,O41,P41,Q41,R41) -> 0.02 | J41: 0.02 | K41: 0.02 | L41: 0.02 | M41: 0.02 | N41: 0.02 | O41: 0.02 | P41: 0.02
B45: Sensitivity
J48: =F5 -> 58.055725 | K48: 2 | L48: 1 | M48: 3 | P48: 2 | Q48: 1 | R48: 3
J49: 0.14 | O49: 0.14
J50: 0.13 | O50: 0.13
J51: 0.12 | O51: 0.12
J52: 0.11375701 | O52: 0.11375701
J53: 0.11 | O53: 0.11
J54: 0.1 | O54: 0.1
J55: 0.09 | O55: 0.09
B59: . | D59: . | E59: . | F59: . | G59: . | H59: . | I59: . | J59: . | K59: . | L59: . | M59: . | N59: . | O59: . | P59: . | Q59: . | R59: . | S59: . | T59: . | U59: . | V59: . | W59: . | X59: . | Y59: . | Z59: .

Sheet Calc
Q1: =DATE(Q2,1,1) -> 44927 | R1: =DATE(R2,1,1) -> 45292 | S1: =DATE(S2,1,1) -> 45658 | T1: =DATE(T2,1,1) -> 46023 | U1: =DATE(U2,1,1) -> 46388 | V1: =DATE(V2,1,1) -> 46753 | W1: =DATE(W2,1,1) -> 47119 | X1: =DATE(X2,1,1) -> 47484 | ... Z1: =DATE(Z2,1,1) -> 48214
B2: Index | E2: Measure | F2: Base | G2: 2013 | H2: =G2+1 -> 2014 | I2: =H2+1 -> 2015 | J2: =I2+1 -> 2016 | K2: =J2+1 -> 2017 | L2: =K2+1 -> 2018 | M2: =L2+1 -> 2019 | N2: =M2+1 -> 2020 | O2: =N2+1 -> 2021 | ... Z2: =Y2+1 -> 2032
G3: fact | H3: fact | I3: fact | J3: fact | K3: fact | L3: fact | M3: fact | N3: fact | O3: fact | P3: fact | Q3: forecast | R3: forecast | S3: forecast | T3: forecast | U3: forecast | V3: forecast | W3: forecast | X3: forecast | Y3: forecast | Z3: forecast
B6: Macro
D8: CPI US | E8: % | F8: =Scenario!F10 -> 1 | G8: =CHOOSE($F8,G9,G10,G11) -> 0.016331 | H8: =CHOOSE($F8,H9,H10,H11) -> 0.0146123 | I8: =CHOOSE($F8,I9,I10,I11) -> 0.0125234 | J8: =CHOOSE($F8,J9,J10,J11) -> 0.0185337 | K8: =CHOOSE($F8,K9,K10,K11) -> 0.0163842 | L8: =CHOOSE($F8,L9,L10,L11) -> 0.019 | M8: =CHOOSE($F8,M9,M10,M11) -> 0.023 | N8: =CHOOSE($F8,N9,N10,N11) -> 0.014 | ... Z8: =CHOOSE($F8,Z9,Z10,Z11) -> 0.02
D9: Sber (base) | E9: % | G9: =Inputs!V4 -> 0.016331 | H9: =Inputs!W4 -> 0.0146123 | I9: =Inputs!X4 -> 0.0125234 | J9: =Inputs!Y4 -> 0.0185337 | K9: =Inputs!Z4 -> 0.0163842 | L9: =Inputs!AA4 -> 0.019 | M9: =Inputs!AB4 -> 0.023 | N9: =Inputs!AC4 -> 0.014 | ... Z9: =Inputs!AO4 -> 0.02
D10: Sber (negative) | E10: % | G10: ='Inputs sber (-)'!V4 -> 0.016331 | H10: ='Inputs sber (-)'!W4 -> 0.0146123 | I10: ='Inputs sber (-)'!X4 -> 0.0125234 | J10: ='Inputs sber (-)'!Y4 -> 0.0185337 | K10: ='Inputs sber (-)'!Z4 -> 0.0163842 | L10: ='Inputs sber (-)'!AA4 -> 0.019 | M10: ='Inputs sber (-)'!AB4 -> 0.023 | N10: ='Inputs sber (-)'!AC4 -> 0.014 | ... Z10: ='Inputs sber (-)'!AO4 -> 0.02
D11: Sber (optimistic) | E11: % | G11: ='Inputs sber (+)'!V4 -> 0.016331 | H11: ='Inputs sber (+)'!W4 -> 0.0146123 | I11: ='Inputs sber (+)'!X4 -> 0.0125234 | J11: ='Inputs sber (+)'!Y4 -> 0.0185337 | K11: ='Inputs sber (+)'!Z4 -> 0.0163842 | L11: ='Inputs sber (+)'!AA4 -> 0.019 | M11: ='Inputs sber (+)'!AB4 -> 0.023 | N11: ='Inputs sber (+)'!AC4 -> 0.014 | ... Z11: ='Inputs sber (+)'!AO4 -> 0.020591825
D13: Natural gas price Henry Hub | E13: $/mmBtu | F13: =Scenario!F11 -> 1 | G13: =CHOOSE($F13,G14,G15,G16) -> 0 | H13: =CHOOSE($F13,H14,H15,H16) -> 0 | I13: =CHOOSE($F13,I14,I15,I16) -> 2.6121 | J13: =CHOOSE($F13,J14,J15,J16) -> 2.4946 | K13: =CHOOSE($F13,K14,K15,K16) -> 2.9629 | L13: =CHOOSE($F13,L14,L15,L16) -> 3.1511 | M13: =CHOOSE($F13,M14,M15,M16) -> 2.5625 | N13: =CHOOSE($F13,N14,N15,N16) -> 2.0184177 | ... Z13: =CHOOSE($F13,Z14,Z15,Z16) -> 4.2317764
D14: Sber (base) | E14: $/mmBtu | G14: =Inputs!V249 -> 0 | H14: =Inputs!W249 -> 0 | I14: =Inputs!X249 -> 2.6121 | J14: =Inputs!Y249 -> 2.4946 | K14: =Inputs!Z249 -> 2.9629 | L14: =Inputs!AA249 -> 3.1511 | M14: =Inputs!AB249 -> 2.5625 | N14: =Inputs!AC249 -> 2.0184177 | ... Z14: =Inputs!AO249 -> 4.2317764
D15: Sber (negative) | E15: $/mmBtu | G15: ='Inputs sber (-)'!V249 -> 0 | H15: ='Inputs sber (-)'!W249 -> 0 | I15: ='Inputs sber (-)'!X249 -> 2.6121 | J15: ='Inputs sber (-)'!Y249 -> 2.4946 | K15: ='Inputs sber (-)'!Z249 -> 2.9629 | L15: ='Inputs sber (-)'!AA249 -> 3.1511 | M15: ='Inputs sber (-)'!AB249 -> 2.5625 | N15: ='Inputs sber (-)'!AC249 -> 2.0184177 | ... Z15: ='Inputs sber (-)'!AO249 -> 2.0740735
D16: Sber (optimistic) | E16: $/mmBtu | G16: ='Inputs sber (+)'!V249 -> 0 | H16: ='Inputs sber (+)'!W249 -> 0 | I16: ='Inputs sber (+)'!X249 -> 2.6121 | J16: ='Inputs sber (+)'!Y249 -> 2.4946 | K16: ='Inputs sber (+)'!Z249 -> 2.9629 | L16: ='Inputs sber (+)'!AA249 -> 3.1511 | M16: ='Inputs sber (+)'!AB249 -> 2.5625 | N16: ='Inputs sber (+)'!AC249 -> 2.0184177 | ... Z16: ='Inputs sber (+)'!AO249 -> 6.8698344
B20: Sales
C22: Production
D24: Operating Capacity | E24: ths t | G24: =SUM(G25:G31) -> 8340 | H24: =SUM(H25:H31) -> 8340 | I24: =SUM(I25:I31) -> 9380 | J24: =SUM(J25:J31) -> 9380 | K24: =SUM(K25:K31) -> 9380 | L24: =SUM(L25:L31) -> 9380 | M24: =SUM(M25:M31) -> 9150 | N24: =SUM(N25:N31) -> 9150 | ... Z24: =SUM(Z25:Z31) -> 11130
D25: USA (Geismar 1 & 2) | E25: ths t | G25: 1000 | H25: 1000 | I25: 2000 | J25: 2000 | K25: 2000 | L25: 2000 | M25: 2000 | N25: 2000 | O25: 2200 | P25: 2200 | Q25: =P25 -> 2200 | R25: =Q25 -> 2200 | S25: =R25 -> 2200 | T25: =S25 -> 2200 | U25: =T25 -> 2200 | V25: =U25 -> 2200 | W25: =V25 -> 2200 | X25: =W25 -> 2200 | ... Z25: =Y25 -> 2200
D26: USA (Geismar 3) | E26: ths t | F26: =Scenario!$F$33 -> 1 | G26: 0 | H26: 0 | I26: 0 | J26: 0 | K26: 0 | L26: 0 | M26: 0 | N26: 0 | O26: 0 | P26: 0 | Q26: =($F26*Scenario!$F$35)*(Scenario!$F34<=Q2) -> 0 | R26: =($F26*Scenario!$F$35)*(Scenario!$F34<=R2) -> 1800 | S26: =($F26*Scenario!$F$35)*(Scenario!$F34<=S2) -> 1800 | T26: =($F26*Scenario!$F$35)*(Scenario!$F34<=T2) -> 1800 | U26: =($F26*Scenario!$F$35)*(Scenario!$F34<=U2) -> 1800 | V26: =($F26*Scenario!$F$35)*(Scenario!$F34<=V2) -> 1800 | W26: =($F26*Scenario!$F$35)*(Scenario!$F34<=W2) -> 1800 | X26: =($F26*Scenario!$F$35)*(Scenario!$F34<=X2) -> 1800 | ... Z26: =($F26*Scenario!$F$35)*(Scenario!$F34<=Z2) -> 1800
D27: New Zealand | E27: ths t | G27: 2430 | H27: 2430 | I27: 2430 | J27: 2430 | K27: 2430 | L27: 2430 | M27: 2200 | N27: 2200 | O27: 2200 | P27: 2200 | Q27: =P27 -> 2200 | R27: =Q27 -> 2200 | S27: =R27 -> 2200 | T27: =S27 -> 2200 | U27: =T27 -> 2200 | V27: =U27 -> 2200 | W27: =V27 -> 2200 | X27: =W27 -> 2200 | ... Z27: =Y27 -> 2200
D28: Trinidad (Methanex interest) | E28: ths t | G28: 2000 | H28: 2000 | I28: 2000 | J28: 2000 | K28: 2000 | L28: 2000 | M28: 2000 | N28: 2000 | O28: 1960 | P28: 1960 | Q28: =P28 -> 1960 | R28: =Q28 -> 1960 | S28: =R28 -> 1960 | T28: =S28 -> 1960 | U28: =T28 -> 1960 | V28: =U28 -> 1960 | W28: =V28 -> 1960 | X28: =W28 -> 1960 | ... Z28: =Y28 -> 1960
D29: Chile | E29: ths t | G29: 1720 | H29: 1720 | I29: 1720 | J29: 1720 | K29: 1720 | L29: 1720 | M29: 1720 | N29: 1720 | O29: 1700 | P29: 1700 | Q29: =P29 -> 1700 | R29: =Q29 -> 1700 | S29: =R29 -> 1700 | T29: =S29 -> 1700 | U29: =T29 -> 1700 | V29: =U29 -> 1700 | W29: =V29 -> 1700 | X29: =W29 -> 1700 | ... Z29: =Y29 -> 1700
D30: Egypt (50% interest) | E30: ths t | G30: 630 | H30: 630 | I30: 630 | J30: 630 | K30: 630 | L30: 630 | M30: 630 | N30: 630 | O30: 630 | P30: 630 | Q30: =P30 -> 630 | R30: =Q30 -> 630 | S30: =R30 -> 630 | T30: =S30 -> 630 | U30: =T30 -> 630 | V30: =U30 -> 630 | W30: =V30 -> 630 | X30: =W30 -> 630 | ... Z30: =Y30 -> 630
D31: Canada (Medicine Hat) | E31: ths t | G31: 560 | H31: 560 | I31: 600 | J31: 600 | K31: 600 | L31: 600 | M31: 600 | N31: 600 | O31: 640 | P31: 640 | Q31: =P31 -> 640 | R31: =Q31 -> 640 | S31: =R31 -> 640 | T31: =S31 -> 640 | U31: =T31 -> 640 | V31: =U31 -> 640 | W31: =V31 -> 640 | X31: =W31 -> 640 | ... Z31: =Y31 -> 640
D33: Production | E33: % | F33: =Scenario!F14 -> 1 | G33: =IFERROR(G42/G24,) -> 0.52086331 | H33: =IFERROR(H42/H24,) -> 0.58189448 | I33: =IFERROR(I42/I24,) -> 0.55362473 | J33: =IFERROR(J42/J24,) -> 0.74808102 | K33: =IFERROR(K42/K24,) -> 0.76620469 | L33: =IFERROR(L42/L24,) -> 0.76876333 | M33: =IFERROR(M42/M24,) -> 0.82939891 | N33: =IFERROR(N42/N24,) -> 0.72284153 | ... Z33: =IFERROR(Z42/Z24,) -> 0.6952381
D34: USA (Geismar 1 & 2) | E34: % | G34: =IFERROR(G43/G25,) -> 0 | H34: =IFERROR(H43/H25,) -> 0 | I34: =IFERROR(I43/I25,) -> 0.4795 | J34: =IFERROR(J43/J25,) -> 1.0275 | K34: =IFERROR(K43/K25,) -> 0.9675 | L34: =IFERROR(L43/L25,) -> 1.039 | M34: =IFERROR(M43/M25,) -> 0.9645 | N34: =IFERROR(N43/N25,) -> 1.02 | ... P34: =IFERROR(P43/P25,) -> 0.92772727 | Q34: =CHOOSE($F$33,P34,AVERAGE($G34:$P34),Scenario!$F$15) -> 0.92772727 | R34: =CHOOSE($F$33,Q34,AVERAGE($G34:$P34),Scenario!$F$15) -> 0.92772727 | S34: =CHOOSE($F$33,R34,AVERAGE($G34:$P34),Scenario!$F$15) -> 0.92772727 | T34: =CHOOSE($F$33,S34,AVERAGE($G34:$P34),Scenario!$F$15) -> 0.92772727 | U34: =CHOOSE($F$33,T34,AVERAGE($G34:$P34),Scenario!$F$15) -> 0.92772727 | V34: =CHOOSE($F$33,U34,AVERAGE($G34:$P34),Scenario!$F$15) -> 0.92772727 | W34: =CHOOSE($F$33,V34,AVERAGE($G34:$P34),Scenario!$F$15) -> 0.92772727 | X34: =CHOOSE($F$33,W34,AVERAGE($G34:$P34),Scenario!$F$15) -> 0.92772727 | ... Z34: =CHOOSE($F$33,Y34,AVERAGE($G34:$P34),Scenario!$F$15) -> 0.92772727
D35: USA (Geismar 3) | E35: ths t | F35: =Scenario!$F$33 -> 1 | G35: =IFERROR(G44/G26,) -> 0 | H35: =IFERROR(H44/H26,) -> 0 | I35: =IFERROR(I44/I26,) -> 0 | J35: =IFERROR(J44/J26,) -> 0 | K35: =IFERROR(K44/K26,) -> 0 | L35: =IFERROR(L44/L26,) -> 0 | M35: =IFERROR(M44/M26,) -> 0 | N35: =IFERROR(N44/N26,) -> 0 | ... P35: =IFERROR(P44/P26,) -> 0 | Q35: =($F35*Scenario!$F$36)*(Scenario!$F34<=Q2) -> 0 | R35: =($F35*Scenario!$F$36)*(Scenario!$F34<=R2) -> 0.9 | S35: =($F35*Scenario!$F$36)*(Scenario!$F34<=S2) -> 0.9 | T35: =($F35*Scenario!$F$36)*(Scenario!$F34<=T2) -> 0.9 | U35: =($F35*Scenario!$F$36)*(Scenario!$F34<=U2) -> 0.9 | V35: =($F35*Scenario!$F$36)*(Scenario!$F34<=V2) -> 0.9 | W35: =($F35*Scenario!$F$36)*(Scenario!$F34<=W2) -> 0.9 | X35: =($F35*Scenario!$F$36)*(Scenario!$F34<=X2) -> 0.9 | ... Z35: =($F35*Scenario!$F$36)*(Scenario!$F34<=Z2) -> 0.9
D36: New Zealand | E36: % | G36: =IFERROR(G45/G27,) -> 0.58395062 | H36: =IFERROR(H45/H27,) -> 0.9037037 | I36: =IFERROR(I45/I27,) -> 0.76378601 | J36: =IFERROR(J45/J27,) -> 0.89753086 | K36: =IFERROR(K45/K27,) -> 0.79958848 | L36: =IFERROR(L45/L27,) -> 0.66090535 | M36: =IFERROR(M45/M27,) -> 0.84772727 | N36: =IFERROR(N45/N27,) -> 0.76 | ... P36: =IFERROR(P45/P27,) -> 0.55909091 | Q36: =CHOOSE($F$33,P36,AVERAGE($G36:$P36),Scenario!$F$15) -> 0.55909091 | R36: =CHOOSE($F$33,Q36,AVERAGE($G36:$P36),Scenario!$F$15) -> 0.55909091 | S36: =CHOOSE($F$33,R36,AVERAGE($G36:$P36),Scenario!$F$15) -> 0.55909091 | T36: =CHOOSE($F$33,S36,AVERAGE($G36:$P36),Scenario!$F$15) -> 0.55909091 | U36: =CHOOSE($F$33,T36,AVERAGE($G36:$P36),Scenario!$F$15) -> 0.55909091 | V36: =CHOOSE($F$33,U36,AVERAGE($G36:$P36),Scenario!$F$15) -> 0.55909091 | W36: =CHOOSE($F$33,V36,AVERAGE($G36:$P36),Scenario!$F$15) -> 0.55909091 | X36: =CHOOSE($F$33,W36,AVERAGE($G36:$P36),Scenario!$F$15) -> 0.55909091 | ... Z36: =CHOOSE($F$33,Y36,AVERAGE($G36:$P36),Scenario!$F$15) -> 0.55909091
D37: Trinidad (Methanex interest) | E37: % | G37: =IFERROR(G46/G28,) -> 0.811 | H37: =IFERROR(H46/H28,) -> 0.7855 | I37: =IFERROR(I46/I28,) -> 0.822 | J37: =IFERROR(J46/J28,) -> 0.8025 | K37: =IFERROR(K46/K28,) -> 0.884 | L37: =IFERROR(L46/L28,) -> 0.851 | M37: =IFERROR(M46/M28,) -> 0.8715 | N37: =IFERROR(N46/N28,) -> 0.499 | ... P37: =IFERROR(P46/P28,) -> 0.5005102 | Q37: =CHOOSE($F$33,P37,AVERAGE($G37:$P37),Scenario!$F$15) -> 0.5005102 | R37: =CHOOSE($F$33,Q37,AVERAGE($G37:$P37),Scenario!$F$15) -> 0.5005102 | S37: =CHOOSE($F$33,R37,AVERAGE($G37:$P37),Scenario!$F$15) -> 0.5005102 | T37: =CHOOSE($F$33,S37,AVERAGE($G37:$P37),Scenario!$F$15) -> 0.5005102 | U37: =CHOOSE($F$33,T37,AVERAGE($G37:$P37),Scenario!$F$15) -> 0.5005102 | V37: =CHOOSE($F$33,U37,AVERAGE($G37:$P37),Scenario!$F$15) -> 0.5005102 | W37: =CHOOSE($F$33,V37,AVERAGE($G37:$P37),Scenario!$F$15) -> 0.5005102 | X37: =CHOOSE($F$33,W37,AVERAGE($G37:$P37),Scenario!$F$15) -> 0.5005102 | ... Z37: =CHOOSE($F$33,Y37,AVERAGE($G37:$P37),Scenario!$F$15) -> 0.5005102
D38: Chile | E38: % | G38: =IFERROR(G47/G29,) -> 0.11860465 | H38: =IFERROR(H47/H29,) -> 0.095930233 | I38: =IFERROR(I47/I29,) -> 0.11860465 | J38: =IFERROR(J47/J29,) -> 0.22965116 | K38: =IFERROR(K47/K29,) -> 0.24069767 | L38: =IFERROR(L47/L29,) -> 0.35581395 | M38: =IFERROR(M47/M29,) -> 0.61046512 | N38: =IFERROR(N47/N29,) -> 0.48604651 | ... P38: =IFERROR(P47/P29,) -> 0.52235294 | Q38: =CHOOSE($F$33,P38,AVERAGE($G38:$P38),Scenario!$F$15) -> 0.52235294 | R38: =CHOOSE($F$33,Q38,AVERAGE($G38:$P38),Scenario!$F$15) -> 0.52235294 | S38: =CHOOSE($F$33,R38,AVERAGE($G38:$P38),Scenario!$F$15) -> 0.52235294 | T38: =CHOOSE($F$33,S38,AVERAGE($G38:$P38),Scenario!$F$15) -> 0.52235294 | U38: =CHOOSE($F$33,T38,AVERAGE($G38:$P38),Scenario!$F$15) -> 0.52235294 | V38: =CHOOSE($F$33,U38,AVERAGE($G38:$P38),Scenario!$F$15) -> 0.52235294 | W38: =CHOOSE($F$33,V38,AVERAGE($G38:$P38),Scenario!$F$15) -> 0.52235294 | X38: =CHOOSE($F$33,W38,AVERAGE($G38:$P38),Scenario!$F$15) -> 0.52235294 | ... Z38: =CHOOSE($F$33,Y38,AVERAGE($G38:$P38),Scenario!$F$15) -> 0.52235294
D39: Egypt (50% interest) | E39: % | G39: =IFERROR(G48/G30,) -> 0.98888889 | H39: =IFERROR(H48/H30,) -> 0.66031746 | I39: =IFERROR(I48/I30,) -> 0.11746032 | J39: =IFERROR(J48/J30,) -> 0.46507937 | K39: =IFERROR(K48/K30,) -> 0.84761905 | L39: =IFERROR(L48/L30,) -> 0.97301587 | M39: =IFERROR(M48/M30,) -> 0.62222222 | N39: =IFERROR(N48/N30,) -> 0.91746032 | ... P39: =IFERROR(P48/P30,) -> 0.61111111 | Q39: =CHOOSE($F$33,P39,AVERAGE($G39:$P39),Scenario!$F$15) -> 0.61111111 | R39: =CHOOSE($F$33,Q39,AVERAGE($G39:$P39),Scenario!$F$15) -> 0.61111111 | S39: =CHOOSE($F$33,R39,AVERAGE($G39:$P39),Scenario!$F$15) -> 0.61111111 | T39: =CHOOSE($F$33,S39,AVERAGE($G39:$P39),Scenario!$F$15) -> 0.61111111 | U39: =CHOOSE($F$33,T39,AVERAGE($G39:$P39),Scenario!$F$15) -> 0.61111111 | V39: =CHOOSE($F$33,U39,AVERAGE($G39:$P39),Scenario!$F$15) -> 0.61111111 | W39: =CHOOSE($F$33,V39,AVERAGE($G39:$P39),Scenario!$F$15) -> 0.61111111 | X39: =CHOOSE($F$33,W39,AVERAGE($G39:$P39),Scenario!$F$15) -> 0.61111111 | ... Z39: =CHOOSE($F$33,Y39,AVERAGE($G39:$P39),Scenario!$F$15) -> 0.61111111
D40: Canada (Medicine Hat) | E40: % | G40: =IFERROR(G49/G31,) -> 0.85 | H40: =IFERROR(H49/H31,) -> 0.90178571 | I40: =IFERROR(I49/I31,) -> 0.76 | J40: =IFERROR(J49/J31,) -> 0.81333333 | K40: =IFERROR(K49/K31,) -> 0.98833333 | L40: =IFERROR(L49/L31,) -> 1 | M40: =IFERROR(M49/M31,) -> 1.0166667 | N40: =IFERROR(N49/N31,) -> 0.81666667 | ... P40: =IFERROR(P49/P31,) -> 0.9265625 | Q40: =CHOOSE($F$33,P40,AVERAGE($G40:$P40),Scenario!$F$15) -> 0.9265625 | R40: =CHOOSE($F$33,Q40,AVERAGE($G40:$P40),Scenario!$F$15) -> 0.9265625 | S40: =CHOOSE($F$33,R40,AVERAGE($G40:$P40),Scenario!$F$15) -> 0.9265625 | T40: =CHOOSE($F$33,S40,AVERAGE($G40:$P40),Scenario!$F$15) -> 0.9265625 | U40: =CHOOSE($F$33,T40,AVERAGE($G40:$P40),Scenario!$F$15) -> 0.9265625 | V40: =CHOOSE($F$33,U40,AVERAGE($G40:$P40),Scenario!$F$15) -> 0.9265625 | W40: =CHOOSE($F$33,V40,AVERAGE($G40:$P40),Scenario!$F$15) -> 0.9265625 | X40: =CHOOSE($F$33,W40,AVERAGE($G40:$P40),Scenario!$F$15) -> 0.9265625 | ... Z40: =CHOOSE($F$33,Y40,AVERAGE($G40:$P40),Scenario!$F$15) -> 0.9265625
D42: Total production | E42: ths t | G42: =SUM(G43:G49) -> 4344 | H42: =SUM(H43:H49) -> 4853 | I42: =SUM(I43:I49) -> 5193 | J42: =SUM(J43:J49) -> 7017 | K42: =SUM(K43:K49) -> 7187 | L42: =SUM(L43:L49) -> 7211 | M42: =SUM(M43:M49) -> 7589 | N42: =SUM(N43:N49) -> 6614 | ... Z42: =SUM(Z43:Z49) -> 7738
D43: USA (Geismar 1 & 2) | E43: ths t | G43: 0 | H43: 0 | I43: 959 | J43: 2055 | K43: 1935 | L43: 2078 | M43: 1929 | N43: 2040 | O43: 1989 | P43: 2041 | Q43: =Q34*Q25 -> 2041 | R43: =R34*R25 -> 2041 | S43: =S34*S25 -> 2041 | T43: =T34*T25 -> 2041 | U43: =U34*U25 -> 2041 | V43: =V34*V25 -> 2041 | W43: =W34*W25 -> 2041 | X43: =X34*X25 -> 2041 | ... Z43: =Z34*Z25 -> 2041
D44: USA (Geismar 3) | E44: ths t | G44: 0 | H44: 0 | I44: 0 | J44: 0 | K44: 0 | L44: 0 | M44: 0 | N44: 0 | O44: 0 | P44: 0 | Q44: =Q35*Q26 -> 0 | R44: =R35*R26 -> 1620 | S44: =S35*S26 -> 1620 | T44: =T35*T26 -> 1620 | U44: =U35*U26 -> 1620 | V44: =V35*V26 -> 1620 | W44: =W35*W26 -> 1620 | X44: =X35*X26 -> 1620 | ... Z44: =Z35*Z26 -> 1620
D45: New Zealand | E45: ths t | G45: 1419 | H45: 2196 | I45: 1856 | J45: 2181 | K45: 1943 | L45: 1606 | M45: 1865 | N45: 1672 | O45: 1348 | P45: 1230 | Q45: =Q36*Q27 -> 1230 | R45: =R36*R27 -> 1230 | S45: =S36*S27 -> 1230 | T45: =T36*T27 -> 1230 | U45: =U36*U27 -> 1230 | V45: =V36*V27 -> 1230 | W45: =W36*W27 -> 1230 | X45: =X36*X27 -> 1230 | ... Z45: =Z36*Z27 -> 1230
D46: Trinidad (Methanex interest) | E46: ths t | G46: =651+971 -> 1622 | H46: =907+664 -> 1571 | I46: 1644 | J46: 1605 | K46: 1768 | L46: 1702 | M46: 1743 | N46: 998 | O46: 1161 | P46: 981 | Q46: =Q37*Q28 -> 981 | R46: =R37*R28 -> 981 | S46: =S37*S28 -> 981 | T46: =T37*T28 -> 981 | U46: =U37*U28 -> 981 | V46: =V37*V28 -> 981 | W46: =W37*W28 -> 981 | X46: =X37*X28 -> 981 | ... Z46: =Z37*Z28 -> 981
D47: Chile | E47: ths t | G47: 204 | H47: 165 | I47: 204 | J47: 395 | K47: 414 | L47: 612 | M47: 1050 | N47: 836 | O47: 807 | P47: 888 | Q47: =Q38*Q29 -> 888 | R47: =R38*R29 -> 888 | S47: =S38*S29 -> 888 | T47: =T38*T29 -> 888 | U47: =U38*U29 -> 888 | V47: =V38*V29 -> 888 | W47: =W38*W29 -> 888 | X47: =X38*X29 -> 888 | ... Z47: =Z38*Z29 -> 888
D48: Egypt (50% interest) | E48: ths t | G48: 623 | H48: 416 | I48: 74 | J48: 293 | K48: 534 | L48: 613 | M48: 392 | N48: 578 | O48: 581 | P48: 385 | Q48: =Q39*Q30 -> 385 | R48: =R39*R30 -> 385 | S48: =S39*S30 -> 385 | T48: =T39*T30 -> 385 | U48: =U39*U30 -> 385 | V48: =V39*V30 -> 385 | W48: =W39*W30 -> 385 | X48: =X39*X30 -> 385 | ... Z48: =Z39*Z30 -> 385
D49: Canada (Medicine Hat) | E49: ths t | G49: 476 | H49: 505 | I49: 456 | J49: 488 | K49: 593 | L49: 600 | M49: 610 | N49: 490 | O49: 628 | P49: 593 | Q49: =Q40*Q31 -> 593 | R49: =R40*R31 -> 593 | S49: =S40*S31 -> 593 | T49: =T40*T31 -> 593 | U49: =U40*U31 -> 593 | V49: =V40*V31 -> 593 | W49: =W40*W31 -> 593 | X49: =X40*X31 -> 593 | ... Z49: =Z40*Z31 -> 593
C52: Sales
D54: Methanex-produced methanol | E54: ths t | G54: 4304 | H54: 4878 | I54: 5050 | J54: 6828 | K54: 7229 | L54: 7002 | M54: 7611 | N54: 6704 | O54: 6207 | P54: 6141 | Q54: =Q55*Q$42 -> 6118 | R54: =R55*R$42 -> 7738 | S54: =S55*S$42 -> 7738 | T54: =T55*T$42 -> 7738 | U54: =U55*U$42 -> 7738 | V54: =V55*V$42 -> 7738 | W54: =W55*W$42 -> 7738 | X54: =X55*X$42 -> 7738 | ... Z54: =Z55*Z$42 -> 7738
D55: % of total production | E55: % | F55: =Scenario!F16 -> 3 | G55: =G54/G$42 -> 0.9907919 | H55: =H54/H$42 -> 1.0051515 | I55: =I54/I$42 -> 0.97246293 | J55: =J54/J$42 -> 0.97306541 | K55: =K54/K$42 -> 1.0058439 | L55: =L54/L$42 -> 0.9710165 | M55: =M54/M$42 -> 1.0028989 | N55: =N54/N$42 -> 1.0136075 | ... P55: =P54/P$42 -> 1.0037594 | Q55: =CHOOSE($F$55,P55,AVERAGE($G55:$P55),Scenario!$F$17) -> 1 | R55: =CHOOSE($F$55,Q55,AVERAGE($G55:$P55),Scenario!$F$17) -> 1 | S55: =CHOOSE($F$55,R55,AVERAGE($G55:$P55),Scenario!$F$17) -> 1 | T55: =CHOOSE($F$55,S55,AVERAGE($G55:$P55),Scenario!$F$17) -> 1 | U55: =CHOOSE($F$55,T55,AVERAGE($G55:$P55),Scenario!$F$17) -> 1 | V55: =CHOOSE($F$55,U55,AVERAGE($G55:$P55),Scenario!$F$17) -> 1 | W55: =CHOOSE($F$55,V55,AVERAGE($G55:$P55),Scenario!$F$17) -> 1 | X55: =CHOOSE($F$55,W55,AVERAGE($G55:$P55),Scenario!$F$17) -> 1 | ... Z55: =CHOOSE($F$55,Y55,AVERAGE($G55:$P55),Scenario!$F$17) -> 1
D57: Purchased methanol | E57: ths t | G57: 2715 | H57: 2685 | I57: 2780 | J57: 1892 | K57: 2289 | L57: 3032 | M57: 2492 | N57: 2994 | O57: 3750 | P57: 3688 | Q57: =Q58*SUM(Q$43,Q$45:Q$49) -> 2864.2849 | R57: =R58*SUM(R$43,R$45:R$49) -> 2864.2849 | S57: =S58*SUM(S$43,S$45:S$49) -> 2864.2849 | T57: =T58*SUM(T$43,T$45:T$49) -> 2864.2849 | U57: =U58*SUM(U$43,U$45:U$49) -> 2864.2849 | V57: =V58*SUM(V$43,V$45:V$49) -> 2864.2849 | W57: =W58*SUM(W$43,W$45:W$49) -> 2864.2849 | X57: =X58*SUM(X$43,X$45:X$49) -> 2864.2849 | ... Z57: =Z58*SUM(Z$43,Z$45:Z$49) -> 2864.2849
D58: % of total production | E58: % | F58: =Scenario!F18 -> 2 | G58: =G57/SUM(G$43,G$45:G$49) -> 0.625 | H58: =H57/SUM(H$43,H$45:H$49) -> 0.55326602 | I58: =I57/SUM(I$43,I$45:I$49) -> 0.53533603 | J58: =J57/SUM(J$43,J$45:J$49) -> 0.2696309 | K58: =K57/SUM(K$43,K$45:K$49) -> 0.31849172 | L58: =L57/SUM(L$43,L$45:L$49) -> 0.42046873 | M58: =M57/SUM(M$43,M$45:M$49) -> 0.32837001 | N58: =N57/SUM(N$43,N$45:N$49) -> 0.45267614 | ... P58: =P57/SUM(P$43,P$45:P$49) -> 0.60281138 | Q58: =CHOOSE($F$58,P58,AVERAGE($G58:$P58),Scenario!$F$19) -> 0.46817341 | R58: =CHOOSE($F$58,Q58,AVERAGE($G58:$P58),Scenario!$F$19) -> 0.46817341 | S58: =CHOOSE($F$58,R58,AVERAGE($G58:$P58),Scenario!$F$19) -> 0.46817341 | T58: =CHOOSE($F$58,S58,AVERAGE($G58:$P58),Scenario!$F$19) -> 0.46817341 | U58: =CHOOSE($F$58,T58,AVERAGE($G58:$P58),Scenario!$F$19) -> 0.46817341 | V58: =CHOOSE($F$58,U58,AVERAGE($G58:$P58),Scenario!$F$19) -> 0.46817341 | W58: =CHOOSE($F$58,V58,AVERAGE($G58:$P58),Scenario!$F$19) -> 0.46817341 | X58: =CHOOSE($F$58,W58,AVERAGE($G58:$P58),Scenario!$F$19) -> 0.46817341 | ... Z58: =CHOOSE($F$58,Y58,AVERAGE($G58:$P58),Scenario!$F$19) -> 0.46817341
D60: Commission sales | E60: ths t | G60: 972 | H60: 941 | I60: 641 | J60: 758 | K60: 1151 | L60: 1174 | M60: 1031 | N60: 1042 | O60: 1227 | P60: 945 | Q60: =Q61*SUM(Q$43,Q$45:Q$49) -> 983.95693 | R60: =R61*SUM(R$43,R$45:R$49) -> 983.95693 | S60: =S61*SUM(S$43,S$45:S$49) -> 983.95693 | T60: =T61*SUM(T$43,T$45:T$49) -> 983.95693 | U60: =U61*SUM(U$43,U$45:U$49) -> 983.95693 | V60: =V61*SUM(V$43,V$45:V$49) -> 983.95693 | W60: =W61*SUM(W$43,W$45:W$49) -> 983.95693 | X60: =X61*SUM(X$43,X$45:X$49) -> 983.95693 | ... Z60: =Z61*SUM(Z$43,Z$45:Z$49) -> 983.95693
D61: % of total production | E61: % | F61: =Scenario!F20 -> 2 | G61: =G60/SUM(G$43,G$45:G$49) -> 0.22375691 | H61: =H60/SUM(H$43,H$45:H$49) -> 0.19390068 | I61: =I60/SUM(I$43,I$45:I$49) -> 0.12343539 | J61: =J60/SUM(J$43,J$45:J$49) -> 0.10802337 | K61: =K60/SUM(K$43,K$45:K$49) -> 0.16015027 | L61: =L60/SUM(L$43,L$45:L$49) -> 0.16280682 | M61: =M60/SUM(M$43,M$45:M$49) -> 0.13585453 | N61: =N60/SUM(N$43,N$45:N$49) -> 0.1575446 | ... P61: =P60/SUM(P$43,P$45:P$49) -> 0.15446224 | Q61: =CHOOSE($F$61,P61,AVERAGE($G61:$P61),Scenario!$F$21) -> 0.16082983 | R61: =CHOOSE($F$61,Q61,AVERAGE($G61:$P61),Scenario!$F$21) -> 0.16082983 | S61: =CHOOSE($F$61,R61,AVERAGE($G61:$P61),Scenario!$F$21) -> 0.16082983 | T61: =CHOOSE($F$61,S61,AVERAGE($G61:$P61),Scenario!$F$21) -> 0.16082983 | U61: =CHOOSE($F$61,T61,AVERAGE($G61:$P61),Scenario!$F$21) -> 0.16082983 | V61: =CHOOSE($F$61,U61,AVERAGE($G61:$P61),Scenario!$F$21) -> 0.16082983 | W61: =CHOOSE($F$61,V61,AVERAGE($G61:$P61),Scenario!$F$21) -> 0.16082983 | X61: =CHOOSE($F$61,W61,AVERAGE($G61:$P61),Scenario!$F$21) -> 0.16082983 | ... Z61: =CHOOSE($F$61,Y61,AVERAGE($G61:$P61),Scenario!$F$21) -> 0.16082983
D63: Total sales volume | E63: ths t | G63: =G54+G57+G60 -> 7991 | H63: =H54+H57+H60 -> 8504 | I63: =I54+I57+I60 -> 8471 | J63: =J54+J57+J60 -> 9478 | K63: =K54+K57+K60 -> 10669 | L63: =L54+L57+L60 -> 11208 | M63: =M54+M57+M60 -> 11134 | N63: =N54+N57+N60 -> 10740 | ... Z63: =Z54+Z57+Z60 -> 11586.242
C66: Price
D68: Average realized price | E68: $/t | G68: =IFERROR(G78/G63*1000,0) -> 378.43161 | H68: =IFERROR(H78/H63*1000,0) -> 379.04504 | I68: =IFERROR(I78/I63*1000,0) -> 262.73191 | J68: =IFERROR(J78/J63*1000,0) -> 210.84923 | K68: =IFERROR(K78/K63*1000,0) -> 286.87243 | L68: =IFERROR(L78/L63*1000,0) -> 350.80719 | M68: =IFERROR(M78/M63*1000,0) -> 294.90875 | N68: =IFERROR(N78/N63*1000,0) -> 246.73771 | ... P68: =IFERROR(P78/P63*1000,0) -> 400.14739 | Q68: =(Q70/P70)*P68 -> 317.93225 | R68: =(R70/Q70)*Q68 -> 380.43867 | S68: =(S70/R70)*R68 -> 421.83693 | T68: =(T70/S70)*S68 -> 407.31583 | U68: =(U70/T70)*T68 -> 406.85635 | V68: =(V70/U70)*U68 -> 408.48377 | W68: =(W70/V70)*V68 -> 410.11771 | X68: =(X70/W70)*W68 -> 411.75818 | ... Z68: =(Z70/Y70)*Y68 -> 415.05883
D70: Price (scanerio) | E70: $/t | F70: =Scenario!F22 -> 1 | G70: =CHOOSE($F70,G71,G72,G73) -> 499.14801 | H70: =CHOOSE($F70,H71,H72,H73) -> 388.20847 | I70: =CHOOSE($F70,I71,I72,I73) -> 309 | J70: =CHOOSE($F70,J71,J72,J73) -> 228 | K70: =CHOOSE($F70,K71,K72,K73) -> 336 | L70: =CHOOSE($F70,L71,L72,L73) -> 404 | M70: =CHOOSE($F70,M71,M72,M73) -> 268.45 | N70: =CHOOSE($F70,N71,N72,N73) -> 242.00492 | ... Z70: =CHOOSE($F70,Z71,Z72,Z73) -> 394.05189
D71: Sber (base) | E71: $/t | G71: =Inputs!V340 -> 499.14801 | H71: =Inputs!W340 -> 388.20847 | I71: =Inputs!X340 -> 309 | J71: =Inputs!Y340 -> 228 | K71: =Inputs!Z340 -> 336 | L71: =Inputs!AA340 -> 404 | M71: =Inputs!AB340 -> 268.45 | N71: =Inputs!AC340 -> 242.00492 | ... Z71: =Inputs!AO340 -> 394.05189
D72: Sber (negative) | E72: $/t | G72: ='Inputs sber (-)'!V340 -> 499.14801 | H72: ='Inputs sber (-)'!W340 -> 388.20847 | I72: ='Inputs sber (-)'!X340 -> 309 | J72: ='Inputs sber (-)'!Y340 -> 228 | K72: ='Inputs sber (-)'!Z340 -> 336 | L72: ='Inputs sber (-)'!AA340 -> 404 | M72: ='Inputs sber (-)'!AB340 -> 268.45 | N72: ='Inputs sber (-)'!AC340 -> 242.00492 | ... Z72: ='Inputs sber (-)'!AO340 -> 300.01727
D73: Sber (optimistic) | E73: $/t | G73: ='Inputs sber (+)'!V340 -> 499.14801 | H73: ='Inputs sber (+)'!W340 -> 388.20847 | I73: ='Inputs sber (+)'!X340 -> 309 | J73: ='Inputs sber (+)'!Y340 -> 228 | K73: ='Inputs sber (+)'!Z340 -> 336 | L73: ='Inputs sber (+)'!AA340 -> 404 | M73: ='Inputs sber (+)'!AB340 -> 268.45 | N73: ='Inputs sber (+)'!AC340 -> 242.00492 | ... Z73: ='Inputs sber (+)'!AO340 -> 401.25694
C76: Revenue
D78: Revenue | E78: mn $ | G78: 3024.047 | H78: 3223.399 | I78: 2225.602 | J78: 1998.429 | K78: 3060.642 | L78: 3931.847 | M78: 3283.514 | N78: 2649.963 | O78: 4414.559 | P78: 4311.188 | Q78: =Q68*Q63/1000 -> 3168.5897 | R78: =R68*R63/1000 -> 4407.8544 | S78: =S68*S63/1000 -> 4887.5047 | T78: =T68*T63/1000 -> 4719.2597 | U78: =U68*U63/1000 -> 4713.936 | V78: =V68*V63/1000 -> 4732.7918 | W78: =W68*W63/1000 -> 4751.723 | X78: =X68*X63/1000 -> 4770.7298 | ... Z78: =Z68*Z63/1000 -> 4808.972
B82: OpEx
C84: Cost of raw materials and purchased methanol
D86: Natural gas price Henry Hub | E86: % | J86: =J13/I13-1 -> -0.044982964 | K86: =K13/J13-1 -> 0.18772549 | L86: =L13/K13-1 -> 0.06351885 | M86: =M13/L13-1 -> -0.18679191 | N86: =N13/M13-1 -> -0.2123248 | O86: =O13/N13-1 -> 0.90813485 | P86: =P13/O13-1 -> 0.68536462 | Q86: =Q13/P13-1 -> -0.53498467 | ... Z86: =Z13/Y13-1 -> 0.004
D87: Cost of raw materials | E87: % | J87: =J89/I89-1 -> -0.26823507 | K87: =K89/J89-1 -> 0.27511545 | L87: =L89/K89-1 -> 0.27429157 | M87: =M89/L89-1 -> -0.0036832863 | N87: =N89/M89-1 -> -0.1849112 | O87: =O89/N89-1 -> 0.54278615 | P87: =P89/O89-1 -> 0.057037846 | Q87: =CORREL($J$86:$P$86,$J$87:$P$87)*Q86 -> -0.37039497 | R87: =CORREL($J$86:$P$86,$J$87:$P$87)*R86 -> 0.20355362 | S87: =CORREL($J$86:$P$86,$J$87:$P$87)*S86 -> 0.056668517 | T87: =CORREL($J$86:$P$86,$J$87:$P$87)*T86 -> -0.003080378 | U87: =CORREL($J$86:$P$86,$J$87:$P$87)*U86 -> -0.0096464699 | V87: =CORREL($J$86:$P$86,$J$87:$P$87)*V86 -> 0.0027693875 | W87: =CORREL($J$86:$P$86,$J$87:$P$87)*W86 -> 0.0027693875 | X87: =CORREL($J$86:$P$86,$J$87:$P$87)*X86 -> 0.0027693875 | ... Z87: =CORREL($J$86:$P$86,$J$87:$P$87)*Z86 -> 0.0027693875
D89: Cost of raw materials | E89: $/t | F89: =Scenario!F25 -> 1 | G89: =G91/G$63*1000 -> 207.87636 | H89: =H91/H$63*1000 -> 217.20814 | I89: =I91/I$63*1000 -> 164.44717 | J89: =J91/J$63*1000 -> 120.33667 | K89: =K91/K$63*1000 -> 153.44315 | L89: =L91/L$63*1000 -> 195.53132 | M89: =M91/M$63*1000 -> 194.81112 | N89: =N91/N$63*1000 -> 158.78836 | ... P89: =P91/P$63*1000 -> 258.94942 | Q89: =CHOOSE($F89,(Q$70/P$70)*P89,P89*(1+Q$8),P89*(1+Q87)) -> 205.74511 | R89: =CHOOSE($F89,(R$70/Q$70)*Q89,Q89*(1+R$8),Q89*(1+R87)) -> 246.19521 | S89: =CHOOSE($F89,(S$70/R$70)*R89,R89*(1+S$8),R89*(1+S87)) -> 272.98548 | T89: =CHOOSE($F89,(T$70/S$70)*S89,S89*(1+T$8),S89*(1+T87)) -> 263.58836 | U89: =CHOOSE($F89,(U$70/T$70)*T89,T89*(1+U$8),T89*(1+U87)) -> 263.29102 | V89: =CHOOSE($F89,(V$70/U$70)*U89,U89*(1+V$8),U89*(1+V87)) -> 264.34418 | W89: =CHOOSE($F89,(W$70/V$70)*V89,V89*(1+W$8),V89*(1+W87)) -> 265.40156 | X89: =CHOOSE($F89,(X$70/W$70)*W89,W89*(1+X$8),W89*(1+X87)) -> 266.46316 | ... Z89: =CHOOSE($F89,(Z$70/Y$70)*Y89,Y89*(1+Z$8),Y89*(1+Z87)) -> 268.59913
D90: Cost of purchased methanol | E90: $/t | F90: =Scenario!F26 -> 1 | G90: =G91/G$63*1000 -> 207.87636 | H90: =H91/H$63*1000 -> 217.20814 | I90: =I91/I$63*1000 -> 164.44717 | J90: =J91/J$63*1000 -> 120.33667 | K90: =K91/K$63*1000 -> 153.44315 | L90: =L91/L$63*1000 -> 195.53132 | M90: =M91/M$63*1000 -> 194.81112 | N90: =N91/N$63*1000 -> 158.78836 | ... P90: =P91/P$63*1000 -> 258.94942 | Q90: =CHOOSE($F90,(Q$70/P$70)*P90,P90*(1+Q$8)) -> 205.74511 | R90: =CHOOSE($F90,(R$70/Q$70)*Q90,Q90*(1+R$8)) -> 246.19521 | S90: =CHOOSE($F90,(S$70/R$70)*R90,R90*(1+S$8)) -> 272.98548 | T90: =CHOOSE($F90,(T$70/S$70)*S90,S90*(1+T$8)) -> 263.58836 | U90: =CHOOSE($F90,(U$70/T$70)*T90,T90*(1+U$8)) -> 263.29102 | V90: =CHOOSE($F90,(V$70/U$70)*U90,U90*(1+V$8)) -> 264.34418 | W90: =CHOOSE($F90,(W$70/V$70)*V90,V90*(1+W$8)) -> 265.40156 | X90: =CHOOSE($F90,(X$70/W$70)*W90,W90*(1+X$8)) -> 266.46316 | ... Z90: =CHOOSE($F90,(Z$70/Y$70)*Y90,Y90*(1+Z$8)) -> 268.59913
D91: Cost of raw materials and purchased methanol | E91: mn $ | G91: 1661.14 | H91: 1847.138 | I91: 1393.032 | J91: 1140.551 | K91: 1637.085 | L91: 2191.515 | M91: 2169.027 | N91: 1705.387 | O91: 2739.817 | P91: 2789.921 | Q91: =(Q89*Q54/1000)+(Q90*(Q57+Q60)/1000) -> 2050.5055 | R91: =(R89*R54/1000)+(R90*(R57+R60)/1000) -> 2852.4772 | S91: =(S89*S54/1000)+(S90*(S57+S60)/1000) -> 3162.8757 | T91: =(T89*T54/1000)+(T90*(T57+T60)/1000) -> 3053.9985 | U91: =(U89*U54/1000)+(U90*(U57+U60)/1000) -> 3050.5534 | V91: =(V89*V54/1000)+(V90*(V57+V60)/1000) -> 3062.7556 | W91: =(W89*W54/1000)+(W90*(W57+W60)/1000) -> 3075.0066 | X91: =(X89*X54/1000)+(X90*(X57+X60)/1000) -> 3087.3066 | ... Z91: =(Z89*Z54/1000)+(Z90*(Z57+Z60)/1000) -> 3112.0545
C94: Ocean freight and other logistics
D96: Ocean freight and other logistics | E96: $/t | F96: =Scenario!F27 -> 1 | G96: =G97/G$63*1000 -> 32.09373 | H96: =H97/H$63*1000 -> 33.789981 | I96: =I97/I$63*1000 -> 29.913115 | J96: =J97/J$63*1000 -> 37.097383 | K96: =K97/K$63*1000 -> 35.122036 | L96: =L97/L$63*1000 -> 35.625714 | M96: =M97/M$63*1000 -> 30.056583 | N96: =N97/N$63*1000 -> 30.599162 | ... P96: =P97/P$63*1000 -> 30.248097 | Q96: =CHOOSE($F96,(Q$70/P$70)*P96,P96*(1+Q$8)) -> 24.033258 | R96: =CHOOSE($F96,(R$70/Q$70)*Q96,Q96*(1+R$8)) -> 28.758268 | S96: =CHOOSE($F96,(S$70/R$70)*R96,R96*(1+S$8)) -> 31.887661 | T96: =CHOOSE($F96,(T$70/S$70)*S96,S96*(1+T$8)) -> 30.789977 | U96: =CHOOSE($F96,(U$70/T$70)*T96,T96*(1+U$8)) -> 30.755243 | V96: =CHOOSE($F96,(V$70/U$70)*U96,U96*(1+V$8)) -> 30.878264 | W96: =CHOOSE($F96,(W$70/V$70)*V96,V96*(1+W$8)) -> 31.001777 | X96: =CHOOSE($F96,(X$70/W$70)*W96,W96*(1+X$8)) -> 31.125784 | ... Z96: =CHOOSE($F96,(Z$70/Y$70)*Y96,Y96*(1+Z$8)) -> 31.375289
D97: Ocean freight and other logistics | E97: mn $ | G97: 256.461 | H97: 287.35 | I97: 253.394 | J97: 351.609 | K97: 374.717 | L97: 399.293 | M97: 334.65 | N97: 328.635 | O97: 356.52 | P97: 325.893 | Q97: =Q96*Q$63/1000 -> 239.52126 | R97: =R96*R$63/1000 -> 333.20025 | S97: =S96*S$63/1000 -> 369.45815 | T97: =T96*T$63/1000 -> 356.74012 | U97: =U96*U$63/1000 -> 356.33769 | V97: =V96*V$63/1000 -> 357.76304 | W97: =W96*W$63/1000 -> 359.19409 | X97: =X96*X$63/1000 -> 360.63087 | ... Z97: =Z96*Z$63/1000 -> 363.52168
C100: G&A
D102: Employee expenses, including share-based compensation | E102: mn $ | F102: =Scenario!F28 -> 2 | G102: 274.463 | H102: 124.111 | I102: 113.627 | J102: 204.762 | K102: 243.707 | L102: 182.519 | M102: 184.171 | N102: 246.779 | O102: 210.849 | P102: 219.012 | Q102: =CHOOSE($F102,(Q$70/P$70)*P102,P102*(1+Q$8)) -> 225.9861 | R102: =CHOOSE($F102,(R$70/Q$70)*Q102,Q102*(1+R$8)) -> 230.63956 | S102: =CHOOSE($F102,(S$70/R$70)*R102,R102*(1+S$8)) -> 235.38885 | T102: =CHOOSE($F102,(T$70/S$70)*S102,S102*(1+T$8)) -> 240.23594 | U102: =CHOOSE($F102,(U$70/T$70)*T102,T102*(1+U$8)) -> 245.04066 | V102: =CHOOSE($F102,(V$70/U$70)*U102,U102*(1+V$8)) -> 249.94147 | W102: =CHOOSE($F102,(W$70/V$70)*V102,V102*(1+W$8)) -> 254.9403 | X102: =CHOOSE($F102,(X$70/W$70)*W102,W102*(1+X$8)) -> 260.03911 | ... Z102: =CHOOSE($F102,(Z$70/Y$70)*Y102,Y102*(1+Z$8)) -> 270.54469
D103: Other expenses | E103: mn $ | F103: =Scenario!F29 -> 2 | G103: 173.456 | H103: 167.222 | I103: 97.846 | J103: 77.507 | K103: 96.44 | L103: 83.593 | M103: 112.089 | N103: 74.322 | O103: 32.324 | P103: 111.275 | Q103: =CHOOSE($F103,(Q$70/P$70)*P103,P103*(1+Q$8)) -> 114.81838 | R103: =CHOOSE($F103,(R$70/Q$70)*Q103,Q103*(1+R$8)) -> 117.1827 | S103: =CHOOSE($F103,(S$70/R$70)*R103,R103*(1+S$8)) -> 119.59571 | T103: =CHOOSE($F103,(T$70/S$70)*S103,S103*(1+T$8)) -> 122.0584 | U103: =CHOOSE($F103,(U$70/T$70)*T103,T103*(1+U$8)) -> 124.49957 | V103: =CHOOSE($F103,(V$70/U$70)*U103,U103*(1+V$8)) -> 126.98956 | W103: =CHOOSE($F103,(W$70/V$70)*V103,V103*(1+W$8)) -> 129.52935 | X103: =CHOOSE($F103,(X$70/W$70)*W103,W103*(1+X$8)) -> 132.11994 | ... Z103: =CHOOSE($F103,(Z$70/Y$70)*Y103,Y103*(1+Z$8)) -> 137.45758
B107: CapEx
D109: Property, plant and equipment | E109: mn $ | F109: =Scenario!F32 -> 1 | G109: 269.367 | H109: 84.168 | I109: 96.909 | J109: 99.881 | K109: 103.17 | L109: 244.476 | M109: 208.467 | N109: 128.786 | O109: 103.485 | P109: 145.701 | Q109: =CHOOSE($F109,P109*(1+Q$8),Q110*Q78) -> 150.34062 | R109: =CHOOSE($F109,Q109*(1+R$8),R110*R78) -> 153.43641 | S109: =CHOOSE($F109,R109*(1+S$8),S110*S78) -> 156.59595 | T109: =CHOOSE($F109,S109*(1+T$8),T110*T78) -> 159.82054 | U109: =CHOOSE($F109,T109*(1+U$8),U110*U78) -> 163.01695 | V109: =CHOOSE($F109,U109*(1+V$8),V110*V78) -> 166.27729 | W109: =CHOOSE($F109,V109*(1+W$8),W110*W78) -> 169.60284 | X109: =CHOOSE($F109,W109*(1+X$8),X110*X78) -> 172.9949 | ... Z109: =CHOOSE($F109,Y109*(1+Z$8),Z110*Z78) -> 179.98389
D110: % of Revenue | E110: % | G110: =IFERROR(G109/G78,) -> 0.089075004 | H110: =IFERROR(H109/H78,) -> 0.026111567 | I110: =IFERROR(I109/I78,) -> 0.043542826 | J110: =IFERROR(J109/J78,) -> 0.049979759 | K110: =IFERROR(K109/K78,) -> 0.033708614 | L110: =IFERROR(L109/L78,) -> 0.062178411 | M110: =IFERROR(M109/M78,) -> 0.063488994 | N110: =IFERROR(N109/N78,) -> 0.048599169 | ... P110: =IFERROR(P109/P78,) -> 0.033796021 | Q110: =P110 -> 0.033796021 | R110: =Q110 -> 0.033796021 | S110: =R110 -> 0.033796021 | T110: =S110 -> 0.033796021 | U110: =T110 -> 0.033796021 | V110: =U110 -> 0.033796021 | W110: =V110 -> 0.033796021 | X110: =W110 -> 0.033796021 | ... Z110: =Y110 -> 0.033796021
D112: Geismar plant under construction | E112: mn $ | F112: =Scenario!F33 -> 1 | G112: 309.469 | H112: 573.844 | I112: 328.112 | M112: 115.393 | N112: 213.03 | O112: 141.952 | P112: 431.68 | Q112: =IFERROR(Scenario!$F37/(Scenario!$F34-$Q$2)*(Scenario!$F34>Q2),0)*$F112 -> 440 | R112: =IFERROR(Scenario!$F37/(Scenario!$F34-$Q$2)*(Scenario!$F34>R2),0)*$F112 -> 0 | S112: =IFERROR(Scenario!$F37/(Scenario!$F34-$Q$2)*(Scenario!$F34>S2),0)*$F112 -> 0 | T112: =IFERROR(Scenario!$F37/(Scenario!$F34-$Q$2)*(Scenario!$F34>T2),0)*$F112 -> 0 | U112: =IFERROR(Scenario!$F37/(Scenario!$F34-$Q$2)*(Scenario!$F34>U2),0)*$F112 -> 0 | V112: =IFERROR(Scenario!$F37/(Scenario!$F34-$Q$2)*(Scenario!$F34>V2),0)*$F112 -> 0 | W112: =IFERROR(Scenario!$F37/(Scenario!$F34-$Q$2)*(Scenario!$F34>W2),0)*$F112 -> 0 | X112: =IFERROR(Scenario!$F37/(Scenario!$F34-$Q$2)*(Scenario!$F34>X2),0)*$F112 -> 0 | ... Z112: =IFERROR(Scenario!$F37/(Scenario!$F34-$Q$2)*(Scenario!$F34>Z2),0)*$F112 -> 0
D113: CapEx maintenance | E113: mn $ | F113: =SUM(M112:P112,Scenario!F37)/50 -> 26.8411 | Q113: =F113 -> 26.8411 | R113: =Q113*(1+R$8) -> 27.393807 | S113: =R113*(1+S$8) -> 27.957896 | T113: =S113*(1+T$8) -> 28.5336 | U113: =T113*(1+U$8) -> 29.104272 | V113: =U113*(1+V$8) -> 29.686357 | W113: =V113*(1+W$8) -> 30.280084 | X113: =W113*(1+X$8) -> 30.885686 | Y113: =X113*(1+Y$8) -> 31.5034 | Z113: =Y113*(1+Z$8) -> 32.133468
D114: CapEx maintenance | E114: mn $ | Q114: =Q113*(Scenario!$F34<=Q2)*$F112 -> 0 | R114: =R113*(Scenario!$F34<=R2)*$F112 -> 27.393807 | S114: =S113*(Scenario!$F34<=S2)*$F112 -> 27.957896 | T114: =T113*(Scenario!$F34<=T2)*$F112 -> 28.5336 | U114: =U113*(Scenario!$F34<=U2)*$F112 -> 29.104272 | V114: =V113*(Scenario!$F34<=V2)*$F112 -> 29.686357 | W114: =W113*(Scenario!$F34<=W2)*$F112 -> 30.280084 | X114: =X113*(Scenario!$F34<=X2)*$F112 -> 30.885686 | ... Z114: =Z113*(Scenario!$F34<=Z2)*$F112 -> 32.133468
B118: PP&E
D120: PP&E bop | E120: mn $ | H120: =BS!G18 -> 2230.938 | I120: =H123 -> 2778.078 | J120: =I123 -> 3158.782 | K120: =J123 -> 3117.469 | L120: =K123 -> 2998.326 | M120: =L123 -> 3025.095 | N120: =M123 -> 3576.195 | O120: =N123 -> 3677.056 | P120: =O123 -> 3686.149 | ... Z120: =Y123 -> 3300.9022
D121: CapEx | E121: mn $ | H121: =H123-H120+H122 -> 689.878 | I121: =I123-I120+I122 -> 575.553 | J121: =J123-J120+J122 -> 186.741 | K121: =K123-K120+K122 -> 113.082 | L121: =L123-L120+L122 -> 272.072 | M121: =M123-M120+M122 -> 895.227 | N121: =N123-N120+N122 -> 457.99 | O121: =O123-O120+O122 -> 372.177 | P121: =P123-P120+P122 -> 841.554 | Q121: =Q109+Q112+Q114 -> 590.34062 | R121: =R109+R112+R114 -> 180.83022 | S121: =S109+S112+S114 -> 184.55384 | T121: =T109+T112+T114 -> 188.35414 | U121: =U109+U112+U114 -> 192.12123 | V121: =V109+V112+V114 -> 195.96365 | W121: =W109+W112+W114 -> 199.88292 | X121: =X109+X112+X114 -> 203.88058 | ... Z121: =Z109+Z112+Z114 -> 212.11736
D122: D&A | E122: mn $ | H122: 142.738 | I122: 194.849 | J122: 228.054 | K122: 232.225 | L122: 245.303 | M122: 344.127 | N122: 357.129 | O122: 363.084 | P122: 372.42 | Q122: =Q124*Q120 -> 358.28537 | R122: =R124*R120 -> 378.29411 | S122: =S124*S120 -> 361.26797 | T122: =T124*T120 -> 346.03096 | U122: =U124*U120 -> 332.43543 | V122: =V124*V120 -> 320.33697 | W122: =W124*W120 -> 309.613 | X122: =X124*X120 -> 300.15162 | ... Z122: =Z124*Z120 -> 284.61719
D123: PP&E eop | E123: mn $ | H123: =BS!H18 -> 2778.078 | I123: =BS!I18 -> 3158.782 | J123: =BS!J18 -> 3117.469 | K123: =BS!K18 -> 2998.326 | L123: =BS!L18 -> 3025.095 | M123: =BS!M18 -> 3576.195 | N123: =BS!N18 -> 3677.056 | O123: =BS!O18 -> 3686.149 | P123: =BS!P18 -> 4155.283 | Q123: =Q120+Q121-Q122 -> 4387.3383 | R123: =R120+R121-R122 -> 4189.8744 | S123: =S120+S121-S122 -> 4013.1602 | T123: =T120+T121-T122 -> 3855.4834 | U123: =U120+U121-U122 -> 3715.1692 | V123: =V120+V121-V122 -> 3590.7959 | W123: =W120+W121-W122 -> 3481.0658 | X123: =X120+X121-X122 -> 3384.7948 | ... Z123: =Z120+Z121-Z122 -> 3228.4024
D124: D&A as % of PP&E bop | E124: % | H124: =H122/H120 -> 0.063981159 | I124: =I122/I120 -> 0.070138059 | J124: =J122/J120 -> 0.072196815 | K124: =K122/K120 -> 0.074491519 | L124: =L122/L120 -> 0.081813318 | M124: =M122/M120 -> 0.11375742 | N124: =N122/N120 -> 0.099862843 | O124: =O122/O120 -> 0.098743125 | P124: =P122/P120 -> 0.10103227 | Q124: =AVERAGE($H$124:$P$124) -> 0.086224059 | R124: =AVERAGE($H$124:$P$124) -> 0.086224059 | S124: =AVERAGE($H$124:$P$124) -> 0.086224059 | T124: =AVERAGE($H$124:$P$124) -> 0.086224059 | U124: =AVERAGE($H$124:$P$124) -> 0.086224059 | V124: =AVERAGE($H$124:$P$124) -> 0.086224059 | W124: =AVERAGE($H$124:$P$124) -> 0.086224059 | X124: =AVERAGE($H$124:$P$124) -> 0.086224059 | ... Z124: =AVERAGE($H$124:$P$124) -> 0.086224059
B128: Debt
D130: Unsecured notes | E130: mn $ | Q130: =Q135+Q141+Q147+Q153 -> 1983.374 | R130: =R135+R141+R147+R153 -> 1684.538 | S130: =S135+S141+S147+S153 -> 1684.538 | T130: =T135+T141+T147+T153 -> 1684.538 | U130: =U135+U141+U147+U153 -> 990.889 | V130: =V135+V141+V147+V153 -> 990.889 | W130: =W135+W141+W147+W153 -> 295.606 | X130: =X135+X141+X147+X153 -> 295.606 | ... Z130: =Z135+Z141+Z147+Z153 -> 295.606
D132: $300 million at 4.25% due December 1, 2024 | F132: 45627
D133: bop | E133: mn $ | Q133: 298.836 | R133: =Q135 -> 298.836 | S133: =R135 -> 0 | T133: =S135 -> 0 | U133: =T135 -> 0 | V133: =U135 -> 0 | W133: =V135 -> 0 | X133: =W135 -> 0 | Y133: =X135 -> 0 | Z133: =Y135 -> 0
D134: payments | E134: mn $ | F134: =YEAR(F132) -> 2024 | Q134: =($F134=Q$2)*$Q133 -> 0 | R134: =($F134=R$2)*$Q133 -> 298.836 | S134: =($F134=S$2)*$Q133 -> 0 | T134: =($F134=T$2)*$Q133 -> 0 | U134: =($F134=U$2)*$Q133 -> 0 | V134: =($F134=V$2)*$Q133 -> 0 | W134: =($F134=W$2)*$Q133 -> 0 | X134: =($F134=X$2)*$Q133 -> 0 | ... Z134: =($F134=Z$2)*$Q133 -> 0
D135: eop | E135: mn $ | Q135: =Q133-Q134 -> 298.836 | R135: =R133-R134 -> 0 | S135: =S133-S134 -> 0 | T135: =T133-T134 -> 0 | U135: =U133-U134 -> 0 | V135: =V133-V134 -> 0 | W135: =W133-W134 -> 0 | X135: =X133-X134 -> 0 | ... Z135: =Z133-Z134 -> 0
D136: Interest | E136: mn $ | F136: 0.0425 | Q136: =MAX(IF(YEAR($F132)>Q$2,$F136*Q133,($F132-Q$1)/365*Q133*$F136),0) -> 12.70053 | R136: =MAX(IF(YEAR($F132)>R$2,$F136*R133,($F132-R$1)/365*R133*$F136),0) -> 11.656651 | S136: =MAX(IF(YEAR($F132)>S$2,$F136*S133,($F132-S$1)/365*S133*$F136),0) -> 0 | T136: =MAX(IF(YEAR($F132)>T$2,$F136*T133,($F132-T$1)/365*T133*$F136),0) -> 0 | U136: =MAX(IF(YEAR($F132)>U$2,$F136*U133,($F132-U$1)/365*U133*$F136),0) -> 0 | V136: =MAX(IF(YEAR($F132)>V$2,$F136*V133,($F132-V$1)/365*V133*$F136),0) -> 0 | W136: =MAX(IF(YEAR($F132)>W$2,$F136*W133,($F132-W$1)/365*W133*$F136),0) -> 0 | X136: =MAX(IF(YEAR($F132)>X$2,$F136*X133,($F132-X$1)/365*X133*$F136),0) -> 0 | ... Z136: =MAX(IF(YEAR($F132)>Z$2,$F136*Z133,($F132-Z$1)/365*Z133*$F136),0) -> 0
D138: $700 million at 5.125% due October 15, 2027 | E138: mn $ | F138: 46675
D139: bop | E139: mn $ | Q139: 693.649 | R139: =Q141 -> 693.649 | S139: =R141 -> 693.649 | T139: =S141 -> 693.649 | U139: =T141 -> 693.649 | V139: =U141 -> 0 | W139: =V141 -> 0 | X139: =W141 -> 0 | Y139: =X141 -> 0 | Z139: =Y141 -> 0
D140: payments | E140: mn $ | F140: =YEAR(F138) -> 2027 | Q140: =($F140=Q$2)*$Q139 -> 0 | R140: =($F140=R$2)*$Q139 -> 0 | S140: =($F140=S$2)*$Q139 -> 0 | T140: =($F140=T$2)*$Q139 -> 0 | U140: =($F140=U$2)*$Q139 -> 693.649 | V140: =($F140=V$2)*$Q139 -> 0 | W140: =($F140=W$2)*$Q139 -> 0 | X140: =($F140=X$2)*$Q139 -> 0 | ... Z140: =($F140=Z$2)*$Q139 -> 0
D141: eop | E141: mn $ | Q141: =Q139-Q140 -> 693.649 | R141: =R139-R140 -> 693.649 | S141: =S139-S140 -> 693.649 | T141: =T139-T140 -> 693.649 | U141: =U139-U140 -> 0 | V141: =V139-V140 -> 0 | W141: =W139-W140 -> 0 | X141: =X139-X140 -> 0 | ... Z141: =Z139-Z140 -> 0
D142: Interest | E142: mn $ | F142: 0.05125 | Q142: =MAX(IF(YEAR($F138)>Q$2,$F142*Q139,($F138-Q$1)/365*Q139*$F142),0) -> 35.549511 | R142: =MAX(IF(YEAR($F138)>R$2,$F142*R139,($F138-R$1)/365*R139*$F142),0) -> 35.549511 | S142: =MAX(IF(YEAR($F138)>S$2,$F142*S139,($F138-S$1)/365*S139*$F142),0) -> 35.549511 | T142: =MAX(IF(YEAR($F138)>T$2,$F142*T139,($F138-T$1)/365*T139*$F142),0) -> 35.549511 | U142: =MAX(IF(YEAR($F138)>U$2,$F142*U139,($F138-U$1)/365*U139*$F142),0) -> 27.952629 | V142: =MAX(IF(YEAR($F138)>V$2,$F142*V139,($F138-V$1)/365*V139*$F142),0) -> 0 | W142: =MAX(IF(YEAR($F138)>W$2,$F142*W139,($F138-W$1)/365*W139*$F142),0) -> 0 | X142: =MAX(IF(YEAR($F138)>X$2,$F142*X139,($F138-X$1)/365*X139*$F142),0) -> 0 | ... Z142: =MAX(IF(YEAR($F138)>Z$2,$F142*Z139,($F138-Z$1)/365*Z139*$F142),0) -> 0
D144: $700 million at 5.25% due December 15, 2029 | E144: mn $ | F144: 47467
D145: bop | E145: mn $ | Q145: 695.283 | R145: =Q147 -> 695.283 | S145: =R147 -> 695.283 | T145: =S147 -> 695.283 | U145: =T147 -> 695.283 | V145: =U147 -> 695.283 | W145: =V147 -> 695.283 | X145: =W147 -> 0 | Y145: =X147 -> 0 | Z145: =Y147 -> 0
D146: payments | E146: mn $ | F146: =YEAR(F144) -> 2029 | Q146: =($F146=Q$2)*$Q145 -> 0 | R146: =($F146=R$2)*$Q145 -> 0 | S146: =($F146=S$2)*$Q145 -> 0 | T146: =($F146=T$2)*$Q145 -> 0 | U146: =($F146=U$2)*$Q145 -> 0 | V146: =($F146=V$2)*$Q145 -> 0 | W146: =($F146=W$2)*$Q145 -> 695.283 | X146: =($F146=X$2)*$Q145 -> 0 | ... Z146: =($F146=Z$2)*$Q145 -> 0
D147: eop | E147: mn $ | Q147: =Q145-Q146 -> 695.283 | R147: =R145-R146 -> 695.283 | S147: =S145-S146 -> 695.283 | T147: =T145-T146 -> 695.283 | U147: =U145-U146 -> 695.283 | V147: =V145-V146 -> 695.283 | W147: =W145-W146 -> 0 | X147: =X145-X146 -> 0 | ... Z147: =Z145-Z146 -> 0
D148: Interest | E148: mn $ | F148: 0.0525 | Q148: =MAX(IF(YEAR($F144)>Q$2,$F148*Q145,($F144-Q$1)/365*Q145*$F148),0) -> 36.502358 | R148: =MAX(IF(YEAR($F144)>R$2,$F148*R145,($F144-R$1)/365*R145*$F148),0) -> 36.502358 | S148: =MAX(IF(YEAR($F144)>S$2,$F148*S145,($F144-S$1)/365*S145*$F148),0) -> 36.502358 | T148: =MAX(IF(YEAR($F144)>T$2,$F148*T145,($F144-T$1)/365*T145*$F148),0) -> 36.502358 | U148: =MAX(IF(YEAR($F144)>U$2,$F148*U145,($F144-U$1)/365*U145*$F148),0) -> 36.502358 | V148: =MAX(IF(YEAR($F144)>V$2,$F148*V145,($F144-V$1)/365*V145*$F148),0) -> 36.502358 | W148: =MAX(IF(YEAR($F144)>W$2,$F148*W145,($F144-W$1)/365*W145*$F148),0) -> 34.802248 | X148: =MAX(IF(YEAR($F144)>X$2,$F148*X145,($F144-X$1)/365*X145*$F148),0) -> 0 | ... Z148: =MAX(IF(YEAR($F144)>Z$2,$F148*Z145,($F144-Z$1)/365*Z145*$F148),0) -> 0
D150: $300 million at 5.65% due December 1, 2044 | E150: mn $ | F150: 52932
D151: bop | E151: mn $ | Q151: 295.606 | R151: =Q153 -> 295.606 | S151: =R153 -> 295.606 | T151: =S153 -> 295.606 | U151: =T153 -> 295.606 | V151: =U153 -> 295.606 | W151: =V153 -> 295.606 | X151: =W153 -> 295.606 | Y151: =X153 -> 295.606 | Z151: =Y153 -> 295.606
D152: payments | E152: mn $ | F152: =YEAR(F150) -> 2044 | Q152: =($F152=Q$2)*$Q151 -> 0 | R152: =($F152=R$2)*$Q151 -> 0 | S152: =($F152=S$2)*$Q151 -> 0 | T152: =($F152=T$2)*$Q151 -> 0 | U152: =($F152=U$2)*$Q151 -> 0 | V152: =($F152=V$2)*$Q151 -> 0 | W152: =($F152=W$2)*$Q151 -> 0 | X152: =($F152=X$2)*$Q151 -> 0 | ... Z152: =($F152=Z$2)*$Q151 -> 0
D153: eop | E153: mn $ | Q153: =Q151-Q152 -> 295.606 | R153: =R151-R152 -> 295.606 | S153: =S151-S152 -> 295.606 | T153: =T151-T152 -> 295.606 | U153: =U151-U152 -> 295.606 | V153: =V151-V152 -> 295.606 | W153: =W151-W152 -> 295.606 | X153: =X151-X152 -> 295.606 | ... Z153: =Z151-Z152 -> 295.606
...

Sheet P&L
B2: Index | E2: Measure | F2: Base | G2: =Calc!G2 -> 2013 | H2: =Calc!H2 -> 2014 | I2: =Calc!I2 -> 2015 | J2: =Calc!J2 -> 2016 | K2: =Calc!K2 -> 2017 | L2: =Calc!L2 -> 2018 | M2: =Calc!M2 -> 2019 | N2: =Calc!N2 -> 2020 | ... Z2: =Calc!Z2 -> 2032
G3: =Calc!G3 -> fact | H3: =Calc!H3 -> fact | I3: =Calc!I3 -> fact | J3: =Calc!J3 -> fact | K3: =Calc!K3 -> fact | L3: =Calc!L3 -> fact | M3: =Calc!M3 -> fact | N3: =Calc!N3 -> fact | ... Z3: =Calc!Z3 -> forecast
B6: P&L
D8: Revenue | E8: mn $ | G8: =Calc!G78 -> 3024.047 | H8: =Calc!H78 -> 3223.399 | I8: =Calc!I78 -> 2225.602 | J8: =Calc!J78 -> 1998.429 | K8: =Calc!K78 -> 3060.642 | L8: =Calc!L78 -> 3931.847 | M8: =Calc!M78 -> 3283.514 | N8: =Calc!N78 -> 2649.963 | ... Z8: =Calc!Z78 -> 4808.972
D10: Cost of raw materials and purchased methanol | E10: mn $ | G10: =Calc!G91 -> 1661.14 | H10: =Calc!H91 -> 1847.138 | I10: =Calc!I91 -> 1393.032 | J10: =Calc!J91 -> 1140.551 | K10: =Calc!K91 -> 1637.085 | L10: =Calc!L91 -> 2191.515 | M10: =Calc!M91 -> 2169.027 | N10: =Calc!N91 -> 1705.387 | ... Z10: =Calc!Z91 -> 3112.0545
D11: Ocean freight and other logistics | E11: mn $ | G11: =Calc!G97 -> 256.461 | H11: =Calc!H97 -> 287.35 | I11: =Calc!I97 -> 253.394 | J11: =Calc!J97 -> 351.609 | K11: =Calc!K97 -> 374.717 | L11: =Calc!L97 -> 399.293 | M11: =Calc!M97 -> 334.65 | N11: =Calc!N97 -> 328.635 | ... Z11: =Calc!Z97 -> 363.52168
D12: Employee expenses, including share-based compensation | E12: mn $ | G12: =Calc!G102 -> 274.463 | H12: =Calc!H102 -> 124.111 | I12: =Calc!I102 -> 113.627 | J12: =Calc!J102 -> 204.762 | K12: =Calc!K102 -> 243.707 | L12: =Calc!L102 -> 182.519 | M12: =Calc!M102 -> 184.171 | N12: =Calc!N102 -> 246.779 | ... Z12: =Calc!Z102 -> 270.54469
D13: Other expenses | E13: mn $ | G13: =Calc!G103 -> 173.456 | H13: =Calc!H103 -> 167.222 | I13: =Calc!I103 -> 97.846 | J13: =Calc!J103 -> 77.507 | K13: =Calc!K103 -> 96.44 | L13: =Calc!L103 -> 83.593 | M13: =Calc!M103 -> 112.089 | N13: =Calc!N103 -> 74.322 | ... Z13: =Calc!Z103 -> 137.45758
D15: Earnings of associate | E15: mn $ | G15: =Calc!G217 -> 22.553833 | H15: =Calc!H217 -> 9.132463 | I15: =Calc!I217 -> 51.842329 | J15: =Calc!J217 -> 19.929504 | K15: =Calc!K217 -> 75.995116 | L15: =Calc!L217 -> 72.000886 | M15: =Calc!M217 -> 52.217774 | N15: =Calc!N217 -> 29.576863 | ... Z15: =Calc!Z217 -> 82.435551
D17: EBITDA | E17: mn $ | G17: =G8-SUM(G10:G13)+G15 -> 681.08083 | H17: =H8-SUM(H10:H13)+H15 -> 806.71046 | I17: =I8-SUM(I10:I13)+I15 -> 419.54533 | J17: =J8-SUM(J10:J13)+J15 -> 243.9295 | K17: =K8-SUM(K10:K13)+K15 -> 784.68812 | L17: =L8-SUM(L10:L13)+L15 -> 1146.9279 | M17: =M8-SUM(M10:M13)+M15 -> 535.79477 | N17: =N8-SUM(N10:N13)+N15 -> 324.41686 | ... Z17: =Z8-SUM(Z10:Z13)+Z15 -> 1007.8291
D18: EBITDA margin | E18: % | G18: =IFERROR(G17/G$8,"-") -> 0.22522164 | H18: =IFERROR(H17/H$8,"-") -> 0.25026702 | I18: =IFERROR(I17/I$8,"-") -> 0.1885087 | J18: =IFERROR(J17/J$8,"-") -> 0.12206063 | K18: =IFERROR(K17/K$8,"-") -> 0.25638024 | L18: =IFERROR(L17/L$8,"-") -> 0.29170206 | M18: =IFERROR(M17/M$8,"-") -> 0.16317725 | N18: =IFERROR(N17/N$8,"-") -> 0.12242317 | ... Z18: =IFERROR(Z17/Z$8,"-") -> 0.20957267
D20: D&A | E20: mn $ | G20: =Calc!G122 -> 0 | H20: =Calc!H122 -> 142.738 | I20: =Calc!I122 -> 194.849 | J20: =Calc!J122 -> 228.054 | K20: =Calc!K122 -> 232.225 | L20: =Calc!L122 -> 245.303 | M20: =Calc!M122 -> 344.127 | N20: =Calc!N122 -> 357.129 | ... Z20: =Calc!Z122 -> 284.61719
D22: EBIT | E22: mn $ | G22: =G17-G20 -> 681.08083 | H22: =H17-H20 -> 663.97246 | I22: =I17-I20 -> 224.69633 | J22: =J17-J20 -> 15.875504 | K22: =K17-K20 -> 552.46312 | L22: =L17-L20 -> 901.62489 | M22: =M17-M20 -> 191.66777 | N22: =N17-N20 -> -32.712137 | ... Z22: =Z17-Z20 -> 723.21193
D23: EBIT margin | E23: % | G23: =IFERROR(G22/G$8,"-") -> 0.22522164 | H23: =IFERROR(H22/H$8,"-") -> 0.20598519 | I23: =IFERROR(I22/I$8,"-") -> 0.1009598 | J23: =IFERROR(J22/J$8,"-") -> 0.007943992 | K23: =IFERROR(K22/K$8,"-") -> 0.18050563 | L23: =IFERROR(L22/L$8,"-") -> 0.22931332 | M23: =IFERROR(M22/M$8,"-") -> 0.05837276 | N23: =IFERROR(N22/N$8,"-") -> -0.012344375 | ... Z23: =IFERROR(Z22/Z$8,"-") -> 0.15038805
D25: Other income (expenses) | E25: mn $ | G25: =-33.867-24.798 -> -58.665 | H25: =42-7.285 -> 34.715 | I25: =65-6.487 -> 58.513 | J25: 32.5 | K25: 0 | L25: 0 | M25: 50 | N25: 9.839 | O25: 0 | P25: 117.946
D26: Finance costs | E26: mn $ | G26: 56.407 | H26: 37.042 | I26: 69.859 | J26: 90.06 | K26: 94.955 | L26: 94.416 | M26: 124.426 | N26: 164.837 | O26: 144.406 | P26: 130.752 | Q26: =-CFS!Q22 -> 159.47333 | R26: =-CFS!R22 -> 153.21145 | S26: =-CFS!S22 -> 136.3408 | T26: =-CFS!T22 -> 131.3938 | U26: =-CFS!U22 -> 118.83692 | V26: =-CFS!V22 -> 90.88429 | W26: =-CFS!W22 -> 89.18418 | X26: =-CFS!X22 -> 54.381933 | ... Z26: =-CFS!Z22 -> 50.92356
D27: Finance income | E27: mn $ | G27: 4.446 | H27: 0 | I27: 0 | J27: 4.18 | K27: 13.377 | L27: 4.266 | M27: 3.598 | N27: 0.278 | O27: 1.036 | P27: 25.348
D29: Income before income taxes | E29: mn $ | G29: =G22+G25-G26+G27 -> 570.45483 | H29: =H22+H25-H26+H27 -> 661.64546 | I29: =I22+I25-I26+I27 -> 213.35033 | J29: =J22+J25-J26+J27 -> -37.504496 | K29: =K22+K25-K26+K27 -> 470.88512 | L29: =L22+L25-L26+L27 -> 811.47489 | M29: =M22+M25-M26+M27 -> 120.83977 | N29: =N22+N25-N26+N27 -> -187.43214 | ... Z29: =Z22+Z25-Z26+Z27 -> 672.28837
D31: Убыток прошлых лет | E31: mn $ | Q31: =SUM(P31:P33) -> 0 | R31: =SUM(Q31:Q33) -> 0 | S31: =SUM(R31:R33) -> 0 | T31: =SUM(S31:S33) -> 0 | U31: =SUM(T31:T33) -> 0 | V31: =SUM(U31:U33) -> 0 | W31: =SUM(V31:V33) -> 0 | X31: =SUM(W31:W33) -> 0 | ... Z31: =SUM(Y31:Y33) -> 0
D32: Убыток периода | E32: mn $ | Q32: =-IF(Q29<0,Q29,) -> 0 | R32: =-IF(R29<0,R29,) -> 0 | S32: =-IF(S29<0,S29,) -> 0 | T32: =-IF(T29<0,T29,) -> 0 | U32: =-IF(U29<0,U29,) -> 0 | V32: =-IF(V29<0,V29,) -> 0 | W32: =-IF(W29<0,W29,) -> 0 | X32: =-IF(X29<0,X29,) -> 0 | ... Z32: =-IF(Z29<0,Z29,) -> 0
D33: Зачет убытка | E33: mn $ | Q33: =-IF(AND(Q29>0,Q31>0,Q31>Q29),Q29,Q31) -> 0 | R33: =-IF(AND(R29>0,R31>0,R31>R29),R29,R31) -> 0 | S33: =-IF(AND(S29>0,S31>0,S31>S29),S29,S31) -> 0 | T33: =-IF(AND(T29>0,T31>0,T31>T29),T29,T31) -> 0 | U33: =-IF(AND(U29>0,U31>0,U31>U29),U29,U31) -> 0 | V33: =-IF(AND(V29>0,V31>0,V31>V29),V29,V31) -> 0 | W33: =-IF(AND(W29>0,W31>0,W31>W29),W29,W31) -> 0 | X33: =-IF(AND(X29>0,X31>0,X31>X29),X29,X31) -> 0 | ... Z33: =-IF(AND(Z29>0,Z31>0,Z31>Z29),Z29,Z31) -> 0
D34: Налогооблагаемая прибыль | E34: mn $ | Q34: =MAX(Q29+Q33,0) -> 81.963228 | R34: =MAX(R29+R33,0) -> 417.97706 | S34: =MAX(S29+S33,0) -> 586.35825 | T34: =MAX(T29+T33,0) -> 549.48934 | U34: =MAX(U29+U33,0) -> 566.90558 | V34: =MAX(V29+V33,0) -> 605.15753 | W34: =MAX(W29+W33,0) -> 615.64542 | X34: =MAX(X29+X33,0) -> 657.86825 | ... Z34: =MAX(Z29+Z33,0) -> 672.28837
D36: Income tax rate | E36: % | G36: =G37/G29 -> 0.12291946 | H36: =H37/H29 -> 0.23477377 | I36: =I37/I29 -> 0.051544331 | J36: =J37/J29 -> 0.24741034 | K36: =K37/K29 -> 0.20342117 | L36: =L37/L29 -> 0.18915065 | M36: =M37/M29 -> 0.037024233 | N36: =N37/N29 -> 0.33134659 | ... P36: =P37/P29 -> 0.20589113 | Q36: =AVERAGE($O36:$P36) -> 0.18580673 | R36: =AVERAGE($O36:$P36) -> 0.18580673 | S36: =AVERAGE($O36:$P36) -> 0.18580673 | T36: =AVERAGE($O36:$P36) -> 0.18580673 | U36: =AVERAGE($O36:$P36) -> 0.18580673 | V36: =AVERAGE($O36:$P36) -> 0.18580673 | W36: =AVERAGE($O36:$P36) -> 0.18580673 | X36: =AVERAGE($O36:$P36) -> 0.18580673 | ... Z36: =AVERAGE($O36:$P36) -> 0.18580673
D37: Income tax (expense) recovery | E37: mn $ | G37: 70.12 | H37: 155.337 | I37: 10.997 | J37: -9.279 | K37: 95.788 | L37: 153.491 | M37: 4.474 | N37: -62.105 | O37: 110.427 | P37: 119.859 | Q37: =Q34*Q36 -> 15.229319 | R37: =R34*R36 -> 77.662949 | S37: =S34*S36 -> 108.94931 | T37: =T34*T36 -> 102.09881 | U37: =U34*U36 -> 105.33487 | V37: =V34*V36 -> 112.44234 | W37: =W34*W36 -> 114.39106 | X37: =X34*X36 -> 122.23634 | ... Z37: =Z34*Z36 -> 124.9157
D39: Net profit | E39: mn $ | G39: =G29-G37 -> 500.33483 | H39: =H29-H37 -> 506.30846 | I39: =I29-I37 -> 202.35333 | J39: =J29-J37 -> -28.225496 | K39: =K29-K37 -> 375.09712 | L39: =L29-L37 -> 657.98389 | M39: =M29-M37 -> 116.36577 | N39: =N29-N37 -> -125.32714 | ... Z39: =Z29-Z37 -> 547.37267
D40: Рентабельность по чистой прибыли | E40: % | G40: =IFERROR(G39/G$8,"-") -> 0.16545207 | H40: =IFERROR(H39/H$8,"-") -> 0.15707285 | I40: =IFERROR(I39/I$8,"-") -> 0.090920717 | J40: =IFERROR(J39/J$8,"-") -> -0.014123842 | K40: =IFERROR(K39/K$8,"-") -> 0.12255504 | L40: =IFERROR(L39/L$8,"-") -> 0.16734728 | M40: =IFERROR(M39/M$8,"-") -> 0.035439402 | N40: =IFERROR(N39/N$8,"-") -> -0.04729392 | ... Z40: =IFERROR(Z39/Z$8,"-") -> 0.11382322
D43: Net profit (GAAP) | E43: mn $ | G43: 377 | H43: 506.308 | I43: 202.353 | J43: -28.225 | K43: 375.097 | L43: 657.984 | M43: 116.366 | N43: -125.327 | O43: 555.911 | P43: 462.288
D44: Check | E44: mn $ | G44: =G39-G43 -> 123.33483 | H44: =H39-H43 -> 0.000463 | I44: =I39-I43 -> 0.000329 | J44: =J39-J43 -> -0.000496 | K44: =K39-K43 -> 0.000116 | L44: =L39-L43 -> -0.000114 | M44: =M39-M43 -> -0.000226 | N44: =N39-N43 -> -0.000137 | ... P44: =P39-P43 -> 0.000461
B48: . | C48: . | D48: . | E48: . | F48: . | G48: . | V48: . | W48: . | X48: . | Y48: . | Z48: .

Sheet CFS
B2: Index | E2: Measure | F2: Base | G2: =Calc!G2 -> 2013 | H2: =Calc!H2 -> 2014 | I2: =Calc!I2 -> 2015 | J2: =Calc!J2 -> 2016 | K2: =Calc!K2 -> 2017 | L2: =Calc!L2 -> 2018 | M2: =Calc!M2 -> 2019 | N2: =Calc!N2 -> 2020 | ... Z2: =Calc!Z2 -> 2032
G3: =Calc!G3 -> fact | H3: =Calc!H3 -> fact | I3: =Calc!I3 -> fact | J3: =Calc!J3 -> fact | K3: =Calc!K3 -> fact | L3: =Calc!L3 -> fact | M3: =Calc!M3 -> fact | N3: =Calc!N3 -> fact | ... Z3: =Calc!Z3 -> forecast
B6: CFS
D8: EBITDA | E8: mn $ | G8: ='P&L'!G17 -> 681.08083 | H8: ='P&L'!H17 -> 806.71046 | I8: ='P&L'!I17 -> 419.54533 | J8: ='P&L'!J17 -> 243.9295 | K8: ='P&L'!K17 -> 784.68812 | L8: ='P&L'!L17 -> 1146.9279 | M8: ='P&L'!M17 -> 535.79477 | N8: ='P&L'!N17 -> 324.41686 | ... Z8: ='P&L'!Z17 -> 1007.8291
D9: Profit tax | E9: mn $ | G9: =-'P&L'!G37 -> -70.12 | H9: =-'P&L'!H37 -> -155.337 | I9: =-'P&L'!I37 -> -10.997 | J9: =-'P&L'!J37 -> 9.279 | K9: =-'P&L'!K37 -> -95.788 | L9: =-'P&L'!L37 -> -153.491 | M9: =-'P&L'!M37 -> -4.474 | N9: =-'P&L'!N37 -> 62.105 | ... Z9: =-'P&L'!Z37 -> -124.9157
D10: ΔNWC | E10: mn $ | G10: =-(Calc!G202-Calc!F202) -> -271.45 | H10: =-(Calc!H202-Calc!G202) -> 104.029 | I10: =-(Calc!I202-Calc!H202) -> -101.084 | J10: =-(Calc!J202-Calc!I202) -> -10.056 | K10: =-(Calc!K202-Calc!J202) -> 37.73 | L10: =-(Calc!L202-Calc!K202) -> -76.823 | M10: =-(Calc!M202-Calc!L202) -> 3.83 | N10: =-(Calc!N202-Calc!M202) -> 160.335 | ... Z10: =-(Calc!Z202-Calc!Y202) -> 0.26839222
D12: OCF | E12: mn $ | G12: 585.797 | H12: 801.017 | I12: 296.951 | J12: 249.93 | K12: 780.22 | L12: 980.206 | M12: 515.431 | N12: 461.082 | O12: 994.369 | P12: 987.349 | Q12: =Q8+SUM(Q9:Q10) -> 605.80242 | R12: =R8+SUM(R9:R10) -> 778.40913 | S12: =S8+SUM(S9:S10) -> 939.82855 | T12: =T8+SUM(T9:T10) -> 939.28993 | U12: =U8+SUM(U9:U10) -> 914.8233 | V12: =V8+SUM(V9:V10) -> 904.09588 | W12: =W8+SUM(W9:W10) -> 900.23727 | X12: =X8+SUM(X9:X10) -> 890.37811 | ... Z12: =Z8+SUM(Z9:Z10) -> 883.18181
D15: Property, plant and equipment | E15: mn $ | G15: =-Calc!G109 -> -269.367 | H15: =-Calc!H109 -> -84.168 | I15: =-Calc!I109 -> -96.909 | J15: =-Calc!J109 -> -99.881 | K15: =-Calc!K109 -> -103.17 | L15: =-Calc!L109 -> -244.476 | M15: =-Calc!M109 -> -208.467 | N15: =-Calc!N109 -> -128.786 | ... P15: =-Calc!P109 -> -145.701 | Q15: =-Calc!Q109-Calc!Q114 -> -150.34062 | R15: =-Calc!R109-Calc!R114 -> -180.83022 | S15: =-Calc!S109-Calc!S114 -> -184.55384 | T15: =-Calc!T109-Calc!T114 -> -188.35414 | U15: =-Calc!U109-Calc!U114 -> -192.12123 | V15: =-Calc!V109-Calc!V114 -> -195.96365 | W15: =-Calc!W109-Calc!W114 -> -199.88292 | X15: =-Calc!X109-Calc!X114 -> -203.88058 | ... Z15: =-Calc!Z109-Calc!Z114 -> -212.11736
D16: Geismar plant under construction | E16: mn $ | G16: =-Calc!G112 -> -309.469 | H16: =-Calc!H112 -> -573.844 | I16: =-Calc!I112 -> -328.112 | J16: =-Calc!J112 -> 0 | K16: =-Calc!K112 -> 0 | L16: =-Calc!L112 -> 0 | M16: =-Calc!M112 -> -115.393 | N16: =-Calc!N112 -> -213.03 | ... Z16: =-Calc!Z112 -> 0
D18: ICF | E18: mn $ | G18: -526.429 | H18: -681.022 | I18: -426.255 | J18: -88.209 | K18: -105.517 | L18: -306.351 | M18: -250.692 | N18: -278.063 | O18: -253.048 | P18: -553.137 | Q18: =SUM(Q15:Q16) -> -590.34062 | R18: =SUM(R15:R16) -> -180.83022 | S18: =SUM(S15:S16) -> -184.55384 | T18: =SUM(T15:T16) -> -188.35414 | U18: =SUM(U15:U16) -> -192.12123 | V18: =SUM(V15:V16) -> -195.96365 | W18: =SUM(W15:W16) -> -199.88292 | X18: =SUM(X15:X16) -> -203.88058 | ... Z18: =SUM(Z15:Z16) -> -212.11736
D21: (-) Payments | E21: mn $ | G21: -39.491 | H21: -41.504 | I21: -193.996 | J21: -48.417 | K21: -56.997 | L21: -213.622 | M21: -101.812 | N21: =-106.834 -> -106.834 | O21: =-62.381-101.054 -> -163.435 | P21: =-9.151-105.863 -> -115.014 | Q21: =-(Calc!Q134+Calc!Q140+Calc!Q146+Calc!Q152+Calc!Q161+Calc!Q167+Calc!Q173+Calc!Q181) -> -107.829 | R21: =-(Calc!R134+Calc!R140+Calc!R146+Calc!R152+Calc!R161+Calc!R167+Calc!R173+Calc!R181) -> -395.538 | S21: =-(Calc!S134+Calc!S140+Calc!S146+Calc!S152+Calc!S161+Calc!S167+Calc!S173+Calc!S181) -> -85.928 | T21: =-(Calc!T134+Calc!T140+Calc!T146+Calc!T152+Calc!T161+Calc!T167+Calc!T173+Calc!T181) -> -74.988 | U21: =-(Calc!U134+Calc!U140+Calc!U146+Calc!U152+Calc!U161+Calc!U167+Calc!U173+Calc!U181) -> -763.133 | V21: =-(Calc!V134+Calc!V140+Calc!V146+Calc!V152+Calc!V161+Calc!V167+Calc!V173+Calc!V181) -> -69.484 | W21: =-(Calc!W134+Calc!W140+Calc!W146+Calc!W152+Calc!W161+Calc!W167+Calc!W173+Calc!W181) -> -764.767 | X21: =-(Calc!X134+Calc!X140+Calc!X146+Calc!X152+Calc!X161+Calc!X167+Calc!X173+Calc!X181) -> -69.484 | ... Z21: =-(Calc!Z134+Calc!Z140+Calc!Z146+Calc!Z152+Calc!Z161+Calc!Z167+Calc!Z173+Calc!Z181) -> -69.484
D22: (-) Interest | E22: mn $ | G22: -55.446 | H22: -52.995 | I22: -82.275 | J22: -82.965 | K22: -86.041 | L22: -90.008 | M22: -115.283 | N22: -165.45 | O22: -165.059 | P22: -161.816 | Q22: =-(Calc!Q136+Calc!Q142+Calc!Q148+Calc!Q154+Calc!Q163+Calc!Q169+Calc!Q175+Calc!Q183) -> -159.47333 | R22: =-(Calc!R136+Calc!R142+Calc!R148+Calc!R154+Calc!R163+Calc!R169+Calc!R175+Calc!R183) -> -153.21145 | S22: =-(Calc!S136+Calc!S142+Calc!S148+Calc!S154+Calc!S163+Calc!S169+Calc!S175+Calc!S183) -> -136.3408 | T22: =-(Calc!T136+Calc!T142+Calc!T148+Calc!T154+Calc!T163+Calc!T169+Calc!T175+Calc!T183) -> -131.3938 | U22: =-(Calc!U136+Calc!U142+Calc!U148+Calc!U154+Calc!U163+Calc!U169+Calc!U175+Calc!U183) -> -118.83692 | V22: =-(Calc!V136+Calc!V142+Calc!V148+Calc!V154+Calc!V163+Calc!V169+Calc!V175+Calc!V183) -> -90.88429 | W22: =-(Calc!W136+Calc!W142+Calc!W148+Calc!W154+Calc!W163+Calc!W169+Calc!W175+Calc!W183) -> -89.18418 | X22: =-(Calc!X136+Calc!X142+Calc!X148+Calc!X154+Calc!X163+Calc!X169+Calc!X175+Calc!X183) -> -54.381933 | ... Z22: =-(Calc!Z136+Calc!Z142+Calc!Z148+Calc!Z154+Calc!Z163+Calc!Z169+Calc!Z175+Calc!Z183) -> -50.92356
D23: (-) Dividend | E23: mn $ | F23: 0.25 | G23: -74.937 | H23: -89.913 | I23: -97.221 | J23: -98.797 | K23: -101.497 | L23: -105.676 | M23: -107.876 | N23: -36.004 | O23: -24.634 | P23: -43.955 | Q23: =-MAX($F23*'P&L'!Q39,0) -> -16.683477 | R23: =-MAX($F23*'P&L'!R39,0) -> -85.078528 | S23: =-MAX($F23*'P&L'!S39,0) -> -119.35224 | T23: =-MAX($F23*'P&L'!T39,0) -> -111.84763 | U23: =-MAX($F23*'P&L'!U39,0) -> -115.39268 | V23: =-MAX($F23*'P&L'!V39,0) -> -123.1788 | W23: =-MAX($F23*'P&L'!W39,0) -> -125.31359 | X23: =-MAX($F23*'P&L'!X39,0) -> -133.90798 | ... Z23: =-MAX($F23*'P&L'!Z39,0) -> -136.84317
D24: (+) Revolver | E24: mn $ | Q24: =-MIN(SUM(P32,Q21:Q23,Q18,Q12,Q25:Q26),0) -> 0 | R24: =-MIN(SUM(Q32,R21:R23,R18,R12,R25:R26),0) -> 0 | S24: =-MIN(SUM(R32,S21:S23,S18,S12,S25:S26),0) -> 0 | T24: =-MIN(SUM(S32,T21:T23,T18,T12,T25:T26),0) -> 0 | U24: =-MIN(SUM(T32,U21:U23,U18,U12,U25:U26),0) -> 0 | V24: =-MIN(SUM(U32,V21:V23,V18,V12,V25:V26),0) -> 0 | W24: =-MIN(SUM(V32,W21:W23,W18,W12,W25:W26),0) -> 0 | X24: =-MIN(SUM(W32,X21:X23,X18,X12,X25:X26),0) -> 0 | ... Z24: =-MIN(SUM(Y32,Z21:Z23,Z18,Z12,Z25:Z26),0) -> 0
D25: (-) Revolver | E25: mn $ | Q25: =-P24 -> 0 | R25: =-Q24 -> 0 | S25: =-R24 -> 0 | T25: =-S24 -> 0 | U25: =-T24 -> 0 | V25: =-U24 -> 0 | W25: =-V24 -> 0 | X25: =-W24 -> 0 | ... Z25: =-Y24 -> 0
D26: (-) % (Revolver) | E26: mn $ | F26: 0.08 | Q26: =-P24*$F26 -> 0 | R26: =-Q24*$F26 -> 0 | S26: =-R24*$F26 -> 0 | T26: =-S24*$F26 -> 0 | U26: =-T24*$F26 -> 0 | V26: =-U24*$F26 -> 0 | W26: =-V24*$F26 -> 0 | X26: =-W24*$F26 -> 0 | ... Z26: =-Y24*$F26 -> 0
D28: FCF | E28: mn $ | G28: -54.017 | H28: 98.869 | I28: -567.362 | J28: -192.765 | K28: -523.114 | L28: -793.257 | M28: -104.053 | N28: 234.059 | O28: -643.093 | P28: -508.534 | Q28: =SUM(Q21:Q26) -> -283.98581 | R28: =SUM(R21:R26) -> -633.82798 | S28: =SUM(S21:S26) -> -341.62104 | T28: =SUM(T21:T26) -> -318.22943 | U28: =SUM(U21:U26) -> -997.3626 | V28: =SUM(V21:V26) -> -283.54709 | W28: =SUM(W21:W26) -> -979.26477 | X28: =SUM(X21:X26) -> -257.77391 | ... Z28: =SUM(Z21:Z26) -> -257.25073
D31: Increase (decrease) in cash and cash equivalents | E31: mn $ | G31: =G12+G18+G28 -> 5.351 | H31: =H12+H18+H28 -> 218.864 | I31: =I12+I18+I28 -> -696.666 | J31: =J12+J18+J28 -> -31.044 | K31: =K12+K18+K28 -> 151.589 | L31: =L12+L18+L28 -> -119.402 | M31: =M12+M18+M28 -> 160.686 | N31: =N12+N18+N28 -> 417.078 | ... Z31: =Z12+Z18+Z28 -> 413.81372
D32: Cash eop | E32: mn $ | G32: =BS!G11 -> 732.736 | H32: =BS!H11 -> 951.6 | I32: =BS!I11 -> 254.934 | J32: =BS!J11 -> 223.89 | K32: =BS!K11 -> 375.479 | L32: =BS!L11 -> 256.077 | M32: =BS!M11 -> 416.763 | N32: =BS!N11 -> 833.841 | ... P32: =BS!P11 -> 857.747 | Q32: =P32+Q31 -> 589.22299 | R32: =Q32+R31 -> 552.97392 | S32: =R32+S31 -> 966.62759 | T32: =S32+T31 -> 1399.3339 | U32: =T32+U31 -> 1124.6734 | V32: =U32+V31 -> 1549.2586 | W32: =V32+W31 -> 1270.3481 | X32: =W32+X31 -> 1699.0718 | ... Z32: =Y32+Z31 -> 2472.0674
D35: Increase (decrease) in cash and cash equivalents (GAAP) | E35: mn $ | G35: 5.351 | H35: 218.864 | I35: -696.666 | J35: -31.044 | K35: 151.589 | L35: -119.402 | M35: 160.686 | N35: 417.078 | O35: 98.228 | P35: -74.322
D36: Check | E36: mn $ | G36: =G35-G31 -> -4.8849813e-14 | H36: =H35-H31 -> 0 | I36: =I35-I31 -> 0 | J36: =J35-J31 -> 0 | K36: =K35-K31 -> 0 | L36: =L35-L31 -> 0 | M36: =M35-M31 -> 0 | N36: =N35-N31 -> 0 | ... P36: =P35-P31 -> -1.1368684e-13
B40: . | C40: . | D40: . | E40: . | F40: . | G40: . | V40: . | W40: . | X40: . | Y40: . | Z40: .

Sheet BS
B2: Index | E2: Measure | F2: Base | G2: =Calc!G2 -> 2013 | H2: =Calc!H2 -> 2014 | I2: =Calc!I2 -> 2015 | J2: =Calc!J2 -> 2016 | K2: =Calc!K2 -> 2017 | L2: =Calc!L2 -> 2018 | M2: =Calc!M2 -> 2019 | N2: =Calc!N2 -> 2020 | ... Z2: =Calc!Z2 -> 2032
G3: =Calc!G3 -> fact | H3: =Calc!H3 -> fact | I3: =Calc!I3 -> fact | J3: =Calc!J3 -> fact | K3: =Calc!K3 -> fact | L3: =Calc!L3 -> fact | M3: =Calc!M3 -> fact | N3: =Calc!N3 -> fact | ... Z3: =Calc!Z3 -> forecast
B6: BS
C8: ASSETS | E8: mn $ | G8: =G10+G17 -> 4120.9 | H8: =H10+H17 -> 4775.34 | I8: =I10+I17 -> 4555.924 | J8: =J10+J17 -> 4556.663 | K8: =K10+K17 -> 4610.742 | L8: =L10+L17 -> 4608.999 | M8: =M10+M17 -> 5196.615 | N8: =N10+N17 -> 5696.051 | ... Z8: =Z10+Z17 -> 7504.0813
D10: Current assets | E10: mn $ | G10: =SUM(G11:G15) -> 1622.367 | H10: =SUM(H11:H15) -> 1685.902 | I10: =SUM(I11:I15) -> 1032.078 | J10: =SUM(J11:J15) -> 1025.667 | K10: =SUM(K11:K15) -> 1243.127 | L10: =SUM(L11:L15) -> 1252.076 | M10: =SUM(M11:M15) -> 1232.521 | N10: =SUM(N11:N15) -> 1594.917 | ... Z10: =SUM(Z11:Z15) -> 3675.8559
D11: Cash and cash equivalents | E11: mn $ | G11: 732.736 | H11: 951.6 | I11: 254.934 | J11: 223.89 | K11: 375.479 | L11: 256.077 | M11: 416.763 | N11: 833.841 | O11: 932.069 | P11: 857.747 | Q11: =CFS!Q32 -> 589.22299 | R11: =CFS!R32 -> 552.97392 | S11: =CFS!S32 -> 966.62759 | T11: =CFS!T32 -> 1399.3339 | U11: =CFS!U32 -> 1124.6734 | V11: =CFS!V32 -> 1549.2586 | W11: =CFS!W32 -> 1270.3481 | X11: =CFS!X32 -> 1699.0718 | ... Z11: =CFS!Z32 -> 2472.0674
D12: Trade and other receivables | E12: mn $ | G12: 534.13 | H12: 404.363 | I12: 504.35 | J12: 499.603 | K12: 536.636 | L12: 514.568 | M12: 488.721 | N12: 412 | O12: 551.367 | P12: 500.925 | Q12: =Calc!Q198 -> 395.74865 | R12: =Calc!R198 -> 550.52962 | S12: =Calc!S198 -> 610.43669 | T12: =Calc!T198 -> 589.42333 | U12: =Calc!U198 -> 588.75842 | V12: =Calc!V198 -> 591.11345 | W12: =Calc!W198 -> 593.47791 | X12: =Calc!X198 -> 595.85182 | ... Z12: =Calc!Z198 -> 600.62817
D13: Inventories | E13: mn $ | G13: 334.968 | H13: 306.802 | I13: 253.234 | J13: 281.328 | K13: 304.464 | L13: 387.959 | M13: 281.052 | N13: 308.696 | O13: 459.556 | P13: 439.771 | Q13: =Calc!Q199 -> 343.93615 | R13: =Calc!R199 -> 478.45277 | S13: =Calc!S199 -> 530.51665 | T13: =Calc!T199 -> 512.25441 | U13: =Calc!U199 -> 511.67655 | V13: =Calc!V199 -> 513.72326 | W13: =Calc!W199 -> 515.77815 | X13: =Calc!X199 -> 517.84126 | ... Z13: =Calc!Z199 -> 521.99228
D14: Prepaid expenses | E14: mn $ | G14: 20.533 | H14: 23.137 | I14: 19.56 | J14: 20.846 | K14: 26.548 | L14: 32.541 | M14: 37.805 | N14: 33.746 | O14: 35.963 | P14: 38.585 | Q14: =Calc!Q200 -> 28.331278 | R14: =Calc!R200 -> 38.052065 | S14: =Calc!S200 -> 41.862319 | T14: =Calc!T200 -> 40.631585 | U14: =Calc!U200 -> 40.668182 | V14: =Calc!V200 -> 40.894527 | W14: =Calc!W200 -> 41.123052 | X14: =Calc!X200 -> 41.353789 | ... Z14: =Calc!Z200 -> 41.822043
D15: Other assets | E15: mn $ | G15: 0 | H15: 0 | I15: 0 | J15: 0 | K15: 0 | L15: 60.931 | M15: 8.18 | N15: 6.634 | O15: 9.842 | P15: 39.346 | Q15: =P15 -> 39.346 | R15: =Q15 -> 39.346 | S15: =R15 -> 39.346 | T15: =S15 -> 39.346 | U15: =T15 -> 39.346 | V15: =U15 -> 39.346 | W15: =V15 -> 39.346 | X15: =W15 -> 39.346 | ... Z15: =Y15 -> 39.346
D17: Non-current assets | E17: mn $ | G17: =SUM(G18:G21) -> 2498.533 | H17: =SUM(H18:H21) -> 3089.438 | I17: =SUM(I18:I21) -> 3523.846 | J17: =SUM(J18:J21) -> 3530.996 | K17: =SUM(K18:K21) -> 3367.615 | L17: =SUM(L18:L21) -> 3356.923 | M17: =SUM(M18:M21) -> 3964.094 | N17: =SUM(N18:N21) -> 4101.134 | ... Z17: =SUM(Z18:Z21) -> 3828.2254
D18: Property, plant and equipment | E18: mn $ | G18: 2230.938 | H18: 2778.078 | I18: 3158.782 | J18: 3117.469 | K18: 2998.326 | L18: 3025.095 | M18: 3576.195 | N18: 3677.056 | O18: 3686.149 | P18: 4155.283 | Q18: =Calc!Q123 -> 4387.3383 | R18: =Calc!R123 -> 4189.8744 | S18: =Calc!S123 -> 4013.1602 | T18: =Calc!T123 -> 3855.4834 | U18: =Calc!U123 -> 3715.1692 | V18: =Calc!V123 -> 3590.7959 | W18: =Calc!W123 -> 3481.0658 | X18: =Calc!X123 -> 3384.7948 | ... Z18: =Calc!Z123 -> 3228.4024
D19: Investment in associate | E19: mn $ | G19: 202.342 | H19: 216.235 | I19: 224.165 | J19: 197.402 | K19: 188.922 | L19: 197.821 | M19: 193.474 | N19: 194.025 | O19: 217.319 | P19: 197.083 | Q19: =P19 -> 197.083 | R19: =Q19 -> 197.083 | S19: =R19 -> 197.083 | T19: =S19 -> 197.083 | U19: =T19 -> 197.083 | V19: =U19 -> 197.083 | W19: =V19 -> 197.083 | X19: =W19 -> 197.083 | ... Z19: =Y19 -> 197.083
D20: Deferred income tax assets | E20: mn $ | G20: 0 | H20: 0 | I20: 61.881 | J20: 137.341 | K20: 102.341 | L20: 59.532 | M20: 111.614 | N20: 137.524 | O20: 98.169 | P20: 46.353 | Q20: =P20 -> 46.353 | R20: =Q20 -> 46.353 | S20: =R20 -> 46.353 | T20: =S20 -> 46.353 | U20: =T20 -> 46.353 | V20: =U20 -> 46.353 | W20: =V20 -> 46.353 | X20: =W20 -> 46.353 | ... Z20: =Y20 -> 46.353
D21: Other assets | E21: mn $ | G21: 65.253 | H21: 95.125 | I21: 79.018 | J21: 78.784 | K21: 78.026 | L21: 74.475 | M21: 82.811 | N21: 92.529 | O21: 99.186 | P21: 356.387 | Q21: =P21 -> 356.387 | R21: =Q21 -> 356.387 | S21: =R21 -> 356.387 | T21: =S21 -> 356.387 | U21: =T21 -> 356.387 | V21: =U21 -> 356.387 | W21: =V21 -> 356.387 | X21: =W21 -> 356.387 | ... Z21: =Y21 -> 356.387
C24: LIABILITIES AND EQUITY | E24: mn $ | G24: =G26+G32+G38 -> 4120.9 | H24: =H26+H32+H38 -> 4775.34 | I24: =I26+I32+I38 -> 4555.924 | J24: =J26+J32+J38 -> 4556.663 | K24: =K26+K32+K38 -> 4610.742 | L24: =L26+L32+L38 -> 4608.999 | M24: =M26+M32+M38 -> 5196.615 | N24: =N26+N32+N38 -> 5696.051 | ... Z24: =Z26+Z32+Z38 -> 7504.0813
D26: Current liabilities | E26: mn $ | G26: =SUM(G27:G30) -> 745.333 | H26: =SUM(H27:H30) -> 819.83 | I26: =SUM(I27:I30) -> 581.942 | J26: =SUM(J27:J30) -> 606.933 | K26: =SUM(K27:K30) -> 747.948 | L26: =SUM(L27:L30) -> 1047.353 | M26: =SUM(M27:M30) -> 648.246 | N26: =SUM(N27:N30) -> 765.392 | ... Z26: =SUM(Z27:Z30) -> 914.14087
D27: Trade, other payables and accrued liabilities | E27: mn $ | G27: 618.181 | H27: 566.881 | I27: 508.639 | J27: 523.216 | K27: 626.817 | L27: 617.414 | M27: 493.754 | N27: 600.953 | O27: 835.951 | P27: 789.2 | Q27: =Calc!Q201 -> 599.2449 | R27: =Calc!R201 -> 804.85272 | S27: =Calc!S201 -> 885.44476 | T27: =Calc!T201 -> 859.41307 | U27: =Calc!U201 -> 860.18713 | V27: =Calc!V201 -> 864.97465 | W27: =Calc!W201 -> 869.80825 | X27: =Calc!X201 -> 874.68866 | ... Z27: =Calc!Z201 -> 884.59287
D28: Current maturities on long-term debt | E28: mn $ | G28: 41.504 | H28: 193.831 | I28: 47.864 | J28: 53.997 | K28: 55.905 | L28: 383.793 | M28: 38.42 | N28: 39.771 | O28: 11.775 | P28: 15.133
D29: Current maturities on lease obligations | E29: mn $ | G29: 0 | H29: 0 | I29: 0 | J29: 0 | K29: 0 | L29: 0 | M29: 89.82 | N29: 97.516 | O29: 98.301 | P29: 108.736
D30: Current maturities on other long-term liabilities | E30: mn $ | G30: 85.648 | H30: 59.118 | I30: 25.439 | J30: 29.72 | K30: 65.226 | L30: 46.146 | M30: 26.252 | N30: 27.152 | O30: 17.191 | P30: 29.548 | Q30: =P30 -> 29.548 | R30: =Q30 -> 29.548 | S30: =R30 -> 29.548 | T30: =S30 -> 29.548 | U30: =T30 -> 29.548 | V30: =U30 -> 29.548 | W30: =V30 -> 29.548 | X30: =W30 -> 29.548 | ... Z30: =Y30 -> 29.548
D32: Non-current liabilities | E32: mn $ | G32: =SUM(G33:G36) -> 1470.234 | H32: =SUM(H33:H36) -> 1902.293 | I32: =SUM(I33:I36) -> 2005.409 | J32: =SUM(J33:J36) -> 2144.38 | K32: =SUM(K33:K36) -> 2117.683 | L32: =SUM(L33:L36) -> 1753.805 | M32: =SUM(M33:M36) -> 2918.009 | N32: =SUM(N33:N36) -> 3489.202 | ... Z32: =SUM(Z33:Z36) -> 851.178
D33: Long-term debt | E33: mn $ | G33: 1126.802 | H33: 1528.207 | I33: 1488.026 | J33: 1502.209 | K33: 1446.366 | L33: 1074.493 | M33: 1730.433 | N33: 2323.601 | O33: 2146.417 | P33: 2136.38 | Q33: =Calc!Q130+Calc!Q157 -> 2151.513 | R33: =Calc!R130+Calc!R157 -> 1852.677 | S33: =Calc!S130+Calc!S157 -> 1852.677 | T33: =Calc!T130+Calc!T157 -> 1852.677 | U33: =Calc!U130+Calc!U157 -> 1159.028 | V33: =Calc!V130+Calc!V157 -> 1159.028 | W33: =Calc!W130+Calc!W157 -> 463.745 | X33: =Calc!X130+Calc!X157 -> 463.745 | ... Z33: =Calc!Z130+Calc!Z157 -> 401.767
D34: Lease obligations | E34: mn $ | G34: 0 | H34: 0 | I34: 0 | J34: 0 | K34: 0 | L34: 0 | M34: 628.685 | N34: 624.718 | O34: 618.8 | P34: 761.427 | Q34: =Calc!Q178 -> 762.334 | R34: =Calc!R178 -> 665.632 | S34: =Calc!S178 -> 579.704 | T34: =Calc!T178 -> 504.716 | U34: =Calc!U178 -> 435.232 | V34: =Calc!V178 -> 365.748 | W34: =Calc!W178 -> 296.264 | X34: =Calc!X178 -> 226.78 | ... Z34: =Calc!Z178 -> 87.812
D35: Other long-term liabilities | E35: mn $ | G35: 188.52 | H35: 140.861 | I35: 231.745 | J35: 351.191 | K35: 404.885 | L35: 398.098 | M35: 286.071 | N35: 327.491 | O35: 193.749 | P35: 134.603 | Q35: =P35 -> 134.603 | R35: =Q35 -> 134.603 | S35: =R35 -> 134.603 | T35: =S35 -> 134.603 | U35: =T35 -> 134.603 | V35: =U35 -> 134.603 | W35: =V35 -> 134.603 | X35: =W35 -> 134.603 | ... Z35: =Y35 -> 134.603
D36: Deferred income tax liabilities | E36: mn $ | G36: 154.912 | H36: 233.225 | I36: 285.638 | J36: 290.98 | K36: 266.432 | L36: 281.214 | M36: 272.82 | N36: 213.392 | O36: 212.705 | P36: 226.996 | Q36: =P36 -> 226.996 | R36: =Q36 -> 226.996 | S36: =R36 -> 226.996 | T36: =S36 -> 226.996 | U36: =T36 -> 226.996 | V36: =U36 -> 226.996 | W36: =V36 -> 226.996 | X36: =W36 -> 226.996 | ... Z36: =Y36 -> 226.996
D38: Equity | E38: mn $ | G38: =SUM(G39:G43) -> 1905.333 | H38: =SUM(H39:H43) -> 2053.217 | I38: =SUM(I39:I43) -> 1968.573 | J38: =SUM(J39:J43) -> 1805.35 | K38: =SUM(K39:K43) -> 1745.111 | L38: =SUM(L39:L43) -> 1807.841 | M38: =SUM(M39:M43) -> 1630.36 | N38: =SUM(N39:N43) -> 1441.457 | ... Z38: =SUM(Z39:Z43) -> 5738.7624
D39: Capital stock | E39: mn $ | G39: 531.573 | H39: 521.022 | I39: 509.464 | J39: 511.465 | K39: 480.331 | L39: 446.544 | M39: 440.472 | N39: 440.723 | O39: 432.728 | P39: 401.295 | Q39: =P39 -> 401.295 | R39: =Q39 -> 401.295 | S39: =R39 -> 401.295 | T39: =S39 -> 401.295 | U39: =T39 -> 401.295 | V39: =U39 -> 401.295 | W39: =V39 -> 401.295 | X39: =W39 -> 401.295 | ... Z39: =Y39 -> 401.295
D40: Contributed surplus | E40: mn $ | G40: 4.994 | H40: 2.803 | I40: 2.426 | J40: 2.568 | K40: 2.124 | L40: 1.597 | M40: 1.783 | N40: 1.873 | O40: 1.928 | P40: 1.904 | Q40: =P40 -> 1.904 | R40: =Q40 -> 1.904 | S40: =R40 -> 1.904 | T40: =S40 -> 1.904 | U40: =T40 -> 1.904 | V40: =U40 -> 1.904 | W40: =V40 -> 1.904 | X40: =W40 -> 1.904 | ... Z40: =Y40 -> 1.904
D41: Retained earnings | E41: mn $ | G41: 1126.7 | H41: 1262.961 | I41: 1235.615 | J41: 1124.104 | K41: 1088.15 | L41: 1145.476 | M41: 1039.819 | N41: 843.606 | O41: 1251.64 | P41: 1466.872 | Q41: =P41+'P&L'!Q39+CFS!Q23 -> 1516.9224 | R41: =Q41+'P&L'!R39+CFS!R23 -> 1772.158 | S41: =R41+'P&L'!S39+CFS!S23 -> 2130.2147 | T41: =S41+'P&L'!T39+CFS!T23 -> 2465.7576 | U41: =T41+'P&L'!U39+CFS!U23 -> 2811.9356 | V41: =U41+'P&L'!V39+CFS!V23 -> 3181.472 | W41: =V41+'P&L'!W39+CFS!W23 -> 3557.4128 | X41: =W41+'P&L'!X39+CFS!X23 -> 3959.1367 | ... Z41: =Y41+'P&L'!Z39+CFS!Z23 -> 4776.1774
D42: Accumulated other comprehensive income (loss) | E42: mn $ | G42: -5.544 | H42: -0.413 | I42: -27.776 | J42: -41.302 | K42: -69.841 | L42: -82.404 | M42: -150.389 | N42: -137.102 | O42: -2.72 | P42: 241.942 | Q42: =P42 -> 241.942 | R42: =Q42 -> 241.942 | S42: =R42 -> 241.942 | T42: =S42 -> 241.942 | U42: =T42 -> 241.942 | V42: =U42 -> 241.942 | W42: =V42 -> 241.942 | X42: =W42 -> 241.942 | ... Z42: =Y42 -> 241.942
D43: Non-controlling interests | E43: mn $ | G43: 247.61 | H43: 266.844 | I43: 248.844 | J43: 208.515 | K43: 244.347 | L43: 296.628 | M43: 298.675 | N43: 292.357 | O43: 271.155 | P43: 317.444 | Q43: =P43 -> 317.444 | R43: =Q43 -> 317.444 | S43: =R43 -> 317.444 | T43: =S43 -> 317.444 | U43: =T43 -> 317.444 | V43: =U43 -> 317.444 | W43: =V43 -> 317.444 | X43: =W43 -> 317.444 | ... Z43: =Y43 -> 317.444
D45: Check | E45: mn $ | G45: =G8-G24 -> 0 | H45: =H8-H24 -> 0 | I45: =I8-I24 -> 0 | J45: =J8-J24 -> 0 | K45: =K8-K24 -> 0 | L45: =L8-L24 -> 0 | M45: =M8-M24 -> 0 | N45: =N8-N24 -> 0 | ... Z45: =Z8-Z24 -> 0
B49: . | C49: . | D49: . | E49: . | F49: . | G49: . | V49: . | W49: . | X49: . | Y49: . | Z49: .
O57: Total debt (incl. lease) | P57: =2131.206+12.885+109.283+752.494 -> 3005.868
O58: Debt (w/o lease) | P58: =2131.206+12.885 -> 2144.091
O59: EBITDA adj. | P59: =160+209+160+192 -> 721
O61: Total debt (incl. lease) / EBITDA adj. | P61: =P57/P59 -> 4.1690264
O62: Debt EBITDA adj. | P62: =P58/P59 -> 2.9737739
O64: Cash | P64: 645.736
O65: Net total debt (incl. lease) | P65: =P57-P64 -> 2360.132
O66: Net debt (w/o lease) | P66: =P58-P64 -> 1498.355
O68: Net total debt (incl. lease) / EBITDA adj. | P68: =P65/$P$59 -> 3.2734147
O69: Net debt / EBITDA adj. | P69: =P66/$P$59 -> 2.0781623

Sheet DCF
B2: Index | E2: Measure | F2: Base | G2: 2013 | H2: 2014 | I2: 2015 | J2: 2016 | K2: 2017 | L2: 2018 | M2: 2019 | N2: 2020 | O2: 2021 | P2: 2022 | Q2: 1П 2023 | R2: 2П 2023 | S2: 2024 | T2: 2025 | U2: 2026 | V2: 2027 | W2: 2028 | X2: 2029 | Y2: 2030 | Z2: 2031 | AA2: 2032
G3: fact | H3: fact | I3: fact | J3: fact | K3: fact | L3: fact | M3: fact | N3: fact | O3: fact | P3: fact | Q3: fact | R3: forecast | S3: forecast | T3: forecast | U3: forecast | V3: forecast | W3: forecast | X3: forecast | Y3: forecast | Z3: forecast | AA3: forecast
B6: DCF
D8: Revenue | E8: mn $ | Q8: 1978 | R8: ='P&L'!Q8-Q8 -> 1190.5897 | S8: ='P&L'!R8 -> 4407.8544 | T8: ='P&L'!S8 -> 4887.5047 | U8: ='P&L'!T8 -> 4719.2597 | V8: ='P&L'!U8 -> 4713.936 | W8: ='P&L'!V8 -> 4732.7918 | X8: ='P&L'!W8 -> 4751.723 | Y8: ='P&L'!X8 -> 4770.7298 | Z8: ='P&L'!Y8 -> 4789.8128 | AA8: ='P&L'!Z8 -> 4808.972
D10: EBITDA | E10: mn $ | Q10: 369 | R10: ='P&L'!Q17-Q10 -> 230.72192 | S10: ='P&L'!R17 -> 949.48262 | T10: ='P&L'!S17 -> 1083.967 | U10: ='P&L'!T17 -> 1026.9141 | V10: ='P&L'!U17 -> 1018.1779 | W10: ='P&L'!V17 -> 1016.3788 | X10: ='P&L'!W17 -> 1014.4426 | Y10: ='P&L'!X17 -> 1012.4018 | Z10: ='P&L'!Y17 -> 1010.1877 | AA10: ='P&L'!Z17 -> 1007.8291
D12: (-) profit tax | E12: mn $ | Q12: =-33.458 -> -33.458 | R12: =-R48-Q12 -> -11.402536 | S12: =-S48 -> -106.13067 | T12: =-T48 -> -134.28234 | U12: =-U48 -> -126.51267 | V12: =-V48 -> -127.41557 | W12: =-W48 -> -129.32925 | X12: =-X48 -> -130.96208 | Y12: =-Y48 -> -132.34087 | Z12: =-Z48 -> -133.47184 | AA12: =-AA48 -> -134.37764
D13: (-) ΔNWC | E13: mn $ | Q13: =464.156+459.153+32.752-702.787 -> 253.274 | R13: =-(Calc!Q202-Q13) -> 84.502817 | S13: =CFS!R10 -> -93.410546 | T13: =CFS!S10 -> -35.189168 | U13: =CFS!T10 -> 14.474636 | V13: =CFS!U10 -> 1.9802401 | W13: =CFS!V10 -> 0.15943181 | X13: =CFS!W10 -> 0.18573145 | Y13: =CFS!X10 -> 0.21264954 | Z13: =CFS!Y10 -> 0.24019879 | AA13: =CFS!Z10 -> 0.26839222
D14: (-) CapEx | E14: mn $ | Q14: =-80.915-157.163 -> -238.078 | R14: =(CFS!Q15+CFS!Q16)-Q14 -> -352.26262 | S14: =(CFS!R15+CFS!R16) -> -180.83022 | T14: =(CFS!S15+CFS!S16) -> -184.55384 | U14: =(CFS!T15+CFS!T16) -> -188.35414 | V14: =(CFS!U15+CFS!U16) -> -192.12123 | W14: =(CFS!V15+CFS!V16) -> -195.96365 | X14: =(CFS!W15+CFS!W16) -> -199.88292 | Y14: =(CFS!X15+CFS!X16) -> -203.88058 | Z14: =(CFS!Y15+CFS!Y16) -> -207.95819 | AA14: =(CFS!Z15+CFS!Z16) -> -212.11736
D16: FCFF | E16: mn $ | R16: =SUM(R10,R12:R14) -> -48.440418 | S16: =SUM(S10,S12:S14) -> 569.11119 | T16: =SUM(T10,T12:T14) -> 729.94167 | U16: =SUM(U10,U12:U14) -> 726.52193 | V16: =SUM(V10,V12:V14) -> 700.62137 | W16: =SUM(W10,W12:W14) -> 691.24532 | X16: =SUM(X10,X12:X14) -> 683.78332 | Y16: =SUM(Y10,Y12:Y14) -> 676.393 | ... AA16: =SUM(AA10,AA12:AA14) -> 661.60251
D18: Period | E18: x | R18: 0.25 | S18: =R18*2+0.5 -> 1 | T18: =S18+1 -> 2 | U18: =T18+1 -> 3 | V18: =U18+1 -> 4 | W18: =V18+1 -> 5 | X18: =W18+1 -> 6 | Y18: =X18+1 -> 7 | Z18: =Y18+1 -> 8 | AA18: =Z18+1 -> 9
D19: WACC | E19: % | F19: =Scenario!J40 -> 0.11375701 | R19: =$F19 -> 0.11375701 | S19: =$F19 -> 0.11375701 | T19: =$F19 -> 0.11375701 | U19: =$F19 -> 0.11375701 | V19: =$F19 -> 0.11375701 | W19: =$F19 -> 0.11375701 | X19: =$F19 -> 0.11375701 | Y19: =$F19 -> 0.11375701 | ... AA19: =$F19 -> 0.11375701
D20: Discount factor | E20: x | R20: =1/(1+R19)^R18 -> 0.97342476 | S20: =1/(1+S19)^S18 -> 0.89786191 | T20: =1/(1+T19)^T18 -> 0.80615601 | U20: =1/(1+U19)^U18 -> 0.72381678 | V20: =1/(1+V19)^V18 -> 0.64988752 | W20: =1/(1+W19)^W18 -> 0.58350925 | X20: =1/(1+X19)^X18 -> 0.52391073 | Y20: =1/(1+Y19)^Y18 -> 0.47039949 | ... AA20: =1/(1+AA19)^AA18 -> 0.37921538
D22: DFCFF | E22: mn $ | R22: =R16*R20 -> -47.153102 | S22: =S16*S20 -> 510.98326 | T22: =T16*T20 -> 588.44687 | U22: =U16*U20 -> 525.86876 | V22: =V16*V20 -> 455.32509 | W22: =W16*W20 -> 403.34804 | X22: =X16*X20 -> 358.24142 | Y22: =Y16*Y20 -> 318.17492 | ... AA22: =AA16*AA20 -> 250.88985
D24: TGR | E24: % | F24: =Scenario!J41 -> 0.02 | AA24: =$F24 -> 0.02
D25: TV | E25: mn $ | AA25: =AA16*(1+AA24)/(AA19-AA24)*AA20 -> 2729.4774
D28: EV | E28: mn $ | R28: =SUM(R22:AA22)+AA25 -> 6376.1563
D29: Net debt | E29: mn $ | R29: =(BS!P28+BS!P29+BS!P33+BS!P34)-BS!P11 -> 2163.929
D30: Other assets/liabilities | E30: mn $ | R30: =(BS!P15+BS!P20+BS!P21)-(BS!P30+BS!P35+BS!P36) -> 50.939
D31: Equity | E31: mn $ | R31: =R28-R29-R30 -> 4161.2883
D33: Diluted weighted average number of common shares outstanding | E33: mn # | R33: =71.677484 -> 71.677484
D34: Share price | E34: $ | R34: =R31/R33 -> 58.055725
B38: Profit tax
D40: EBITDA | E40: mn $ | R40: ='P&L'!Q17 -> 599.72192 | S40: ='P&L'!R17 -> 949.48262 | T40: ='P&L'!S17 -> 1083.967 | U40: ='P&L'!T17 -> 1026.9141 | V40: ='P&L'!U17 -> 1018.1779 | W40: ='P&L'!V17 -> 1016.3788 | X40: ='P&L'!W17 -> 1014.4426 | Y40: ='P&L'!X17 -> 1012.4018 | ... AA40: ='P&L'!Z17 -> 1007.8291
D42: (-) D&A | E42: mn $ | R42: ='P&L'!Q20 -> 358.28537 | S42: ='P&L'!R20 -> 378.29411 | T42: ='P&L'!S20 -> 361.26797 | U42: ='P&L'!T20 -> 346.03096 | V42: ='P&L'!U20 -> 332.43543 | W42: ='P&L'!V20 -> 320.33697 | X42: ='P&L'!W20 -> 309.613 | Y42: ='P&L'!X20 -> 300.15162 | ... AA42: ='P&L'!Z20 -> 284.61719
D44: EBIT | E44: mn $ | R44: =R40-R42 -> 241.43656 | S44: =S40-S42 -> 571.18851 | T44: =T40-T42 -> 722.69905 | U44: =U40-U42 -> 680.88314 | V44: =V40-V42 -> 685.7425 | W44: =W40-W42 -> 696.04182 | X44: =X40-X42 -> 704.8296 | Y44: =Y40-Y42 -> 712.25018 | ... AA44: =AA40-AA42 -> 723.21193
D46: Tax rate | E46: % | R46: ='P&L'!Q36 -> 0.18580673 | S46: ='P&L'!R36 -> 0.18580673 | T46: ='P&L'!S36 -> 0.18580673 | U46: ='P&L'!T36 -> 0.18580673 | V46: ='P&L'!U36 -> 0.18580673 | W46: ='P&L'!V36 -> 0.18580673 | X46: ='P&L'!W36 -> 0.18580673 | Y46: ='P&L'!X36 -> 0.18580673 | ... AA46: ='P&L'!Z36 -> 0.18580673
D48: Profit tax | E48: mn $ | R48: =R44*R46 -> 44.860536 | S48: =S44*S46 -> 106.13067 | T48: =T44*T46 -> 134.28234 | U48: =U44*U46 -> 126.51267 | V48: =V44*V46 -> 127.41557 | W48: =W44*W46 -> 129.32925 | X48: =X44*X46 -> 130.96208 | Y48: =Y44*Y46 -> 132.34087 | ... AA48: =AA44*AA46 -> 134.37764
B52: . | C52: . | D52: . | E52: . | F52: . | G52: . | W52: . | X52: . | Y52: . | Z52: . | AA52: .

Sheet Inputs
A1: INPUTS | B1: Отрасль | C1: Подотрасль/ Дивизион | D1: Источник | E1: Дата обновления | F1: Наименование | G1: Ед. измерения | H1: Link | I1: Комментарий к заполнению (формула) | J1: 2001 | K1: 2002 | L1: 2003 | M1: 2004 | N1: 2005 | O1: 2006 | P1: 2007 | Q1: 2008 | R1: 2009 | S1: 2010 | T1: 2011 | U1: 2012 | V1: 2013 | W1: 2014 | X1: 2015 | Y1: 2016 | Z1: 2017 | AA1: 2018 | AB1: 2019 | AC1: 2020 | AD1: 2021 | AE1: 2022 | AF1: 2023 | AG1: 2024 | AH1: 2025 | AI1: 2026 | AJ1: 2027 | AK1: 2028 | AL1: 2029 | AM1: 2030 | AN1: 2031 | AO1: 2032 | AP1: 2033 | AQ1: 2034 | AR1: 2035 | AS1: 2036 | AT1: 2037 | AU1: 2038 | AV1: 2039 | AW1: 2040 | AX1: 2041 | AY1: 2042 | AZ1: 2043 | BA1: 2044 | BB1: 2045 | BC1: 2046 | BD1: 2047 | BE1: 2048 | BF1: 2049 | BG1: 2050
A2: Общие | D2: ЦМИ | F2: Рост реального ВВП | G2: % | H2: Наименование листа, номер строки [например: Scenarios, line 352] | I2: С 2021 года прогноз CIB | J2: 0.051 | K2: 0.047 | L2: 0.072956141 | M2: 0.07175933 | N2: 0.063764415 | O2: 0.081534248 | P2: 0.085350329 | Q2: 0.052477517 | R2: -0.078208582 | S2: 0.045037137 | T2: 0.042643516 | U2: 0.036559016 | V2: 0.017853545 | W2: 0.0073860077 | X2: -0.025383168 | Y2: 0.0028878412 | Z2: 0.016468837 | AA2: 0.028063408 | AB2: 0.020329827 | AC2: -0.026832962 | AD2: 0.056142323 | AE2: -0.020696995 | AF2: 0.022180927 | AG2: 0.011781039 | AH2: 0.0094168941 | AI2: 0.013064327 | AJ2: 0.015 | AK2: =AJ2 -> 0.015 | AL2: =AK2 -> 0.015 | AM2: =AL2 -> 0.015 | AN2: =AM2 -> 0.015 | AO2: =AN2 -> 0.015 | AP2: =AO2 -> 0.015 | AQ2: =AP2 -> 0.015 | AR2: =AQ2 -> 0.015 | ... BG2: =BF2 -> 0.015
A3: Общие | D3: ЦМИ | F3: Инфляция - Рост индекса потребительских цен (RUB, eop CPI) | G3: % | I3: С 2021 года прогноз CIB | J3: 0.1858 | K3: 0.1506 | L3: 0.1199 | M3: 0.1173 | N3: 0.1092 | O3: 0.09 | P3: 0.1187 | Q3: 0.1328 | R3: 0.088 | S3: 0.0878 | T3: 0.061 | U3: 0.066 | V3: 0.065 | W3: 0.114 | X3: 0.1291 | Y3: 0.054 | Z3: 0.025 | AA3: 0.0426 | AB3: 0.0304 | AC3: 0.0491 | AD3: 0.083945618 | AE3: 0.1192357 | AF3: 0.070965338 | AG3: 0.06344142 | AH3: 0.031589623 | AI3: 0.039665644 | AJ3: 0.04 | AK3: =AJ3 -> 0.04 | AL3: =AK3 -> 0.04 | AM3: =AL3 -> 0.04 | AN3: =AM3 -> 0.04 | AO3: =AN3 -> 0.04 | AP3: =AO3 -> 0.04 | AQ3: =AP3 -> 0.04 | AR3: =AQ3 -> 0.04 | ... BG3: =BF3 -> 0.04
A4: Общие | D4: CIB Research | F4: Инфляция - Рост индекса потребительских цен в США, в долларах США (USD, eop CPI) | G4: % | I4: EoY PCE, source: FX/IR team | J4: 0.0172429 | K4: 0.0172766 | L4: 0.0141467 | M4: 0.021474 | N4: 0.0219964 | O4: 0.0222292 | P4: 0.0233468 | Q4: 0.0135128 | R4: 0.0161556 | S4: 0.0090211 | T4: 0.0205826 | U4: 0.0171363 | V4: 0.016331 | W4: 0.0146123 | X4: 0.0125234 | Y4: 0.0185337 | Z4: 0.0163842 | AA4: 0.019 | AB4: 0.023 | AC4: 0.014 | AD4: 0.07096524 | AE4: 0.065 | AF4: 0.031843454 | AG4: 0.020591825 | AH4: 0.020591825 | AI4: 0.020591825 | AJ4: 0.02 | AK4: 0.02 | AL4: 0.02 | AM4: 0.02 | AN4: 0.02 | AO4: 0.02 | AP4: 0.02 | AQ4: 0.02 | AR4: 0.02 | AS4: 0.02 | AT4: 0.02 | AU4: 0.02 | AV4: 0.02 | AW4: 0.02 | AX4: 0.02 | AY4: 0.02 | AZ4: 0.02 | BA4: 0.02 | BB4: 0.02 | BC4: =BB4 -> 0.02 | BD4: =BC4 -> 0.02 | BE4: =BD4 -> 0.02 | BF4: =BE4 -> 0.02 | BG4: =BF4 -> 0.02
A5: Общие | D5: ЦМИ | F5: Инфляция - Рост индекса цен производителей (RUB, eop PPI) | G5: % | I5: С 2021 года прогноз CIB | J5: 0.0833 | K5: 0.1765 | L5: 0.1254 | M5: 0.2883 | N5: 0.1335 | O5: 0.1037 | P5: 0.2507 | Q5: -0.07 | R5: 0.1385 | S5: 0.1666 | T5: 0.1201 | U5: 0.051 | V5: 0.0346 | W5: 0.0628 | X5: 0.1214 | Y5: 0.0745 | Z5: 0.0837 | AA5: 0.1171 | AB5: -0.0426 | AC5: 0.0356 | AD5: 0.2852 | AE5: -0.033 | AF5: 0.23133026 | AG5: 0.014501784 | AH5: 0.021269904 | AI5: 0.036386718 | AJ5: 0.04 | AK5: =AJ5 -> 0.04 | AL5: =AK5 -> 0.04 | AM5: =AL5 -> 0.04 | AN5: =AM5 -> 0.04 | AO5: =AN5 -> 0.04 | AP5: =AO5 -> 0.04 | AQ5: =AP5 -> 0.04 | AR5: =AQ5 -> 0.04 | ... BG5: =BF5 -> 0.04
A6: Общие | D6: ЦМИ | F6: Инфляция - Дефлятор ВВП (RUB, GDP Deflator) | G6: % | I6: =0.8CPI+0.2PPI; С 2021 года прогноз CIB | J6: 0.16489519 | K6: 0.15613926 | L6: 0.13780061 | M6: 0.20282077 | N6: 0.19306095 | O6: 0.15170047 | P6: 0.13804421 | Q6: 0.17959714 | R6: 0.019937228 | S6: 0.14187039 | T6: 0.15914448 | U6: 0.074 | V6: 0.05 | W6: 0.089 | X6: 0.079 | Y6: 0.035158922 | Z6: 0.044 | AA6: 0.099989476 | AB6: 0.030841738 | AC6: 0.009 | AD6: 0.19 | AE6: 0.158 | AF6: 0.064881731 | AG6: 0.075871885 | AH6: 0.032 | AI6: 0.035 | AJ6: =0.8*AJ3+0.2*AJ5 -> 0.04 | AK6: =0.8*AK3+0.2*AK5 -> 0.04 | AL6: =0.8*AL3+0.2*AL5 -> 0.04 | AM6: =0.8*AM3+0.2*AM5 -> 0.04 | AN6: =0.8*AN3+0.2*AN5 -> 0.04 | AO6: =0.8*AO3+0.2*AO5 -> 0.04 | AP6: =0.8*AP3+0.2*AP5 -> 0.04 | AQ6: =0.8*AQ3+0.2*AQ5 -> 0.04 | ... BG6: =0.8*BG3+0.2*BG5 -> 0.04
A7: Общие | D7: Расчет | F7: Курс рубля к доллару США в конце года (eop USD/RUB) | G7: $/руб | I7: 2015-17 модель ЦМИ c ценой на нефть CIB Research, после - CIB Research, с 2019 года прогноз CIB; =предыдущий год*1.02 | J7: 30.14 | K7: 31.78 | L7: 29.45 | M7: 27.75 | N7: 28.78 | O7: 26.33 | P7: 24.55 | Q7: 29.38 | R7: 30.24 | S7: 30.48 | T7: 32.2 | U7: 30.37 | V7: 32.73 | W7: 56.26 | X7: 72.8827 | Y7: 60.6569 | Z7: 57.6002 | AA7: 69.4706 | AB7: 61.9057 | AC7: 73.8757 | AD7: 74.2926 | AE7: 70.3375 | AF7: 89 | AG7: 89.84 | AH7: 91.04 | AI7: 92.24 | AJ7: =AJ14 -> 95.5638 | AK7: =AK14 -> 97.475076 | AL7: =AL14 -> 99.424578 | AM7: =AM14 -> 101.41307 | AN7: =AN14 -> 103.44133 | AO7: =AO14 -> 105.51016 | AP7: =AP14 -> 107.62036 | AQ7: =AQ14 -> 109.77277 | ... BG7: =BG14 -> 150.69449
A8: Общие | D8: Расчет | F8: Курс рубля к EUR в конце года (eop EUR/RUB) | G8: EUR/руб | I8: =EUR/USD*курс доллара | J8: 26.49 | K8: 33.11 | L8: 36.82 | M8: 37.81 | N8: 34.19 | O8: 34.7 | P8: 35.93 | Q8: 41.44 | R8: 43.39 | S8: 40.33 | T8: 41.67 | U8: 40.23 | V8: 44.97 | W8: 68.34 | X8: 79.56 | Y8: 63.8111 | Z8: 68.8668 | AA8: 79.4605 | AB8: 69.3406 | AC8: 90.6824 | AD8: 84.0695 | AE8: 75.6553 | AF8: =AF7*AF36 -> 95.948114 | AG8: =AG7*AG36 -> 96.578 | AH8: =AH7*AH36 -> 98.3232 | AI8: =AI7*AI36 -> 99.6192 | AJ8: =AJ7*AJ36 -> 103.2089 | AK8: =AK7*AK36 -> 105.27308 | AL8: =AL7*AL36 -> 107.37854 | AM8: =AM7*AM36 -> 109.52611 | ... BG8: =BG7*BG36 -> 162.75004
A9: Общие | D9: ЦМИ | F9: Рост реальных расп. денежных доходов населения | G9: % | I9: С 2021 года прогноз CIB | J9: 0.087 | K9: 0.111 | L9: 0.15 | M9: 0.104 | N9: 0.124 | O9: 0.135 | P9: 0.121 | Q9: 0.024 | R9: 0.03 | S9: 0.059 | T9: 0.005 | U9: 0.058 | V9: 0.048 | W9: -0.012 | X9: -0.024 | Y9: -0.045 | Z9: -0.005 | AA9: 0.0008 | AB9: 0.009025 | AC9: -0.01975 | AD9: 0.030790398 | AE9: -0.00945202 | AF9: 0.044452944 | AG9: 0.0062427696 | AH9: 0.0094875358 | AI9: 0.012054108 | AJ9: =AI9 -> 0.012054108 | AK9: =AJ9 -> 0.012054108 | AL9: =AK9 -> 0.012054108 | AM9: =AL9 -> 0.012054108 | AN9: =AM9 -> 0.012054108 | AO9: =AN9 -> 0.012054108 | AP9: =AO9 -> 0.012054108 | AQ9: =AP9 -> 0.012054108 | ... BG9: =BF9 -> 0.012054108
A10: Общие | D10: ЦМИ | F10: Ставка Libor 3m | G10: % | I10: ЦМИ, 2022 и далее = 2021 | J10: 0.0188125 | K10: 0.0138 | L10: 0.0115188 | M10: 0.0256438 | N10: 0.0453625 | O10: 0.0536 | P10: 0.047025 | Q10: 0.01425 | R10: 0.0025063 | S10: 0.0030281 | T10: 0.00581 | U10: 0.0043006071 | V10: 0.0026720119 | W10: 0.002336998 | X10: 0.006127 | Y10: 0.0099789 | Z10: 0.0169428 | AA10: 0.0280763 | AB10: 0.0190838 | AC10: 0.0024 | AD10: 0.0021 | AE10: 0.0477 | AF10: 0.057 | AG10: 0.0395 | AH10: 0.0295 | AI10: 0.0255 | AJ10: =AI10 -> 0.0255 | AK10: =AJ10 -> 0.0255 | AL10: =AK10 -> 0.0255 | AM10: =AL10 -> 0.0255 | AN10: =AM10 -> 0.0255 | AO10: =AN10 -> 0.0255 | AP10: =AO10 -> 0.0255 | AQ10: =AP10 -> 0.0255 | ... BG10: =BF10 -> 0.0255
A11: Общие | D11: ЦМИ | F11: Ставка Mosprime 3m | G11: % | I11: EoY | N11: 0.0622 | O11: 0.058 | P11: 0.0671 | Q11: 0.218 | R11: 0.0705 | S11: 0.0406 | T11: 0.0722 | U11: 0.070919919 | V11: 0.070100407 | W11: 0.10529433 | X11: 0.1179 | Y11: 0.1049 | Z11: 0.0788 | AA11: 0.0858 | AB11: 0.0645 | AC11: 0.0492 | AD11: 0.095 | AE11: 0.0841 | AF11: 0.0955 | AG11: 0.083 | AH11: 0.07 | AI11: 0.0655 | AJ11: =AI11+(AJ$39-AI$39) -> 0.0655 | AK11: =AJ11+(AK$39-AJ$39) -> 0.0655 | AL11: =AK11+(AL$39-AK$39) -> 0.0655 | AM11: =AL11+(AM$39-AL$39) -> 0.0655 | AN11: =AM11+(AN$39-AM$39) -> 0.0655 | AO11: =AN11+(AO$39-AN$39) -> 0.0655 | AP11: =AO11+(AP$39-AO$39) -> 0.0655 | AQ11: =AP11+(AQ$39-AP$39) -> 0.0655 | ... BG11: =BF11+(BG$39-BF$39) -> 0.0655
A12: Общие | D12: Законодательство | F12: Ставка НДС | G12: % | I12: С 2019 года прогноз CIB | U12: 0.18 | V12: 0.18 | W12: 0.18 | X12: 0.18 | Y12: 0.18 | Z12: 0.18 | AA12: 0.18 | AB12: 0.2 | AC12: 0.2 | AD12: 0.2 | AE12: =AD12 -> 0.2 | AF12: =AE12 -> 0.2 | AG12: =AF12 -> 0.2 | AH12: =AG12 -> 0.2 | AI12: =AH12 -> 0.2 | AJ12: =AI12 -> 0.2 | AK12: =AJ12 -> 0.2 | AL12: =AK12 -> 0.2 | ... BG12: =BF12 -> 0.2
A13: Общие | D13: Законодательство | F13: Ставка НДФЛ | G13: % | I13: С 2019 года прогноз CIB | U13: 0.13 | V13: 0.13 | W13: 0.13 | X13: 0.13 | Y13: 0.13 | Z13: 0.13 | AA13: 0.13 | AB13: 0.13 | AC13: 0.13 | AD13: 0.13 | AE13: =AD13 -> 0.13 | AF13: =AE13 -> 0.13 | AG13: =AF13 -> 0.13 | AH13: =AG13 -> 0.13 | AI13: =AH13 -> 0.13 | AJ13: =AI13 -> 0.13 | AK13: =AJ13 -> 0.13 | AL13: =AK13 -> 0.13 | ... BG13: =BF13 -> 0.13
A14: Общие | D14: ЦМИ | F14: Средний за период курс рубля к доллару США (av USD/RUB) | G14: $/руб | I14: С 2021 года прогноз CIB | J14: 29.17 | K14: 31.35 | L14: 30.68 | M14: 28.81 | N14: 28.7 | O14: 27.18 | P14: 25.57 | Q14: 24.81 | R14: 31.68 | S14: 30.36 | T14: 29.35 | U14: 31.07 | V14: 31.82 | W14: 38.38 | X14: 60.94 | Y14: 67.05 | Z14: 58.298185 | AA14: 62.926389 | AB14: 64.618432 | AC14: 72.323002 | AD14: 73.65435 | AE14: 68.485225 | AF14: 85.046667 | AG14: 91.455 | AH14: 92.49 | AI14: 93.69 | AJ14: =AI14*(1+AJ3-AJ4) -> 95.5638 | AK14: =AJ14*(1+AK3-AK4) -> 97.475076 | AL14: =AK14*(1+AL3-AL4) -> 99.424578 | AM14: =AL14*(1+AM3-AM4) -> 101.41307 | AN14: =AM14*(1+AN3-AN4) -> 103.44133 | AO14: =AN14*(1+AO3-AO4) -> 105.51016 | AP14: =AO14*(1+AP3-AP4) -> 107.62036 | AQ14: =AP14*(1+AQ3-AQ4) -> 109.77277 | ... BG14: =BF14*(1+BG3-BG4) -> 150.69449
A15: Общие | D15: ЦМИ | F15: Средний за период курс рубля к EUR (av EUR/RUB) | G15: EUR/руб | I15: формула | J15: 26.13 | K15: 29.65 | L15: 34.69 | M15: 35.81 | N15: 34.17 | O15: 34.11 | P15: 35.01 | Q15: 36.41 | R15: 44.13 | S15: 40.27 | T15: 40.87 | U15: 39.93752 | V15: 42.382855 | W15: 51.002878 | X15: 67.977302 | Y15: 73.992422 | Z15: 66.030462 | AA15: 74.132999 | AB15: 72.318717 | AC15: 82.835824 | AD15: 87.086125 | AE15: =AE14*AE35 -> 72.022339 | AF15: =AF14*AF35 -> 91.686149 | AG15: =AG14*AG35 -> 98.314125 | AH15: =AH14*AH35 -> 99.8892 | AI15: =AI14*AI35 -> 101.1852 | AJ15: =AJ14*AJ35 -> 103.2089 | AK15: =AK14*AK35 -> 105.27308 | AL15: =AL14*AL35 -> 107.37854 | ... BG15: =BG14*BG35 -> 162.75004
A16: Общие | D16: Законодательство | F16: Налог на имущество, инвентаризационная стоимость (НК Часть 2 Статья 380, максимальная ставка) | G16: % | I16: С 2019 года = 2018 | U16: 0.022 | V16: 0.022 | W16: 0.022 | X16: 0.022 | Y16: 0.022 | Z16: 0.022 | AA16: 0.022 | AB16: 0.022 | AC16: 0.022 | AD16: 0.022 | AE16: =AD16 -> 0.022 | AF16: =AE16 -> 0.022 | AG16: =AF16 -> 0.022 | AH16: =AG16 -> 0.022 | AI16: =AH16 -> 0.022 | AJ16: =AI16 -> 0.022 | AK16: =AJ16 -> 0.022 | AL16: =AK16 -> 0.022 | ... BG16: =BF16 -> 0.022
A17: Общие | D17: Законодательство | F17: Налог на имущество, кадастровая стоимость Москва (Закон г. Москвы от 05.11.2003 N 64, ред. от 25.11.2015, "О налоге на имущество организаций") | G17: % | I17: С 2019 года = 2018 | W17: 0.009 | X17: 0.012 | Y17: 0.013 | Z17: 0.014 | AA17: 0.015 | AB17: 0.016 | AC17: 0.017 | AD17: 0.018 | AE17: =AD17+0.1% -> 0.019 | AF17: =AE17+0.1% -> 0.02 | AG17: =AF17 -> 0.02 | AH17: =AG17 -> 0.02 | AI17: =AH17 -> 0.02 | AJ17: =AI17 -> 0.02 | AK17: =AJ17 -> 0.02 | AL17: =AK17 -> 0.02 | AM17: =AL17 -> 0.02 | AN17: =AM17 -> 0.02 | ... BG17: =BF17 -> 0.02
A18: Общие | D18: Законодательство | F18: Налог на имущество, кадастровая стоимость кроме Москвы (НК Часть 2 Статья 380, максимальная ставка) | G18: % | I18: С 2019 года = 2018 | W18: 0.01 | X18: 0.015 | Y18: 0.02 | Z18: 0.02 | AA18: 0.02 | AB18: 0.02 | AC18: 0.02 | AD18: 0.02 | AE18: =AD18 -> 0.02 | AF18: =AE18 -> 0.02 | AG18: =AF18 -> 0.02 | AH18: =AG18 -> 0.02 | AI18: =AH18 -> 0.02 | AJ18: =AI18 -> 0.02 | AK18: =AJ18 -> 0.02 | AL18: =AK18 -> 0.02 | ... BG18: =BF18 -> 0.02
A19: Общие | D19: ЦМИ | F19: Инфляция з.платы (Рост номинальных заработных плат) | G19: % | I19: С 2021 года прогноз CIB; =CPI+рост реальных доходов | J19: 0.457 | K19: 0.346 | L19: 0.261 | M19: 0.226 | N19: 0.269 | O19: 0.243 | P19: 0.278 | Q19: 0.272 | R19: 0.078 | S19: 0.124 | T19: 0.115 | U19: 0.139 | V19: 0.119 | W19: 0.091 | X19: 0.051 | Y19: 0.079 | Z19: 0.067 | AA19: 0.10965864 | AB19: 0.091798583 | AC19: 0.07603513 | AD19: 0.10656959 | AE19: 0.13434236 | AF19: 0.12369823 | AG19: 0.089980247 | AH19: 0.054399205 | AI19: 0.050882975 | AJ19: =AJ3+AJ9 -> 0.052054108 | AK19: =AK3+AK9 -> 0.052054108 | AL19: =AL3+AL9 -> 0.052054108 | AM19: =AM3+AM9 -> 0.052054108 | AN19: =AN3+AN9 -> 0.052054108 | AO19: =AO3+AO9 -> 0.052054108 | AP19: =AP3+AP9 -> 0.052054108 | AQ19: =AQ3+AQ9 -> 0.052054108 | ... BG19: =BG3+BG9 -> 0.052054108
A20: Общие | D20: ЦМИ | F20: Ставка Euribor 3m | G20: % | I20: EoY, ЦМИ, 2022 и далее = 2021 | J20: 0.03294 | K20: 0.02865 | L20: 0.02124 | M20: 0.02155 | N20: 0.02488 | O20: 0.03725 | P20: 0.04684 | Q20: 0.02892 | R20: 0.007 | S20: 0.01006 | T20: 0.01356 | U20: 0.0049081058 | V20: 0.0015218502 | W20: 0.0017973474 | X20: -0.0012786 | Y20: -0.00319 | Z20: -0.003279 | AA20: -0.00309 | AB20: -0.00383 | AC20: -0.00545 | AD20: -0.00572 | AE20: 0.02132 | AF20: 0.039 | AG20: 0.023 | AH20: 0.014 | AI20: 0.0095 | AJ20: =AI20 -> 0.0095 | AK20: =AJ20 -> 0.0095 | AL20: =AK20 -> 0.0095 | AM20: =AL20 -> 0.0095 | AN20: =AM20 -> 0.0095 | AO20: =AN20 -> 0.0095 | AP20: =AO20 -> 0.0095 | AQ20: =AP20 -> 0.0095 | ... BG20: =BF20 -> 0.0095
A21: Общие | D21: ЦМИ | F21: Процентный своп IRS 1Y Mosprime | G21: % | I21: EoY | O21: 0.0578 | P21: 0.0568 | Q21: 0.1575 | R21: 0.0732 | S21: 0.05335 | T21: 0.0721 | U21: 0.073222594 | V21: 0.069354529 | W21: 0.10586616 | X21: 0.116 | Y21: 0.10465 | Z21: 0.078 | AA21: 0.0957 | AB21: 0.0646 | AC21: 0.0504 | AD21: 0.1022 | AE21: 0.088 | AF21: 0.14 | AG21: 0.1035 | AH21: 0.0735 | AI21: 0.062 | AJ21: =AI21+(AJ$39-AI$39) -> 0.062 | AK21: =AJ21+(AK$39-AJ$39) -> 0.062 | AL21: =AK21+(AL$39-AK$39) -> 0.062 | AM21: =AL21+(AM$39-AL$39) -> 0.062 | AN21: =AM21+(AN$39-AM$39) -> 0.062 | AO21: =AN21+(AO$39-AN$39) -> 0.062 | AP21: =AO21+(AP$39-AO$39) -> 0.062 | AQ21: =AP21+(AQ$39-AP$39) -> 0.062 | ... BG21: =BF21+(BG$39-BF$39) -> 0.062
A22: Общие | D22: ЦМИ | F22: Процентный своп IRS 3Y Mosprime | G22: % | I22: EoY | O22: 0.0615 | P22: 0.0667 | Q22: 0.16 | R22: 0.076 | S22: 0.0675 | T22: 0.0742 | U22: 0.075070977 | V22: 0.069934962 | W22: 0.09891364 | X22: 0.1079 | Y22: 0.0953 | Z22: 0.0759 | AA22: 0.0968 | AB22: 0.0634 | AC22: 0.0554 | AD22: 0.0935 | AE22: 0.097 | AF22: 0.13 | AG22: 0.105 | AH22: 0.074 | AI22: 0.064 | AJ22: =AI22+(AJ$39-AI$39) -> 0.064 | AK22: =AJ22+(AK$39-AJ$39) -> 0.064 | AL22: =AK22+(AL$39-AK$39) -> 0.064 | AM22: =AL22+(AM$39-AL$39) -> 0.064 | AN22: =AM22+(AN$39-AM$39) -> 0.064 | AO22: =AN22+(AO$39-AN$39) -> 0.064 | AP22: =AO22+(AP$39-AO$39) -> 0.064 | AQ22: =AP22+(AQ$39-AP$39) -> 0.064 | ... BG22: =BF22+(BG$39-BF$39) -> 0.064
A23: Общие | D23: ЦМИ | F23: Процентный своп IRS 5Y Mosprime | G23: % | I23: EoY | O23: 0.064 | P23: 0.0718 | Q23: 0.165 | R23: 0.0785 | S23: 0.0735 | T23: 0.0754 | U23: 0.076751556 | V23: 0.071434632 | W23: 0.096330785 | X23: 0.1062 | Y23: 0.0918 | Z23: 0.0755 | AA23: 0.0956 | AB23: 0.0646 | AC23: 0.0588 | AD23: 0.0894 | AE23: 0.102 | AF23: 0.123 | AG23: 0.1065 | AH23: 0.0775 | AI23: 0.0695 | AJ23: =AI23+(AJ$39-AI$39) -> 0.0695 | AK23: =AJ23+(AK$39-AJ$39) -> 0.0695 | AL23: =AK23+(AL$39-AK$39) -> 0.0695 | AM23: =AL23+(AM$39-AL$39) -> 0.0695 | AN23: =AM23+(AN$39-AM$39) -> 0.0695 | AO23: =AN23+(AO$39-AN$39) -> 0.0695 | AP23: =AO23+(AP$39-AO$39) -> 0.0695 | AQ23: =AP23+(AQ$39-AP$39) -> 0.0695 | ... BG23: =BF23+(BG$39-BF$39) -> 0.0695
A24: Общие | D24: ЦМИ | F24: Процентный своп IRS 7Y Mosprime | G24: % | I24: EoY | O24: 0.0646 | P24: 0.0737 | Q24: 0.165 | R24: 0.0815 | S24: 0.07651 | T24: 0.0771 | U24: 0.078596912 | V24: 0.073566594 | W24: 0.095379851 | X24: 0.1054 | Y24: 0.0896 | Z24: 0.0753 | AA24: 0.0945 | AB24: 0.0682 | AC24: 0.0613 | AD24: 0.0879 | AE24: =AE23+(AE25-AE23)*2/5 -> 0.1048 | AF24: =AF23+(AF25-AF23)*2/5 -> 0.1204 | AG24: =AG23+(AG25-AG23)*2/5 -> 0.1067 | AH24: =AH23+(AH25-AH23)*2/5 -> 0.0795 | AI24: =AI23+(AI25-AI23)*2/5 -> 0.0719 | AJ24: =AJ23+(AJ25-AJ23)*2/5 -> 0.0719 | AK24: =AK23+(AK25-AK23)*2/5 -> 0.0719 | AL24: =AL23+(AL25-AL23)*2/5 -> 0.0719 | ... BG24: =BG23+(BG25-BG23)*2/5 -> 0.0719
A25: Общие | D25: ЦМИ | F25: Процентный своп IRS 10Y Mosprime | G25: % | I25: EoY | O25: 0.0651 | P25: 0.0766 | Q25: 0.165 | R25: 0.082 | S25: 0.07951 | T25: 0.0789 | U25: 0.081269617 | V25: 0.076304414 | W25: 0.095675602 | X25: 0.1039 | Y25: 0.0873 | Z25: 0.0753 | AA25: 0.0932 | AB25: 0.0684 | AC25: 0.0646 | AD25: 0.0877 | AE25: 0.109 | AF25: 0.1165 | AG25: 0.107 | AH25: 0.0825 | AI25: 0.0755 | AJ25: =AI25+(AJ$39-AI$39) -> 0.0755 | AK25: =AJ25+(AK$39-AJ$39) -> 0.0755 | AL25: =AK25+(AL$39-AK$39) -> 0.0755 | AM25: =AL25+(AM$39-AL$39) -> 0.0755 | AN25: =AM25+(AN$39-AM$39) -> 0.0755 | AO25: =AN25+(AO$39-AN$39) -> 0.0755 | AP25: =AO25+(AP$39-AO$39) -> 0.0755 | AQ25: =AP25+(AQ$39-AP$39) -> 0.0755 | ... BG25: =BF25+(BG$39-BF$39) -> 0.0755
A26: Общие | D26: Расчет | F26: Средний за период курс рубля к CHF (av CHF/RUB) | G26: CHF/руб | I26: формула | J26: 17.318563 | K26: 20.225352 | L26: 22.797648 | M26: 23.200051 | N26: 22.726587 | O26: 21.674498 | P26: 21.310417 | Q26: 22.92536 | R26: 29.245194 | S26: 29.492689 | T26: 33.218057 | U26: 33.114757 | V26: 34.428351 | W26: 42.014608 | X26: 63.877109 | Y26: 67.848924 | Z26: 59.296313 | AA26: 64.271353 | AB26: 65.038546 | AC26: 77.342137 | AD26: 80.517746 | AE26: =AE14/AE41 -> 74.698218 | AF26: =AF14/AF41 -> 93.21274 | AG26: =AG14/AG41 -> 101.56885 | AH26: =AH14/AH41 -> 104.07858 | AI26: =AI14/AI41 -> 105.42894 | AJ26: =AJ14/AJ41 -> 107.53751 | AK26: =AK14/AK41 -> 109.68827 | AL26: =AL14/AL41 -> 111.88203 | ... BG26: =BG14/BG41 -> 169.57583
A27: Общие | D27: Расчет | F27: Курс рубля к CHF в конце года (eop CHF/RUB) | G27: CHF/руб | I27: формула | J27: 17.86 | K27: 22.778 | L27: 23.5995 | M27: 24.4827 | N27: 21.9563 | O27: 21.597 | P27: 21.7879 | Q27: 27.8329 | R27: 29.137 | S27: 32.4084 | T27: 34.2366 | U27: 33.2888 | V27: 36.696 | W27: 56.9763 | X27: 73.611527 | Y27: 59.4151 | Z27: 58.9743 | AA27: 70.5787 | AB27: 63.6039 | AC27: 83.5131 | AD27: 80.9376 | AE27: =AE7/AE40 -> 77.272183 | AF27: =AF7/AF40 -> 99.075472 | AG27: =AG7/AG40 -> 101.33611 | AH27: =AH7/AH40 -> 102.4469 | AI27: =AI7/AI40 -> 103.79726 | AJ27: =AJ7/AJ40 -> 107.53751 | AK27: =AK7/AK40 -> 109.68827 | AL27: =AL7/AL40 -> 111.88203 | ... BG27: =BG7/BG40 -> 169.57583
A28: Общие | D28: CIB Research | F28: Инфляция - Рост индекса цен производителей в США, в долларах США (USD, eop PPI) | G28: % | I28: =CPI | J28: -0.016 | K28: 0.012 | L28: 0.04 | M28: 0.042 | N28: 0.054 | O28: 0.011 | P28: 0.062 | Q28: -0.009 | R28: 0.043 | S28: 0.038 | T28: 0.047 | U28: 0.021 | V28: 0.004 | W28: 0.008 | X28: -0.051 | Y28: -0.019 | Z28: 0.032 | AA28: 0.013 | AB28: 0.017 | AC28: -0.008 | AD28: 0.122 | AE28: =AE4 -> 0.065 | AF28: =AF4 -> 0.031843454 | AG28: =AG4 -> 0.020591825 | AH28: =AH4 -> 0.020591825 | AI28: =AI4 -> 0.020591825 | AJ28: =AJ4 -> 0.02 | AK28: =AK4 -> 0.02 | AL28: =AL4 -> 0.02 | ... BG28: =BG4 -> 0.02
A29: Общие | D29: CIB Research | F29: Инфляция - Рост индекса потребительских цен в Еврозоне (EUR, eop CPI) | G29: % | I29: EoY HICP, source: FX/IR team | J29: 0.021 | K29: 0.023 | L29: 0.02 | M29: 0.023 | N29: 0.023 | O29: 0.019 | P29: 0.031 | Q29: 0.016 | R29: 0.009 | S29: 0.022 | T29: 0.028 | U29: 0.022212505 | V29: 0.0084695012 | W29: -0.0016118086 | X29: 0.002 | Y29: 0.011 | Z29: 0.013 | AA29: 0.015 | AB29: 0.013 | AC29: -0.003 | AD29: 0.05 | AE29: 0.092 | AF29: 0.041286925 | AG29: 0.022018961 | AH29: 0.020591825 | AI29: 0.020591825 | AJ29: 0.02 | AK29: =AJ29 -> 0.02 | AL29: =AK29 -> 0.02 | AM29: =AL29 -> 0.02 | AN29: =AM29 -> 0.02 | AO29: =AN29 -> 0.02 | AP29: =AO29 -> 0.02 | AQ29: =AP29 -> 0.02 | AR29: =AQ29 -> 0.02 | ... BG29: =BF29 -> 0.02
A30: Общие | D30: CIB Research | F30: Инфляция - Рост индекса цен производителей в Еврозоне (EUR, eop PPI) | G30: % | I30: =CPI | J30: -0.005 | K30: 0.015 | L30: 0.01 | M30: 0.037 | N30: 0.045 | O30: 0.038 | P30: 0.044 | Q30: 0.015 | R30: -0.03 | S30: 0.05 | T30: 0.044 | U30: 0.024 | V30: -0.001 | W30: -0.013 | X30: -0.019 | Y30: -0.011 | Z30: 0.022 | AA30: 0.031 | AB30: -0.007 | AC30: -0.011 | AD30: 0.237 | AE30: =AE29 -> 0.092 | AF30: =AF29 -> 0.041286925 | AG30: =AG29 -> 0.022018961 | AH30: =AH29 -> 0.020591825 | AI30: =AI29 -> 0.020591825 | AJ30: =AJ29 -> 0.02 | AK30: =AK29 -> 0.02 | AL30: =AL29 -> 0.02 | ... BG30: =BG29 -> 0.02
A31: Общие | D31: Законодательство | F31: Ставка страхового взноса в ФОМС | G31: % | I31: Не меняется | U31: 0.051 | V31: 0.051 | W31: 0.051 | X31: 0.051 | Y31: 0.051 | Z31: 0.051 | AA31: 0.051 | AB31: 0.051 | AC31: 0.051 | AD31: 0.051 | AE31: =AD31 -> 0.051 | AF31: =AE31 -> 0.051 | AG31: =AF31 -> 0.051 | AH31: =AG31 -> 0.051 | AI31: =AH31 -> 0.051 | AJ31: =AI31 -> 0.051 | AK31: =AJ31 -> 0.051 | AL31: =AK31 -> 0.051 | ... BG31: =BF31 -> 0.051
A32: Общие | D32: Законодательство | F32: Ставка страхового взноса в ФСС | G32: % | I32: Не меняется | U32: 0.029 | V32: 0.029 | W32: 0.029 | X32: 0.029 | Y32: 0.029 | Z32: 0.029 | AA32: 0.029 | AB32: 0.029 | AC32: 0.029 | AD32: 0.029 | AE32: =AD32 -> 0.029 | AF32: =AE32 -> 0.029 | AG32: =AF32 -> 0.029 | AH32: =AG32 -> 0.029 | AI32: =AH32 -> 0.029 | AJ32: =AI32 -> 0.029 | AK32: =AJ32 -> 0.029 | AL32: =AK32 -> 0.029 | ... BG32: =BF32 -> 0.029
A33: Общие | D33: Законодательство | F33: Ставка страхового взноса в ПФР | G33: % | I33: Не меняется | U33: 0.22 | V33: 0.22 | W33: 0.22 | X33: 0.22 | Y33: 0.22 | Z33: 0.22 | AA33: 0.22 | AB33: 0.22 | AC33: 0.22 | AD33: 0.22 | AE33: =AD33 -> 0.22 | AF33: =AE33 -> 0.22 | AG33: =AF33 -> 0.22 | AH33: =AG33 -> 0.22 | AI33: =AH33 -> 0.22 | AJ33: =AI33 -> 0.22 | AK33: =AJ33 -> 0.22 | AL33: =AK33 -> 0.22 | ... BG33: =BF33 -> 0.22
A34: Общие | D34: Законодательство | F34: Ставка налога на прибыль организаций | G34: % | I34: Не меняется | U34: 0.2 | V34: 0.2 | W34: 0.2 | X34: 0.2 | Y34: 0.2 | Z34: 0.2 | AA34: 0.2 | AB34: 0.2 | AC34: 0.2 | AD34: 0.2 | AE34: =AD34 -> 0.2 | AF34: =AE34 -> 0.2 | AG34: =AF34 -> 0.2 | AH34: =AG34 -> 0.2 | AI34: =AH34 -> 0.2 | AJ34: =AI34 -> 0.2 | AK34: =AJ34 -> 0.2 | AL34: =AK34 -> 0.2 | ... BG34: =BF34 -> 0.2
A35: Общие | D35: ЦМИ | F35: Средний за период курс EUR к доллару США (av EUR/USD) | G35: EUR/$ | I35: 2017-21 ЦМИ | J35: 0.8956 | K35: 0.9456 | L35: 1.1312 | M35: 1.2439 | N35: 1.2441 | O35: 1.2556 | P35: 1.3705 | Q35: 1.4708 | R35: 1.3948 | S35: 1.3257 | T35: 1.392 | W35: 1.32 | X35: 1.1098449 | Y35: 1.1075317 | Z35: 1.1301778 | AA35: 1.1806945 | AB35: 1.1073 | AC35: 1.1411541 | AD35: 1.183766 | AE35: 1.0516478 | AF35: 1.0780687 | AG35: 1.075 | AH35: 1.08 | AI35: 1.08 | AJ35: =AI35 -> 1.08 | AK35: =AJ35 -> 1.08 | AL35: =AK35 -> 1.08 | AM35: =AL35 -> 1.08 | AN35: =AM35 -> 1.08 | AO35: =AN35 -> 1.08 | AP35: =AO35 -> 1.08 | AQ35: =AP35 -> 1.08 | ... BG35: =BF35 -> 1.08
A36: Общие | D36: Расчет | F36: Курс EUR к доллару США в конце года (eop EUR/USD) | G36: EUR/$ | J36: 0.8813 | K36: 1.0487 | L36: 1.263 | M36: 1.3621 | N36: 1.1797 | O36: 1.317 | P36: 1.4721 | Q36: 1.3917 | R36: 1.4406 | S36: 1.3362 | T36: 1.2939 | U36: 1.3194 | V36: 1.3791 | W36: 1.2141 | X36: 1.08655 | Y36: 1.0516 | Z36: 1.1994 | AA36: 1.1456 | AB36: 1.1214 | AC36: 1.2217 | AD36: 1.137 | AE36: =AE35 -> 1.0516478 | AF36: =AF35 -> 1.0780687 | AG36: =AG35 -> 1.075 | AH36: =AH35 -> 1.08 | AI36: =AH36 -> 1.08 | AJ36: =AI36 -> 1.08 | AK36: =AJ36 -> 1.08 | AL36: =AK36 -> 1.08 | AM36: =AL36 -> 1.08 | AN36: =AN35 -> 1.08 | AO36: =AO35 -> 1.08 | AP36: =AP35 -> 1.08 | AQ36: =AQ35 -> 1.08 | AR36: =AR35 -> 1.08 | AS36: =AS35 -> 1.08 | AT36: =AT35 -> 1.08 | AU36: =AU35 -> 1.08 | ... BG36: =BG35 -> 1.08
A37: Общие | D37: ЦМИ | F37: ECB policy rate (Main Refinancing Operations rate) | G37: % | I37: EoY, ЦМИ, 2022 и далее = 2021 | J37: 0.0325 | K37: 0.0275 | L37: 0.02 | M37: 0.02 | N37: 0.0225 | O37: 0.035 | P37: 0.04 | Q37: 0.025 | R37: 0.01 | S37: 0.01 | T37: 0.01 | U37: 0.0075 | V37: 0.0025 | W37: 0.0005 | X37: 0.0005 | Y37: 0 | Z37: 0 | AA37: 0 | AB37: 0 | AC37: 0 | AD37: 0 | AE37: 0.025 | AF37: 0.045 | AG37: 0.0325 | AH37: 0.0225 | AI37: 0.015 | AJ37: =AI37 -> 0.015 | AK37: =AJ37 -> 0.015 | AL37: =AK37 -> 0.015 | AM37: =AL37 -> 0.015 | AN37: =AM37 -> 0.015 | AO37: =AN37 -> 0.015 | AP37: =AO37 -> 0.015 | AQ37: =AP37 -> 0.015 | ... BG37: =BF37 -> 0.015
A38: Общие | D38: Расчет | F38: Курс EUR к CHF в конце года (eop EUR/CHF) | G38: EUR/CHF | I38: формула | J38: 1.4777 | K38: 1.4514 | L38: 1.56045 | M38: 1.546 | N38: 1.55615 | O38: 1.6091 | P38: 1.6536 | Q38: 1.49358 | R38: 1.48365 | S38: 1.25161 | T38: 1.21689 | U38: 1.2072 | V38: 1.2276 | W38: 1.2024 | X38: 1.0887316 | Y38: 1.074 | Z38: 1.17 | AA38: 1.127 | AB38: 1.0854 | AC38: 1.0809642 | AD38: 1.0373444 | AE38: 1.065 | AF38: 1.06 | AG38: 1.055 | AH38: =AH36*AH40 -> 0.9597479 | AI38: =AI36*AI40 -> 0.9597479 | AJ38: =AJ36*AJ40 -> 0.9597479 | AK38: =AK36*AK40 -> 0.9597479 | AL38: =AL36*AL40 -> 0.9597479 | AM38: =AM36*AM40 -> 0.9597479 | AN38: =AN36*AN40 -> 0.9597479 | AO38: =AO36*AO40 -> 0.9597479 | ... BG38: =BG36*BG40 -> 0.9597479
A39: Общие | D39: ЦМИ | F39: Ключевая ставка на конец года (eop) | G39: % | I39: С 2021 года = инфляция + 2% | T39: 0.0525 | W39: 0.17 | X39: 0.11 | Y39: 0.1 | Z39: 0.0775 | AA39: 0.0775 | AB39: 0.0625 | AC39: 0.0425 | AD39: 0.085 | AE39: 0.075 | AF39: 0.14 | AG39: 0.11 | AH39: 0.08 | AI39: 0.06 | AJ39: =AI39 -> 0.06 | AK39: =AJ39 -> 0.06 | AL39: =AK39 -> 0.06 | AM39: =AL39 -> 0.06 | AN39: =AM39 -> 0.06 | AO39: =AN39 -> 0.06 | AP39: =AO39 -> 0.06 | AQ39: =AP39 -> 0.06 | ... BG39: =BF39 -> 0.06
A40: Общие | D40: Расчет | F40: USD/CHF eop | G40: USD/CHF | J40: 1.6603 | K40: 1.3836 | L40: 1.2391 | M40: 1.1404 | N40: 1.3134 | O40: 1.2201 | P40: 1.1335 | Q40: 1.0687 | R40: 1.0352 | S40: 0.9352 | T40: 0.9381 | X40: 1.01 | Y40: 1.016 | Z40: 0.974 | AA40: 0.983 | AB40: 0.9676 | AC40: 0.8852 | AD40: 0.9129 | AE40: 0.91025641 | AF40: 0.89830508 | AG40: 0.88655462 | AH40: =AI41 -> 0.88865546 | AI40: =AJ41 -> 0.88865546 | AJ40: =AK41 -> 0.88865546 | AK40: =AL41 -> 0.88865546 | AL40: =AM41 -> 0.88865546 | AM40: =AM41 -> 0.88865546 | AN40: =AO41 -> 0.88865546 | AO40: =AP41 -> 0.88865546 | AP40: =AQ41 -> 0.88865546 | AQ40: =AR41 -> 0.88865546 | AR40: =AS41 -> 0.88865546 | AS40: =AT41 -> 0.88865546 | AT40: =AU41 -> 0.88865546 | AU40: =AV41 -> 0.88865546 | ... BA40: =BB41 -> 0.88865546 | BB40: =BB41 -> 0.88865546 | BC40: =BC41 -> 0.88865546 | BD40: =BD41 -> 0.88865546 | BE40: =BE41 -> 0.88865546 | BF40: =BF41 -> 0.88865546 | BG40: =BG41 -> 0.88865546
A41: Общие | D41: ЦМИ | F41: USD/CHF average | G41: USD/CHF | I41: формула | J41: 1.6871387 | K41: 1.5552533 | L41: 1.3443716 | M41: 1.2421034 | N41: 1.2463265 | O41: 1.2528881 | P41: 1.2000165 | Q41: 1.0823534 | R41: 1.0849889 | S41: 1.0423498 | T41: 0.88658192 | Y41: 0.98173705 | Z41: 0.985 | AA41: 0.985 | AB41: 0.993825 | AC41: 0.93885 | AD41: 0.91415 | AE41: 0.91682542 | AF41: 0.91239316 | AG41: 0.90042373 | AH41: 0.88865546 | AI41: =AH41 -> 0.88865546 | AJ41: =AI41 -> 0.88865546 | AK41: =AJ41 -> 0.88865546 | AL41: =AK41 -> 0.88865546 | AM41: =AL41 -> 0.88865546 | AN41: =AM41 -> 0.88865546 | AO41: =AN41 -> 0.88865546 | AP41: =AO41 -> 0.88865546 | ... BG41: =BF41 -> 0.88865546
A42: Общие | D42: ЦМИ | F42: Ключевая ставка средняя за период (av) | G42: % | I42: формула | W42: 0.084375 | X42: 0.12625 | Y42: 0.105 | Z42: 0.0903125 | AA42: 0.074375 | AB42: 0.073125 | AC42: 0.05 | AD42: 0.0578125 | AE42: 0.1125 | AF42: 0.096875 | AG42: 0.13375 | AH42: 0.0925 | AI42: 0.07 | AJ42: =AJ39 -> 0.06 | AK42: =AK39 -> 0.06 | AL42: =AL39 -> 0.06 | AM42: =AM39 -> 0.06 | AN42: =AN39 -> 0.06 | AO42: =AO39 -> 0.06 | AP42: =AP39 -> 0.06 | AQ42: =AQ39 -> 0.06 | ... BG42: =BG39 -> 0.06
A43: Общие | D43: ЦМИ | F43: Курс юаня к доллару (средний за период) | G43: USD/CNY | J43: 8.27705 | K43: 8.27695 | L43: 8.277025 | M43: 8.2768 | N43: 8.193025 | O43: 7.972825 | P43: 7.606025 | Q43: 6.950925 | R43: 6.8315 | S43: 6.76895 | T43: 6.464025 | U43: 6.30805 | V43: 6.148975 | W43: 6.1616 | X43: 6.284675 | Y43: 6.6475 | Z43: 6.757225 | AA43: 6.616875 | AB43: 6.905625 | AC43: 6.898575 | AD43: 6.5 | AE43: 6.7295 | AF43: 7.0978461 | AG43: 7.19 | AH43: 7.015 | AI43: 6.90475 | AJ43: =AI43 -> 6.90475 | AK43: =AJ43 -> 6.90475 | AL43: =AK43 -> 6.90475 | AM43: =AL43 -> 6.90475 | AN43: =AM43 -> 6.90475 | AO43: =AN43 -> 6.90475 | AP43: =AO43 -> 6.90475 | AQ43: =AP43 -> 6.90475 | ... BG43: =BF43 -> 6.90475
A44: Общие | D44: ЦМИ | F44: Курс юаня к доллару (на конец периода) | G44: USD/CNY | J44: 8.2765 | K44: 8.277 | L44: 8.2767 | M44: 8.2765 | N44: 8.0702 | O44: 7.8045 | P44: 7.3037 | Q44: 6.8277 | R44: 6.8271 | S44: 6.607 | T44: 6.295 | U44: 6.2306 | V44: 6.0543 | W44: 6.2055 | X44: 6.4937 | Y44: 6.945 | Z44: 6.5068 | AA44: 6.8785 | AB44: 6.9632 | AC44: 6.5272 | AD44: 6.373 | AE44: =AE43 -> 6.7295 | AF44: =AF43 -> 7.0978461 | AG44: =AG43 -> 7.19 | AH44: =AH43 -> 7.015 | AI44: =AI43 -> 6.90475 | AJ44: =AJ43 -> 6.90475 | AK44: =AK43 -> 6.90475 | AL44: =AL43 -> 6.90475 | ... BG44: =BG43 -> 6.90475
A45: Общие | D45: ЦМИ | F45: Курс рубля к юаню, руб. (средний за период) | G45: CNY/руб | J45: 3.527325 | K45: 3.791175 | L45: 3.7073 | M45: 3.47975 | N45: 3.45395 | O45: 3.408225 | P45: 3.3615 | Q45: 3.58125 | R45: 4.649125 | S45: 4.486975 | T45: 4.550725 | U45: 4.922125 | V45: 5.181825 | W45: 6.26285 | X45: 9.738075 | Y45: 10.094625 | Z45: 8.636 | AA45: 9.485225 | AB45: 9.373575 | AC45: 10.491275 | AD45: 11.331438 | AE45: =AE14/AE43 -> 10.176867 | AF45: =AF14/AF43 -> 11.982039 | AG45: =AG14/AG43 -> 12.71975 | AH45: =AH14/AH43 -> 13.184604 | AI45: =AI14/AI43 -> 13.56892 | AJ45: =AJ14/AJ43 -> 13.840298 | AK45: =AK14/AK43 -> 14.117104 | AL45: =AL14/AL43 -> 14.399446 | ... BG45: =BG14/BG43 -> 21.824756
A46: Общие | D46: ЦМИ | F46: Курс рубля к юаню, руб. (на конец периода) | G46: CNY/руб | J46: 3.6857 | K46: 3.8607 | L46: 3.5331 | M46: 3.3492 | N46: 3.5614 | O46: 3.3731 | P46: 3.3682 | Q46: 4.3064 | R46: 4.3994 | S46: 4.6219 | T46: 5.1024 | U46: 4.9036 | V46: 5.433 | W46: 9.354 | X46: 11.372 | Y46: 8.7827 | Z46: 8.85 | AA46: 10.0892 | AB46: 8.9053 | AC46: 11.3156 | AD46: 11.657398 | AE46: =AE7/AE44 -> 10.452114 | AF46: =AF7/AF44 -> 12.539015 | AG46: =AG7/AG44 -> 12.495132 | AH46: =AH7/AH44 -> 12.977904 | AI46: =AI7/AI44 -> 13.35892 | AJ46: =AJ7/AJ44 -> 13.840298 | AK46: =AK7/AK44 -> 14.117104 | AL46: =AL7/AL44 -> 14.399446 | ... BG46: =BG7/BG44 -> 21.824756
A47: Общие | D47: ЦМИ | F47: Курс рупии к доллару (средний за период) | G47: USD/INR | W47: 61.02 | X47: 64.1 | Y47: 67.17 | Z47: 65.11 | AA47: 68.4 | AB47: 70.4 | AC47: 74.1 | AD47: 73.9 | AE47: 78.6 | AF47: 82.6 | AG47: 84 | AH47: 85.3 | AI47: 86.6 | AJ47: =AI47*(1+2%) -> 88.332 | AK47: =AJ47*(1+2%) -> 90.09864 | AL47: =AK47*(1+2%) -> 91.900613 | AM47: =AL47*(1+2%) -> 93.738625 | AN47: =AM47*(1+2%) -> 95.613398 | AO47: =AN47*(1+2%) -> 97.525666 | AP47: =AO47*(1+2%) -> 99.476179 | AQ47: =AP47*(1+2%) -> 101.4657 | ... BG47: =BF47*(1+2%) -> 139.29067
A48: Общие | D48: ЦМИ | F48: Курс рупии к доллару (на конец периода) | G48: USD/INR | W48: 63.035 | X48: 66.208 | Y48: 67.955 | Z48: 63.84 | AA48: 69.57 | AB48: 71.355 | AC48: 73.054 | AD48: 74.486 | AE48: 82.745 | AF48: =AF47 -> 82.6 | AG48: =AG47 -> 84 | AH48: =AH47 -> 85.3 | AI48: =AI47 -> 86.6 | AJ48: =AJ47 -> 88.332 | AK48: =AK47 -> 90.09864 | AL48: =AL47 -> 91.900613 | AM48: =AM47 -> 93.738625 | ... BG48: =BG47 -> 139.29067
A49: Общие | D49: ЦМИ | F49: Ставка Roisfix 3M | G49: % | W49: 0.2105 | X49: 0.1098 | Y49: 0.1005 | Z49: 0.0754 | AA49: 0.0777 | AB49: 0.0612 | AC49: 0.0422 | AD49: 0.0869 | AE49: 0.0762 | AF49: 0.1405 | AG49: 0.108 | AH49: 0.079 | AI49: 0.0605 | AJ49: =AI49+(AJ$39-AI$39) -> 0.0605 | AK49: =AJ49+(AK$39-AJ$39) -> 0.0605 | AL49: =AK49+(AL$39-AK$39) -> 0.0605 | AM49: =AL49+(AM$39-AL$39) -> 0.0605 | AN49: =AM49+(AN$39-AM$39) -> 0.0605 | AO49: =AN49+(AO$39-AN$39) -> 0.0605 | AP49: =AO49+(AP$39-AO$39) -> 0.0605 | AQ49: =AP49+(AQ$39-AP$39) -> 0.0605 | ... BG49: =BF49+(BG$39-BF$39) -> 0.0605
Z54: =SUMIF(Inputs!$X$1:$AY$1,CL$1031-1,Inputs!$X58:$AY58)+0.25*(SUMIF(Inputs!$X$1:$AY$1,CL$1031,Inputs!$X58:$AY58)-SUMIF(Inputs!$X$1:$AY$1,CL$1031-1,Inputs!$X58:$AY58)) -> 0
A58: Отраслевые | B58: Уголь | D58: Аналитический Хаб | F58: Hard Coking Coal (FOB Australia) | G58: $/т | U58: 192 | V58: 149 | W58: 117 | X58: 90 | Y58: 143.2 | Z58: 187 | AA58: 207 | AB58: 177 | AC58: 125 | AD58: 225 | AE58: 364.531 | AF58: 274.55401 | AG58: 240 | AH58: 200 | AI58: 195 | AJ58: 197.73 | AK58: 200.49822 | AL58: 203.3052 | AM58: 206.15147 | AN58: 209.03759 | AO58: 211.96411 | AP58: 214.93161 | AQ58: 217.94065 | AR58: 220.99182 | AS58: 224.08571 | AT58: 227.22291 | AU58: 230.40403 | AV58: 233.62969 | AW58: 236.9005 | AX58: 240.21711 | AY58: 243.58015 | AZ58: 246.99027 | BA58: 250.44813 | BB58: 253.95441 | BC58: 257.50977 | BD58: 261.11491 | BE58: 264.77052 | BF58: 268.4773 | BG58: 272.23599
A59: Отраслевые | B59: Уголь | D59: Аналитический Хаб | F59: Антрацит | G59: $/т | U59: 169 | V59: 132 | W59: 108 | X59: 100 | Y59: 92 | Z59: 116 | AA59: 133.77083 | AB59: 140.02083 | AC59: 114.625 | AD59: 129.80501 | AE59: 136.34877 | AF59: 125.19968 | AG59: 121.66929 | AH59: 122.37388 | AI59: 124.76527 | AJ59: 127.1262 | AK59: 129.5249 | AL59: 131.96198 | AM59: 134.43805 | AN59: 136.63928 | AO59: 138.87132 | AP59: 141.13462 | AQ59: 143.4296 | AR59: 145.75671 | AS59: 148.1164 | AT59: 150.50912 | AU59: 152.93535 | AV59: 155.39554 | AW59: 157.89017 | AX59: 160.41973 | AY59: 162.9847 | AZ59: 165.58558 | BA59: 168.22288 | BB59: 170.89709 | BC59: 173.60875 | BD59: 176.35836 | BE59: 179.14648 | BF59: 181.97362 | BG59: 184.84035
A60: Отраслевые | B60: Уголь | D60: Аналитический Хаб | F60: Энергетический уголь (CIF ARA) | G60: $/т | U60: 93 | V60: 82 | W60: 76 | X60: 56.7 | Y60: 59.41 | Z60: 84.29 | AA60: 91.98 | AB60: 61.440873 | AC60: 50.453162 | AD60: 120.05 | AE60: 290.03916 | AF60: 128.97193 | AG60: 120 | AH60: 108 | AI60: 108 | AJ60: 109.728 | AK60: 111.48365 | AL60: 113.26739 | AM60: 115.07966 | AN60: 116.46062 | AO60: 117.85815 | AP60: 119.27245 | AQ60: 120.70372 | AR60: 122.15216 | AS60: 123.61799 | AT60: 125.1014 | AU60: 126.60262 | AV60: 128.12185 | AW60: 129.65931 | AX60: 131.21522 | AY60: 132.78981 | AZ60: 134.38328 | BA60: 135.99588 | BB60: 137.62783 | BC60: 139.27937 | BD60: 140.95072 | BE60: 142.64213 | BF60: 144.35383 | BG60: 146.08608
A61: Отраслевые | B61: Уголь | D61: Аналитический Хаб | F61: Thermal Coal (FOB Newcastle) | G61: $/т | U61: 95 | V61: 84 | W61: 71 | X61: 57.73 | Y61: 65.42 | Z61: 87.53 | AA61: 105.78 | AB61: 78.498654 | AC61: 61.196552 | AD61: 132.98159 | AE61: 344.61073 | AF61: 179.63327 | AG61: 160 | AH61: 140 | AI61: 130 | AJ61: 132.08 | AK61: 134.19328 | AL61: 136.34037 | AM61: 138.52182 | AN61: 140.18408 | AO61: 141.86629 | AP61: 143.56868 | AQ61: 145.29151 | AR61: 147.03501 | AS61: 148.79943 | AT61: 150.58502 | AU61: 152.39204 | AV61: 154.22074 | AW61: 156.07139 | AX61: 157.94425 | AY61: 159.83958 | AZ61: 161.75766 | BA61: 163.69875 | BB61: 165.66313 | BC61: 167.65109 | BD61: 169.6629 | BE61: 171.69886 | BF61: 173.75925 | BG61: 175.84436
A63: Отраслевые | B63: Металлы | C63: Цветная металлургия | D63: Аналитический Хаб | F63: Алюминий (London Metals Exchange, без премии) | G63: $/т | U63: 2052 | V63: 1888 | W63: 1895 | X63: 1681 | Y63: 1611 | Z63: 2111 | AA63: 2114 | AB63: 1794 | AC63: 1706 | AD63: 2477 | AE63: 2701 | AF63: 2252.6109 | AG63: 2360 | AH63: 2550 | AI63: 2693.6547 | AJ63: 2736.7531 | AK63: 2780.5412 | AL63: 2825.0299 | AM63: 2870.2303 | AN63: 2904.6731 | AO63: 2939.5292 | AP63: 2974.8035 | AQ63: 3010.5012 | AR63: 3046.6272 | AS63: 3083.1867 | AT63: 3120.1849 | AU63: 3157.6272 | AV63: 3195.5187 | AW63: 3233.8649 | AX63: 3272.6713 | AY63: 3311.9433 | AZ63: 3351.6867 | BA63: 3391.9069 | BB63: 3432.6098 | BC63: 3473.8011 | BD63: 3515.4867 | BE63: 3557.6726 | BF63: 3600.3646 | BG63: 3643.569
A64: Отраслевые | B64: Металлы | C64: Черная металлургия | D64: Аналитический Хаб | F64: Арматура (Rebar, EXW Russia) | G64: $/т | U64: 634 | V64: 543 | W64: 489 | X64: 332.18516 | Y64: 363.50508 | Z64: 451.97062 | AA64: 501.82639 | AB64: 493.82921 | AC64: 423.67847 | AD64: 718.47756 | AE64: 644.36337 | AF64: 525.88468 | AG64: 533.77865 | AH64: 534.04642 | AI64: 538.27766 | AJ64: 536.12777 | AK64: 544.09394 | AL64: 552.17787 | AM64: 560.38133 | AN64: 568.70608 | AO64: 577.15393 | AP64: 585.72671 | AQ64: 594.42626 | AR64: 603.25448 | AS64: 612.21328 | AT64: 621.30459 | AU64: 630.53038 | AV64: 639.89265 | AW64: 649.39344 | AX64: 659.03479 | AY64: 668.8188 | AZ64: 678.74758 | BA64: 688.8233 | BB64: 699.04812 | BC64: 709.42427 | BD64: 719.954 | BE64: 730.6396 | BF64: 741.48337 | BG64: 752.48767
A65: Отраслевые | B65: Металлы | C65: Черная металлургия | D65: Аналитический Хаб | F65: Арматура (Rebar, FOB Black Sea) | G65: $/т | U65: 619 | V65: 586 | W65: 527 | X65: 361.41667 | Y65: 372.83333 | Z65: 465.5 | AA65: 530.41667 | AB65: 449 | AC65: 445.08333 | AD65: 705.41667 | AE65: 642.41667 | AF65: 536.91667 | AG65: 543.77865 | AH65: 539.04642 | AI65: 543.27766 | AJ65: 541.12777 | AK65: 549.09394 | AL65: 557.17787 | AM65: 565.38133 | AN65: 573.70608 | AO65: 582.15393 | AP65: 590.72671 | AQ65: 599.42626 | AR65: 608.25448 | AS65: 617.21328 | AT65: 626.30459 | AU65: 635.53038 | AV65: 644.89265 | AW65: 654.39344 | AX65: 664.03479 | AY65: 673.8188 | AZ65: 683.74758 | BA65: 693.8233 | BB65: 704.04812 | BC65: 714.42427 | BD65: 724.954 | BE65: 735.6396 | BF65: 746.48337 | BG65: 757.48767
A66: Отраслевые | B66: Металлы | C66: Трубы | D66: Аналитический Хаб | F66: Бесшовные трубы (EXW Russia) | G66: $/т | I66: Нет исторических данных с 2018 года | U66: 1288.8095 | V66: 1218.3526 | W66: 1040.3368 | X66: 1078 | Y66: 970 | Z66: 1152 | AA66: 1294 | AB66: 1300 | AC66: 1166 | AD66: 1149 | AE66: 1241.1373 | AF66: 1182.7747 | AG66: 1137.0669 | AH66: 1128.9184 | AI66: 1133.3055 | AJ66: 1133.5708 | AK66: 1140.3024 | AL66: 1167.1125 | AM66: 1174.0022 | AN66: 1180.9728 | AO66: 1188.0253 | AP66: 1195.1609 | AQ66: 1202.3809 | AR66: 1209.6863 | AS66: 1217.0785 | AT66: 1224.5588 | AU66: 1232.1282 | AV66: 1239.7883 | AW66: 1247.5402 | AX66: 1255.3852 | AY66: 1263.3248 | AZ66: 1271.3602 | BA66: 1279.4929 | BB66: 1287.7243 | BC66: 1296.0557 | BD66: 1304.4886 | BE66: 1313.0246 | BF66: 1321.665 | BG66: 1330.4114
A67: Отраслевые | B67: Металлы | C67: Черная металлургия | D67: Аналитический Хаб | F67: Горячебрикетированное железо (HBI, EXW Russia) | G67: $/т | I67: Нет исторических данных с 2018 года | U67: 395 | V67: 369 | W67: 370 | X67: 262 | Y67: 216.90683 | Z67: 219.89667 | AA67: 272.25248 | AB67: 242 | AC67: 217 | AD67: 414 | AE67: 326 | AF67: 246.36337 | AG67: 244.49895 | AH67: 249.18788 | AI67: 251.66233 | AJ67: 250.40405 | AK67: 255.06332 | AL67: 259.79147 | AM67: 264.58954 | AN67: 269.4589 | AO67: 274.40027 | AP67: 279.41471 | AQ67: 284.50332 | AR67: 289.66719 | AS67: 294.90744 | AT67: 300.2252 | AU67: 305.62163 | AV67: 311.0979 | AW67: 316.65519 | AX67: 322.29471 | AY67: 328.01767 | AZ67: 333.82532 | BA67: 339.71892 | BB67: 345.69974 | BC67: 351.76945 | BD67: 357.929 | BE67: 364.17972 | BF67: 370.52297 | BG67: 376.96013
A68: Отраслевые | B68: Металлы | C68: Черная металлургия | D68: Аналитический Хаб | F68: Горячебрикетированное железо (HBI, FOB Black Sea) | G68: $/т | I68: Нет исторических данных с 2018 года | U68: 371 | V68: 350 | W68: 363 | X68: 257 | Y68: 236 | Z68: 240 | AA68: 297 | AB68: 262 | AC68: 256 | AD68: 435 | AE68: 363 | AF68: 281.16667 | AG68: 288.8698 | AH68: 291.08613 | AI68: 293.57509 | AJ68: 292.31045 | AK68: 296.99643 | AL68: 301.75169 | AM68: 306.57725 | AN68: 311.47417 | AO68: 316.44349 | AP68: 321.4863 | AQ68: 326.60368 | AR68: 331.79675 | AS68: 337.06663 | AT68: 342.41446 | AU68: 347.8414 | AV68: 353.34862 | AW68: 358.93732 | AX68: 364.6087 | AY68: 370.364 | AZ68: 376.20446 | BA68: 382.13135 | BB68: 388.14595 | BC68: 394.24957 | BD68: 400.44353 | BE68: 406.72917 | BF68: 413.10786 | BG68: 419.58098
A69: Отраслевые | B69: Металлы | C69: Черная металлургия | D69: Аналитический Хаб | F69: Горячекатанный прокат (HRC, EXW Russia) | G69: $/т | U69: 561 | V69: 509 | W69: 477 | X69: 0 | Y69: 424 | Z69: 534 | AA69: 549.21676 | AB69: 527 | AC69: 478 | AD69: 895 | AE69: 787.25497 | AF69: 658.9854 | AG69: 664.48629 | AH69: 657.02548 | AI69: 673.38324 | AJ69: 682.477 | AK69: 692.32905 | AL69: 702.32379 | AM69: 712.46329 | AN69: 722.74965 | AO69: 733.18501 | AP69: 743.77154 | AQ69: 754.51143 | AR69: 765.40691 | AS69: 776.46025 | AT69: 787.67373 | AU69: 799.04969 | AV69: 810.59049 | AW69: 822.29853 | AX69: 834.17624 | AY69: 846.22608 | AZ69: 858.45057 | BA69: 870.85223 | BB69: 883.43365 | BC69: 896.19744 | BD69: 909.14626 | BE69: 922.28279 | BF69: 935.60977 | BG69: 949.12997
A70: Отраслевые | B70: Металлы | C70: Черная металлургия | D70: Аналитический Хаб | F70: Горячекатанный прокат (HRC, FOB Black Sea) | G70: $/т | U70: 581 | V70: 543 | W70: 522 | X70: 349.83333 | Y70: 388.83333 | Z70: 503.75 | AA70: 555.16667 | AB70: 464 | AC70: 471 | AD70: 860 | AE70: 705.91667 | AF70: 584.08333 | AG70: 611.61688 | AH70: 607.01519 | AI70: 606.38073 | AJ70: 604.73215 | AK70: 614.10954 | AL70: 623.63279 | AM70: 633.30418 | AN70: 663.12601 | AO70: 673.10064 | AP70: 683.23045 | AQ70: 693.51786 | AR70: 703.96533 | AS70: 714.57536 | AT70: 725.35048 | AU70: 736.29326 | AV70: 747.40633 | AW70: 758.69235 | AX70: 770.154 | AY70: 781.79404 | AZ70: 793.61524 | BA70: 805.62044 | BB70: 817.81251 | BC70: 830.19435 | BD70: 842.76895 | BE70: 855.53929 | BF70: 868.50845 | BG70: 881.67952
A71: Отраслевые | B71: Металлы | C71: Черная металлургия | D71: Аналитический Хаб | F71: Горячеоцинкованный прокат (HDG, EXW Russia) | G71: $/т | U71: 957 | V71: 815 | W71: 716 | X71: 562 | Y71: 647 | Z71: 700 | AA71: 769 | AB71: 732 | AC71: 714 | AD71: 1161 | AE71: 999.39554 | AF71: 824.13169 | AG71: 874.01286 | AH71: 870.00368 | AI71: 889.86992 | AJ71: 902.42747 | AK71: 915.79873 | AL71: 929.36898 | AM71: 943.1412 | AN71: 957.11841 | AO71: 971.30367 | AP71: 985.7001 | AQ71: 1000.3108 | AR71: 1015.1391 | AS71: 1030.1882 | AT71: 1045.4613 | AU71: 1060.9619 | AV71: 1076.6933 | AW71: 1092.6589 | AX71: 1108.8624 | AY71: 1125.3072 | AZ71: 1141.997 | BA71: 1158.9354 | BB71: 1176.1262 | BC71: 1193.5731 | BD71: 1211.2799 | BE71: 1229.2505 | BF71: 1247.489 | BG71: 1265.9993
A72: Отраслевые | B72: Металлы | C72: Черная металлургия | D72: Аналитический Хаб | F72: Горячеоцинкованный прокат (HDG, FOB Black Sea) | G72: $/т | U72: 737.64408 | V72: 692.30197 | W72: 649.52198 | X72: 613 | Y72: 657 | Z72: 735 | AA72: 760.125 | AB72: 647 | AC72: 663 | AD72: 1164 | AE72: 1023.3417 | AF72: 816.80216 | AG72: 878.63107 | AH72: 870.96791 | AI72: 907.0184 | AJ72: 929.52063 | AK72: 942.55612 | AL72: 955.77447 | AM72: 969.17823 | AN72: 962.77002 | AO72: 976.55246 | AP72: 990.52823 | AQ72: 1004.7 | AR72: 1019.0707 | AS72: 1033.6429 | AT72: 1048.4195 | AU72: 1063.4034 | AV72: 1078.5975 | AW72: 1094.0047 | AX72: 1109.6281 | AY72: 1125.4706 | AZ72: 1141.5353 | BA72: 1157.8255 | BB72: 1174.3441 | BC72: 1191.0945 | BD72: 1208.0798 | BE72: 1225.3034 | BF72: 1242.7687 | BG72: 1260.4789
A73: Отраслевые | B73: Металлы | C73: Черная металлургия | D73: Аналитический Хаб | F73: Железная руда (Iron Ore 62%, CFR China) | G73: $/т | U73: 129 | V73: 136 | W73: 97 | X73: 55 | Y73: 58 | Z73: 71 | AA73: 68.93 | AB73: 93 | AC73: 108 | AD73: 159 | AE73: 120.9078 | AF73: 115.66547 | AG73: 110 | AH73: 105 | AI73: 106.72971 | AJ73: 108.43739 | AK73: 110.17239 | AL73: 111.93515 | AM73: 113.72611 | AN73: 115.54573 | AO73: 117.39446 | AP73: 119.27277 | AQ73: 121.18113 | AR73: 123.12003 | AS73: 125.08995 | AT73: 127.09139 | AU73: 129.12485 | AV73: 131.19085 | AW73: 133.2899 | AX73: 135.42254 | AY73: 137.5893 | AZ73: 139.79073 | BA73: 142.02738 | BB73: 144.29982 | BC73: 146.60862 | BD73: 148.95436 | BE73: 151.33763 | BF73: 153.75903 | BG73: 156.21917
A74: Отраслевые | B74: Металлы | C74: Черная металлургия | D74: Аналитический Хаб | F74: Заготовка квадратная (Billet, EXW Russia) | G74: $/т | U74: 574.97962 | V74: 467.93015 | W74: 445.59877 | X74: 300.76849 | Y74: 274.67175 | Z74: 452.47062 | AA74: 460.30973 | AB74: 413 | AC74: 367 | AD74: 623 | AE74: 599.49572 | AF74: 499.05135 | AG74: 501.07431 | AH74: 494.18602 | AI74: 496.72866 | AJ74: 503.27629 | AK74: 510.81697 | AL74: 518.47003 | AM74: 526.23713 | AN74: 534.11999 | AO74: 542.12034 | AP74: 550.23993 | AQ74: 558.48056 | AR74: 566.84403 | AS74: 575.33219 | AT74: 583.9469 | AU74: 592.69005 | AV74: 601.56358 | AW74: 610.56943 | AX74: 619.70958 | AY74: 628.98605 | AZ74: 638.40089 | BA74: 647.95615 | BB74: 657.65395 | BC74: 667.49642 | BD74: 677.48573 | BE74: 687.62408 | BF74: 697.91371 | BG74: 708.35687
A75: Отраслевые | B75: Металлы | C75: Черная металлургия | D75: Аналитический Хаб | F75: Заготовка квадратная (Billet, FOB Black Sea) | G75: $/т | U75: 560 | V75: 511 | W75: 483 | X75: 330 | Y75: 284 | Z75: 466 | AA75: 488.9 | AB75: 411.13208 | AC75: 402.59804 | AD75: 615.18868 | AE75: 597.54902 | AF75: 510.08333 | AG75: 506.07431 | AH75: 499.18602 | AI75: 501.72866 | AJ75: 508.27629 | AK75: 515.81697 | AL75: 523.47003 | AM75: 531.23713 | AN75: 539.11999 | AO75: 547.12034 | AP75: 555.23993 | AQ75: 563.48056 | AR75: 571.84403 | AS75: 580.33219 | AT75: 588.9469 | AU75: 597.69005 | AV75: 606.56358 | AW75: 615.56943 | AX75: 624.70958 | AY75: 633.98605 | AZ75: 643.40089 | BA75: 652.95615 | BB75: 662.65395 | BC75: 672.49642 | BD75: 682.48573 | BE75: 692.62408 | BF75: 702.91371 | BG75: 713.35687
A76: Отраслевые | B76: Металлы | C76: Черная металлургия | D76: Аналитический Хаб | F76: Заготовка плоская (Slab, EXW Russia) | G76: $/т | I76: Нет исторических данных с 2018 года | U76: 529.97962 | V76: 439.93015 | W76: 451.59877 | X76: 477.07302 | Y76: 451.9448 | Z76: 586.35766 | AA76: 677.09416 | AB76: 471 | AC76: 421 | AD76: 779 | AE76: 590.90164 | AF76: 525.33333 | AG76: 561.52337 | AH76: 540.43848 | AI76: 523.29641 | AJ76: 520.15939 | AK76: 528.02453 | AL76: 536.01135 | AM76: 544.12173 | AN76: 552.3576 | AO76: 560.72089 | AP76: 569.21359 | AQ76: 577.83771 | AR76: 586.59528 | AS76: 595.48838 | AT76: 604.51911 | AU76: 613.68961 | AV76: 623.00205 | AW76: 632.45863 | AX76: 642.06159 | AY76: 651.8132 | AZ76: 661.71578 | BA76: 671.77167 | BB76: 681.98324 | BC76: 692.29496 | BD76: 702.76631 | BE76: 713.39976 | BF76: 724.19783 | BG76: 735.16308
A77: Отраслевые | B77: Металлы | C77: Черная металлургия | D77: Аналитический Хаб | F77: Заготовка плоская, (Slab, FOB Black Sea) | G77: $/т | U77: 515 | V77: 483 | W77: 489 | X77: 295.75 | Y77: 330 | Z77: 440.5 | AA77: 507.16667 | AB77: 409 | AC77: 414 | AD77: 749 | AE77: 560.90164 | AF77: 495.33333 | AG77: 531.52337 | AH77: 520.43848 | AI77: 513.29641 | AJ77: 520.15939 | AK77: 528.02453 | AL77: 536.01135 | AM77: 544.12173 | AN77: 552.3576 | AO77: 560.72089 | AP77: 569.21359 | AQ77: 577.83771 | AR77: 586.59528 | AS77: 595.48838 | AT77: 604.51911 | AU77: 613.68961 | AV77: 623.00205 | AW77: 632.45863 | AX77: 642.06159 | AY77: 651.8132 | AZ77: 661.71578 | BA77: 671.77167 | BB77: 681.98324 | BC77: 692.29496 | BD77: 702.76631 | BE77: 713.39976 | BF77: 724.19783 | BG77: 735.16308
A78: Отраслевые | B78: Металлы | C78: Цветная металлургия | D78: Аналитический Хаб | F78: Золото (London Metals Exchange) | G78: $/унция | U78: 1669 | V78: 1412 | W78: 1266 | X78: 1160 | Y78: 1249 | Z78: 1258.75 | AA78: 1269.21 | AB78: 1393 | AC78: 1772 | AD78: 1799 | AE78: 1802 | AF78: 1933.5741 | AG78: 1900 | AH78: 1820 | AI78: 1750 | AJ78: 1750 | AK78: 1771 | AL78: 1792.252 | AM78: 1813.759 | AN78: 1821.0141 | AO78: 1828.2981 | AP78: 1835.6113 | AQ78: 1842.9538 | AR78: 1850.3256 | AS78: 1857.7269 | AT78: 1865.1578 | AU78: 1872.6184 | AV78: 1880.1089 | AW78: 1887.6293 | AX78: 1895.1798 | AY78: 1902.7606 | AZ78: 1910.3716 | BA78: 1918.0131 | BB78: 1925.6851 | BC78: 1933.3879 | BD78: 1941.1214 | BE78: 1948.8859 | BF78: 1956.6815 | BG78: 1964.5082
A79: Отраслевые | B79: Металлы | C79: Цветная металлургия | D79: Аналитический Хаб | F79: Медь (London Metals Exchange) | G79: $/т | U79: 7953 | V79: 7349 | W79: 6827 | X79: 5493 | Y79: 4871 | Z79: 6173 | AA79: 6544 | AB79: 6005 | AC79: 6186 | AD79: 9320 | AE79: 8805 | AF79: 8650 | AG79: 8450 | AH79: 8600 | AI79: 8700 | AJ79: 8800 | AK79: 8940.8 | AL79: 9083.8528 | AM79: 9229.1944 | AN79: 9321.4864 | AO79: 9414.7013 | AP79: 9508.8483 | AQ79: 9603.9367 | AR79: 9699.9761 | AS79: 9796.9759 | AT79: 9894.9456 | AU79: 9993.8951 | AV79: 10093.834 | AW79: 10194.772 | AX79: 10296.72 | AY79: 10399.687 | AZ79: 10503.684 | BA79: 10608.721 | BB79: 10714.808 | BC79: 10821.956 | BD79: 10930.176 | BE79: 11039.478 | BF79: 11149.872 | BG79: 11261.371
A80: Отраслевые | B80: Металлы | C80: Черная металлургия | D80: Аналитический Хаб | F80: Металлолом (Scrap, EXW Russia ) | G80: $/т | U80: 318 | V80: 296 | W80: 273 | X80: 179.99403 | Y80: 176.84501 | Z80: 250.79558 | AA80: 279.41005 | AB80: 254.41696 | AC80: 236.8984 | AD80: 373.06568 | AE80: 373.06568 | AF80: 322.51604 | AG80: 296.5437 | AH80: 296.69246 | AI80: 299.04314 | AJ80: 297.84876 | AK80: 302.27441 | AL80: 306.76548 | AM80: 311.32296 | AN80: 315.94782 | AO80: 320.64107 | AP80: 325.40373 | AQ80: 330.23681 | AR80: 335.14138 | AS80: 340.11849 | AT80: 345.16921 | AU80: 350.29466 | AV80: 355.49592 | AW80: 360.77413 | AX80: 366.13044 | AY80: 371.566 | AZ80: 377.08199 | BA80: 382.67961 | BB80: 388.36007 | BC80: 394.1246 | BD80: 399.97445 | BE80: 405.91089 | BF80: 411.9352 | BG80: 418.0487
A81: Отраслевые | B81: Металлы | C81: Черная металлургия | D81: Аналитический Хаб | F81: Металлолом (Scrap, FOB Black sea) | G81: $/т | X81: 210.33333 | Y81: 204.33333 | Z81: 268.91667 | AA81: 301.5 | AB81: 255 | AC81: 262 | AD81: 421 | AE81: 387.08333 | AF81: 327.16667 | AG81: 319.8698 | AH81: 317.08613 | AI81: 319.57509 | AJ81: 318.31045 | AK81: 322.99643 | AL81: 327.75169 | AM81: 332.57725 | AN81: 337.47417 | AO81: 342.44349 | AP81: 347.4863 | AQ81: 352.60368 | AR81: 357.79675 | AS81: 363.06663 | AT81: 368.41446 | AU81: 373.8414 | AV81: 379.34862 | AW81: 384.93732 | AX81: 390.6087 | AY81: 396.364 | AZ81: 402.20446 | BA81: 408.13135 | BB81: 414.14595 | BC81: 420.24957 | BD81: 426.44353 | BE81: 432.72917 | BF81: 439.10786 | BG81: 445.58098
A82: Отраслевые | B82: Металлы | C82: Цветная металлургия | D82: Аналитический Хаб | F82: Никель (London Metals Exchange) | G82: $/т | U82: 17519 | V82: 15089 | W82: 16960 | X82: 11877 | Y82: 9645 | Z82: 10471 | AA82: 13186 | AB82: 13944 | AC82: 13803 | AD82: 18474 | AE82: 25623 | AF82: 22369.225 | AG82: 19700 | AH82: 19800 | AI82: 20000 | AJ82: 20320 | AK82: 20645.12 | AL82: 20975.442 | AM82: 21311.049 | AN82: 21609.404 | AO82: 21911.935 | AP82: 22218.702 | AQ82: 22529.764 | AR82: 22845.181 | AS82: 23165.013 | AT82: 23489.324 | AU82: 23818.174 | AV82: 24151.629 | AW82: 24489.751 | AX82: 24832.608 | AY82: 25180.264 | AZ82: 25532.788 | BA82: 25890.247 | BB82: 26252.711 | BC82: 26620.249 | BD82: 26992.932 | BE82: 27370.833 | BF82: 27754.025 | BG82: 28142.581
A83: Отраслевые | B83: Металлы | C83: Черная металлургия | D83: Аналитический Хаб | F83: Окатыш (Pellet, EXW Russia) | G83: $/т | I83: Нет исторических данных с 2018 года | U83: 113 | V83: 102 | W83: 73 | X83: 51.84683 | Y83: 48.906834 | Z83: 75.438338 | AA83: 81.127479 | AB83: 105 | AC83: 87 | AD83: 157 | AE83: 107.25226 | AF83: 87.982582 | AG83: 94.721316 | AH83: 99.349259 | AI83: 100.56771 | AJ83: 101.76089 | AK83: 102.96362 | AL83: 104.17597 | AM83: 105.39801 | AN83: 106.63059 | AO83: 107.87303 | AP83: 109.12542 | AQ83: 110.38782 | AR83: 111.66033 | AS83: 112.94302 | AT83: 114.23598 | AU83: 115.53928 | AV83: 116.85301 | AW83: 118.17726 | AX83: 119.5121 | AY83: 120.85762 | AZ83: 122.21391 | BA83: 123.58106 | BB83: 124.95914 | BC83: 126.34906 | BD83: 127.75009 | BE83: 129.16233 | BF83: 130.58587 | BG83: 132.0208
A84: Отраслевые | B84: Металлы | C84: Черная металлургия | D84: Аналитический Хаб | F84: Окатыш (Pellet, FOB Black Sea) | G84: $/т | I84: Нет исторических данных с 2018 года | U84: 112 | V84: 107 | W84: 101 | X84: 66.916667 | Y84: 68 | Z84: 95.541667 | AA84: 105.875 | AB84: 125 | AC84: 126 | AD84: 178 | AE84: 159.00162 | AF84: 132.41595 | AG84: 137.15468 | AH84: 138.80557 | AI84: 140.02478 | AJ84: 141.21871 | AK84: 142.42219 | AL84: 143.63529 | AM84: 144.8581 | AN84: 146.09107 | AO84: 147.33389 | AP84: 148.58666 | AQ84: 149.84946 | AR84: 151.12236 | AS84: 152.40544 | AT84: 153.69879 | AU84: 155.00249 | AV84: 156.31662 | AW84: 157.64126 | AX84: 158.9765 | AY84: 160.32243 | AZ84: 161.67913 | BA84: 163.04667 | BB84: 164.42517 | BC84: 165.81508 | BD84: 167.21611 | BE84: 168.62835 | BF84: 170.05189 | BG84: 171.48682
A85: Отраслевые | B85: Металлы | C85: Цветная металлургия | D85: Аналитический Хаб | F85: Свинец (London Metals Exchange) | G85: $/т | U85: 2074 | V85: 2155 | W85: 2112 | X85: 1794 | Y85: 1875 | Z85: 2250 | AA85: 2248 | AB85: 1999 | AC85: 1826 | AD85: 2202 | AE85: 2147 | AF85: 2151.1358 | AG85: 2100 | AH85: 2100 | AI85: 2134.5943 | AJ85: 2168.7478 | AK85: 2203.4477 | AL85: 2238.7029 | AM85: 2274.5221 | AN85: 2274.5221 | AO85: 2274.5221 | AP85: 2274.5221 | AQ85: 2274.5221 | AR85: 2274.5221 | AS85: 2274.5221 | AT85: 2274.5221 | AU85: 2274.5221 | AV85: 2274.5221 | AW85: 2274.5221 | AX85: 2274.5221 | AY85: 2274.5221 | AZ85: 2274.5221 | BA85: 2274.5221 | BB85: 2274.5221 | BC85: 2274.5221 | BD85: 2274.5221 | BE85: 2274.5221 | BF85: 2274.5221 | BG85: 2274.5221
A86: Отраслевые | B86: Металлы | C86: Цветная металлургия | D86: Аналитический Хаб | F86: Серебро (London Metals Exchange) | G86: $/унция | U86: 31.2 | V86: 23.9 | W86: 19.1 | X86: 15.7 | Y86: 17.1167 | Z86: 17.0742 | AA86: 15.71 | AB86: 16 | AC86: 21 | AD86: 25 | AE86: 22 | AF86: 23.551875 | AG86: 23.7 | AH86: 23.5 | AI86: 23.3 | AJ86: 23.6262 | AK86: 23.956967 | AL86: 24.292364 | AM86: 24.632457 | AN86: 24.878782 | AO86: 25.12757 | AP86: 25.378846 | AQ86: 25.632634 | AR86: 25.88896 | AS86: 26.14785 | AT86: 26.409328 | AU86: 26.673422 | AV86: 26.940156 | AW86: 27.209557 | AX86: 27.481653 | AY86: 27.75647 | AZ86: 28.034034 | BA86: 28.314375 | BB86: 28.597518 | BC86: 28.883494 | BD86: 29.172328 | BE86: 29.464052 | BF86: 29.758692 | BG86: 30.056279
A87: Отраслевые | B87: Металлы | C87: Трубы | D87: Аналитический Хаб | F87: Трубы большого диаметра (LDP, EXW Russia) | G87: $/т | I87: Нет исторических данных с 2018 года | U87: 1777.5639 | V87: 1777.5639 | W87: 1813.1152 | X87: 1272 | Y87: 1179 | Z87: 1373 | AA87: 1083 | AB87: 979 | AC87: 840 | AD87: 923 | AE87: 995.50235 | AF87: 971.23676 | AG87: 981.39902 | AH87: 982.44303 | AI87: 992.42564 | AJ87: 997.30383 | AK87: 1006.9532 | AL87: 1016.7178 | AM87: 1026.599 | AN87: 1036.5986 | AO87: 1046.7179 | AP87: 1056.9587 | AQ87: 1067.3225 | AR87: 1077.811 | AS87: 1088.4259 | AT87: 1099.1688 | AU87: 1110.0415 | AV87: 1121.0456 | AW87: 1132.183 | AX87: 1143.4554 | AY87: 1154.8646 | AZ87: 1166.4125 | BA87: 1178.101 | BB87: 1189.9319 | BC87: 1201.9429 | BD87: 1214.1005 | BE87: 1226.4066 | BF87: 1238.8633 | BG87: 1251.4725
A88: Отраслевые | B88: Металлы | C88: Цветная металлургия | D88: Аналитический Хаб | F88: Ферросилико-марганец (Европа) | G88: $/т | X88: 0 | Y88: 845 | Z88: 1217 | AA88: 1179.3309 | AB88: 1069.6653 | AC88: 1014.6449 | AD88: 1704.2318 | AE88: 1615.6637 | AF88: 1173.0888 | AG88: 1173.0888 | AH88: 1173.0888 | AI88: 1185.1669 | AJ88: 1197.0185 | AK88: 1208.9887 | AL88: 1221.0786 | AM88: 1233.2894 | AN88: 1245.6223 | AO88: 1258.0785 | AP88: 1270.6593 | AQ88: 1283.3659 | AR88: 1296.1995 | AS88: 1309.1615 | AT88: 1322.2531 | AU88: 1335.4757 | AV88: 1348.8304 | AW88: 1362.3187 | AX88: 1375.9419 | AY88: 1389.7013 | AZ88: 1403.5984 | BA88: 1417.6343 | BB88: 1431.8107 | BC88: 1446.1288 | BD88: 1460.5901 | BE88: 1475.196 | BF88: 1489.9479 | BG88: 1504.8474
A89: Отраслевые | B89: Металлы | C89: Цветная металлургия | D89: Аналитический Хаб | F89: Ферросилиций (Европа) | G89: $/т | X89: 0 | Y89: 1028 | Z89: 1461 | AA89: 1386.4786 | AB89: 1126.7143 | AC89: 1079.1803 | AD89: 1983.3542 | AE89: 1850.9836 | AF89: 1460.8258 | AG89: 1460.8258 | AH89: 1369.3993 | AI89: 1373.2161 | AJ89: 1386.9482 | AK89: 1400.8177 | AL89: 1414.8259 | AM89: 1428.9741 | AN89: 1443.2639 | AO89: 1457.6965 | AP89: 1472.2735 | AQ89: 1486.9962 | AR89: 1501.8662 | AS89: 1516.8848 | AT89: 1532.0537 | AU89: 1547.3742 | AV89: 1562.848 | AW89: 1578.4765 | AX89: 1594.2612 | AY89: 1610.2038 | AZ89: 1626.3059 | BA89: 1642.5689 | BB89: 1658.9946 | BC89: 1675.5846 | BD89: 1692.3404 | BE89: 1709.2638 | BF89: 1726.3564 | BG89: 1743.62
A90: Отраслевые | B90: Металлы | C90: Цветная металлургия | D90: Аналитический Хаб | F90: Феррохром (High carbon/Europe) | G90: cents/lb | I90: Нет исторических данных с 2018 года | U90: 107.9 | V90: 99.6 | W90: 108.1 | X90: 96.8 | Y90: 103 | Z90: 120 | AA90: 125 | AB90: 87.812245 | AC90: 81.192623 | AD90: 124.6875 | AE90: 190 | AF90: 227.67318 | AG90: 170 | AH90: 150 | AI90: 130 | AJ90: 134.54715 | AK90: 135.92715 | AL90: 137.32371 | AM90: 138.73703 | AN90: 139.56945 | AO90: 140.40687 | AP90: 141.24931 | AQ90: 142.09681 | AR90: 142.94939 | AS90: 143.80708 | AT90: 144.66993 | AU90: 145.53795 | AV90: 146.41117 | AW90: 147.28964 | AX90: 148.17338 | AY90: 149.06242 | AZ90: 149.95679 | BA90: 150.85654 | BB90: 151.76167 | BC90: 152.67224 | BD90: 153.58828 | BE90: 154.50981 | BF90: 155.43687 | BG90: 156.36949
A91: Отраслевые | B91: Металлы | C91: Черная металлургия | D91: Аналитический Хаб | F91: Холоднокатанный прокат (CRC, EXW Russia) | G91: $/т | U91: 679 | V91: 596 | W91: 538 | X91: 459 | Y91: 479 | Z91: 600 | AA91: 623.39734 | AB91: 658.83926 | AC91: 595.70839 | AD91: 1040.4122 | AE91: 855 | AF91: 704.08714 | AG91: 751.99077 | AH91: 745.97146 | AI91: 763.79446 | AJ91: 774.3348 | AK91: 785.65658 | AL91: 797.14456 | AM91: 808.80119 | AN91: 820.62896 | AO91: 832.63039 | AP91: 844.80804 | AQ91: 857.16452 | AR91: 869.70245 | AS91: 882.42451 | AT91: 895.33342 | AU91: 908.43194 | AV91: 921.72286 | AW91: 935.20901 | AX91: 948.89329 | AY91: 962.77861 | AZ91: 976.86793 | BA91: 991.16427 | BB91: 1005.6707 | BC91: 1020.3903 | BD91: 1035.3262 | BE91: 1050.4816 | BF91: 1065.8597 | BG91: 1081.4639
A92: Отраслевые | B92: Металлы | C92: Черная металлургия | D92: Аналитический Хаб | F92: Холоднокатанный прокат (CRC, FOB Black Sea) | G92: $/т | U92: 679 | V92: 622 | W92: 608 | X92: 427.75 | Y92: 442.25 | Z92: 554.08333 | AA92: 616.25 | AB92: 527 | AC92: 499 | AD92: 1001 | AE92: 838.25 | AF92: 711.41667 | AG92: 747.37256 | AH92: 745.00723 | AI92: 746.64598 | AJ92: 747.24164 | AK92: 758.89918 | AL92: 770.73907 | AM92: 782.76416 | AN92: 814.97735 | AO92: 827.38161 | AP92: 839.97991 | AQ92: 852.77531 | AR92: 865.7709 | AS92: 878.96981 | AT92: 892.37524 | AU92: 905.99043 | AV92: 919.81865 | AW92: 933.86326 | AX92: 948.12765 | AY92: 962.61527 | AZ92: 977.32961 | BA92: 992.27424 | BB92: 1007.4528 | BC92: 1022.8689 | BD92: 1038.5262 | BE92: 1054.4287 | BF92: 1070.5801 | BG92: 1086.9843
A93: Отраслевые | B93: Металлы | C93: Цветная металлургия | D93: Аналитический Хаб | F93: Цинк (London Metals Exchange) | G93: $/т | U93: 1965 | V93: 1938 | W93: 2166 | X93: 1939 | Y93: 2101 | Z93: 2893 | AA93: 2892 | AB93: 2548 | AC93: 2269 | AD93: 3005 | AE93: 3475 | AF93: 2672.0724 | AG93: 2700 | AH93: 2800 | AI93: 2900 | AJ93: 2946.4 | AK93: 2993.5424 | AL93: 3041.4391 | AM93: 3090.1021 | AN93: 3121.0031 | AO93: 3152.2132 | AP93: 3183.7353 | AQ93: 3215.5726 | AR93: 3247.7284 | AS93: 3280.2057 | AT93: 3313.0077 | AU93: 3346.1378 | AV93: 3379.5992 | AW93: 3413.3952 | AX93: 3447.5291 | AY93: 3482.0044 | AZ93: 3516.8244 | BA93: 3551.9927 | BB93: 3587.5126 | BC93: 3623.3877 | BD93: 3659.6216 | BE93: 3696.2178 | BF93: 3733.18 | BG93: 3770.5118
A94: Отраслевые | B94: Металлы | C94: Черная металлургия | D94: Аналитический Хаб | F94: Чугун (Pig iron, EXW Russia) | G94: $/т | I94: Нет исторических данных с 2018 года | U94: 430.1757 | V94: 346.64168 | W94: 339.48556 | X94: 230.82832 | Y94: 221.36705 | Z94: 339.73178 | AA94: 349.25364 | AB94: 384 | AC94: 337 | AD94: 508 | AE94: 457.7186 | AF94: 344.881 | AG94: 398.35315 | AH94: 397.02609 | AI94: 399.46612 | AJ94: 384.7041 | AK94: 390.65054 | AL94: 396.6892 | AM94: 402.82151 | AN94: 409.04893 | AO94: 415.37295 | AP94: 421.79505 | AQ94: 428.31678 | AR94: 434.93968 | AS94: 441.66532 | AT94: 448.4953 | AU94: 455.43125 | AV94: 462.47482 | AW94: 469.62767 | AX94: 476.89152 | AY94: 484.26808 | AZ94: 491.75912 | BA94: 499.36642 | BB94: 507.09178 | BC94: 514.93704 | BD94: 522.90407 | BE94: 530.99476 | BF94: 539.21105 | BG94: 547.55488
A95: Отраслевые | B95: Металлы | C95: Черная металлургия | D95: Аналитический Хаб | F95: Чугун (Pig iron, FOB Black Sea) | G95: $/т | U95: 415.19608 | V95: 389.71154 | W95: 376.88679 | X95: 243.75 | Y95: 255.91667 | Z95: 352.66667 | AA95: 378.08333 | AB95: 326 | AC95: 340 | AD95: 550 | AE95: 469 | AF95: 384.83333 | AG95: 408.71273 | AH95: 385.43903 | AI95: 386.07207 | AJ95: 391.05855 | AK95: 397.01716 | AL95: 403.06694 | AM95: 409.20927 | AN95: 415.44559 | AO95: 421.77734 | AP95: 428.20597 | AQ95: 434.73299 | AR95: 441.3599 | AS95: 448.08824 | AT95: 454.91956 | AU95: 461.85546 | AV95: 468.89752 | AW95: 476.04739 | AX95: 483.30673 | AY95: 490.67721 | AZ95: 498.16055 | BA95: 505.75847 | BB95: 513.47274 | BC95: 521.30515 | BD95: 529.25752 | BE95: 537.33168 | BF95: 545.52952 | BG95: 553.85293
A96: Отраслевые | B96: Металлы | C96: Цветная металлургия | D96: Аналитический Хаб | F96: Платина (LME) | G96: $/унция | X96: 1054 | Y96: 989 | Z96: 949.91 | AA96: 879.64 | AB96: 865 | AC96: 886 | AD96: 1092 | AE96: 964 | AF96: 984.40867 | AG96: 1080 | AH96: 1100 | AI96: 1118.1208 | AJ96: 1136.0107 | AK96: 1154.1869 | AL96: 1172.6539 | AM96: 1191.4164 | AN96: 1208.0962 | AO96: 1225.0095 | AP96: 1242.1597 | AQ96: 1259.5499 | AR96: 1277.1836 | AS96: 1295.0642 | AT96: 1313.1951 | AU96: 1331.5798 | AV96: 1350.2219 | AW96: 1369.125 | AX96: 1388.2928 | AY96: 1407.7289 | AZ96: 1427.4371 | BA96: 1447.4212 | BB96: 1467.6851 | BC96: 1488.2327 | BD96: 1509.068 | BE96: 1530.1949 | BF96: 1551.6176 | BG96: 1573.3403
A97: Отраслевые | B97: Металлы | C97: Цветная металлургия | D97: Аналитический Хаб | F97: Палладий (LME) | G97: $/унция | X97: 690 | Y97: 615 | Z97: 870.78 | AA97: 1030.49 | AB97: 1541 | AC97: 2201 | AD97: 2397 | AE97: 2109 | AF97: 1391.1101 | AG97: 1350 | AH97: 1300 | AI97: 1280 | AJ97: 1250 | AK97: 1250 | AL97: 1200 | AM97: 1219.2 | AN97: 1233.8304 | AO97: 1248.6364 | AP97: 1263.62 | AQ97: 1278.7834 | AR97: 1294.1288 | AS97: 1309.6584 | AT97: 1325.3743 | AU97: 1341.2788 | AV97: 1357.3741 | AW97: 1369.125 | AX97: 1385.5545 | AY97: 1402.1812 | AZ97: 1419.0074 | BA97: 1436.0354 | BB97: 1453.2679 | BC97: 1470.7071 | BD97: 1488.3556 | BE97: 1506.2158 | BF97: 1524.2904 | BG97: 1542.5819
A98: Отраслевые | B98: Металлы | C98: Цветная металлургия | D98: Аналитический Хаб | F98: Феррохром (6-8%, 58-60% Cr/China import CIF) | G98: cents/lb | I98: Добавлен 25.01.2019 | U98: 92 | V98: 87.5 | W98: 83 | X98: 76.5 | Y98: 78.5 | Z98: 95.5 | AA98: 86.305623 | AB98: 75.560131 | AC98: 68.197826 | AD98: 110.44018 | AE98: 103.21221 | AF98: 100 | AG98: 100 | AH98: 100 | AI98: 105 | AJ98: 115 | AK98: 116.38 | AL98: 117.77656 | AM98: 119.18988 | AN98: 119.90502 | AO98: 120.62445 | AP98: 121.34819 | AQ98: 122.07628 | AR98: 122.80874 | AS98: 123.54559 | AT98: 124.28687 | AU98: 125.03259 | AV98: 125.78278 | AW98: 126.53748 | AX98: 127.29671 | AY98: 128.06049 | AZ98: 128.82885 | BA98: 129.60182 | BB98: 130.37943 | BC98: 131.16171 | BD98: 131.94868 | BE98: 132.74037 | BF98: 133.53681 | BG98: 134.33804
A99: Отраслевые | B99: Металлы | C99: Черная металлургия | D99: Аналитический Хаб | F99: Сварные трубы (EXW Russia) | G99: $/т | Z99: 564 | AA99: 575.80253 | AB99: 533 | AC99: 476 | AD99: 850 | AE99: 789.64416 | AF99: 692.1895 | AG99: 691.31798 | AH99: 688.99631 | AI99: 699.86122 | AJ99: 705.02834 | AK99: 713.81685 | AL99: 722.72514 | AM99: 731.75491 | AN99: 740.90787 | AO99: 750.18574 | AP99: 759.59029 | AQ99: 769.12331 | AR99: 778.78661 | AS99: 788.58201 | AT99: 798.5114 | AU99: 808.57666 | AV99: 818.7797 | AW99: 829.12248 | AX99: 839.60696 | AY99: 850.23515 | AZ99: 861.00908 | BA99: 871.93081 | BB99: 883.00243 | BC99: 894.31551 | BD99: 905.78347 | BE99: 917.4085 | BF99: 929.19281 | BG99: 941.13867
A100: Отраслевые | B100: Металлы | C100: Черная металлургия | D100: Аналитический Хаб | F100: Кобальт | G100: $/фунт | X100: 13.52102 | Y100: 12.0596 | Z100: 26.931723 | AA100: 37.048163 | AB100: 16.5 | AC100: 15.4 | AD100: 23.7 | AE100: 30.5 | AF100: 15.890508 | AG100: 16.2 | AH100: 18.5 | AI100: 20 | AJ100: 20.32 | AK100: 20.64512 | AL100: 20.975442 | AM100: 21.311049 | AN100: 21.524159 | AO100: 21.739401 | AP100: 21.956795 | AQ100: 22.176363 | AR100: 22.398127 | AS100: 22.622108 | AT100: 22.848329 | AU100: 23.076812 | AV100: 23.30758 | AW100: 23.540656 | AX100: 23.776063 | AY100: 24.013823 | AZ100: 24.253962 | BA100: 24.496501 | BB100: 24.741466 | BC100: 24.988881 | BD100: 25.23877 | BE100: 25.491157 | BF100: 25.746069 | BG100: 26.00353
A101: Отраслевые | B101: Уголь | D101: Аналитический Хаб | F101: PCI Coal Австралия, FOB | G101: $/т | I101: Добавлен 21.11.2020 | X101: 83.875 | Y101: 87.5 | Z101: 139.375 | AA101: 148.875 | AB101: 129 | AC101: 78 | AD101: 164 | AE101: 322.5634 | AF101: 221.98845 | AG101: 194.78525 | AH101: 163.94425 | AI101: 160.3233 | AJ101: 162.63196 | AK101: 164.97386 | AL101: 167.34948 | AM101: 169.75932 | AN101: 172.06804 | AO101: 174.40817 | AP101: 176.78012 | AQ101: 179.18433 | AR101: 181.62124 | AS101: 184.09128 | AT101: 186.59493 | AU101: 189.13262 | AV101: 191.70482 | AW101: 194.31201 | AX101: 196.95465 | AY101: 199.63323 | AZ101: 202.34825 | BA101: 205.10018 | BB101: 207.88954 | BC101: 210.71684 | BD101: 213.58259 | BE101: 216.48731 | BF101: 219.43154 | BG101: 222.41581
A102: Отраслевые | B102: Уголь | D102: Аналитический Хаб | F102: Энергоуголь Baltic, FOB | X102: 0 | Y102: 0 | Z102: 0 | AA102: 0 | AB102: 0 | AC102: 0 | AD102: 111.13783 | AE102: 146.95515 | AF102: 88.554232 | AG102: 85.906972 | AH102: 86.516187 | AI102: 88.583873 | AJ102: 90.625215 | AK102: 92.699219 | AL102: 94.806406 | AM102: 96.947309 | AN102: 98.850571 | AO102: 100.78048 | AP102: 102.73741 | AQ102: 104.72173 | AR102: 106.73383 | AS102: 108.77411 | AT102: 110.84294 | AU102: 112.94075 | AV102: 115.06792 | AW102: 117.22487 | AX102: 119.41202 | AY102: 121.62978 | AZ102: 123.8786 | BA102: 126.1589 | BB102: 128.47113 | BC102: 130.81572 | BD102: 133.19314 | BE102: 135.60385 | BF102: 138.0483 | BG102: 140.52698
